Workbook
Name ifw_edit_options_1478993052: #REF!
Name ifw_edit_title_1478993052: #REF!
Name ifw_edit_description_1478993052: #REF!
Name ifw_edit_urls_1_1478993052: #REF!
Name ifw_edit_selectors_1_1478993052: #REF!

Sheet Elevators
A1: Station | B1: Services | C1: Division | D1: Line | E1: ♿ / ❌ | F1: IF NOT, ARE THERE ANY OFFICAL PLANS TO DO SO? IF NOT, POSSIBLE REASONS? | G1: DATE MADE FIRST ACCESSIBLE | H1: SOURCES | I1: Opened | J1: Borough | K1: Neighborhood | L1: Ridership (2024) | M1: Rank
A2: 1 Av | B2: L | C2: BMT | D2: Canarsie Line | E2: ♿ | G2: August 6, 2020 | H2: MTA Officials Announce Opening of New Elevators at Two L Train Stations and Join Accessibility Advocates to Call for Urgently Needed Federal Funding | I2: 8948 | J2: Manhattan | K2: East Village | L2: 6266103 | M2: 35
A3: 125 St | B3: 1 | C3: IRT | D3: Broadway-7 Av Line | E3: ♿ | I3: 1762 | J3: Manhattan | K3: Manhattanville | L3: 1977586 | M3: 165
A4: 125 St | B4: A,B,C,D | C4: IND | D4: 8 Av Line | E4: ♿ | G4: 2000 | I4: 11942 | J4: Manhattan | K4: Harlem | L4: 5853749 | M4: 45
A5: 125 St | B5: 4,5,6 | C5: IRT | D5: Lexington Av Line | E5: ♿ | I5: 6773 | J5: Manhattan | K5: East Harlem | L5: 5425934 | M5: 51
A6: 135 St | B6: 2,3 | C6: IRT | D6: Lenox Av Line | E6: ♿ | I6: 1789 | J6: Manhattan | K6: Harlem | L6: 2237928 | M6: 149
A7: 14 St-Union Sq | B7: N,Q,R,W | C7: BMT | D7: Broadway Line | E7: ♿ | G7: 2000 | I7: 6457 | J7: Manhattan | K7: Union Square | L7: 22811597 | M7: 4
A8: 14 St-Union Sq | B8: L | C8: BMT | D8: Canarsie Line | E8: ♿ | G8: 2000 | I8: 8948 | J8: Manhattan | K8: Union Square | L8: 22811597 | M8: 4
A9: 14 St/6 Av | B9: F,M | C9: IND | D9: 6 Av Line | E9: ♿ | I9: 14960 | J9: Manhattan | K9: Chelsea | L9: 10463838 | M9: 19
A10: 14 St/Eighth Av | B10: L | C10: BMT | D10: Canarsie Line | E10: ♿ | I10: 11473 | J10: Manhattan | K10: Chelsea | L10: 11672402 | M10: 15
A11: 14 St/Eighth Av | B11: A,C,E | C11: IND | D11: 8 Av Line | E11: ♿ | I11: 11942 | J11: Manhattan | K11: Chelsea | L11: 11672402 | M11: 15
A12: 14 St/Sixth Av | B12: 1,2,3 | C12: IRT | D12: Broadway-7 Av Line | E12: ♿ | I12: 6757 | J12: Manhattan | K12: Chelsea | L12: 10463838 | M12: 19
A13: 14 St/Sixth Av | B13: L | C13: BMT | D13: Canarsie Line | E13: ♿ | I13: 8948 | J13: Manhattan | K13: Chelsea | L13: 10463838 | M13: 19
A14: 161 St-Yankee Stadium | B14: B, D | C14: IND | D14: Concourse Line | E14: ♿ | G14: late 2002 | I14: 12236 | J14: The Bronx | K14: Highbridge | L14: 5964943 | M14: 41
A15: 161 St-Yankee Stadium | B15: 4 | C15: IRT | D15: Jerome Av Line | E15: ♿ | G15: late 2002 | I15: 6363 | J15: The Bronx | K15: Highbridge
A16: 170 St | B16: 4 | C16: IRT | D16: Jerome Av Line | E16: ♿ | I16: 6363 | J16: The Bronx | K16: Highbridge | L16: 1396033 | M16: 228
A17: 175 St | B17: A | C17: IND | D17: 8 Av Line | E17: ♿ | G17: November 1989 (?) | I17: 11942 | J17: Manhattan | K17: Washington Heights | L17: 2284232 | M17: 142
A18: 181 St | B18: A | C18: IND | D18: 8 Av Line | E18: ♿ | I18: 11942 | J18: Manhattan | K18: Washington Heights | L18: 2042771 | M18: 160
A19: 207 St | B19: 1 | C19: IRT | D19: Broadway-7 Av Line | E19: ♿ | G19: Late 1990s | I19: 2648 | J19: Manhattan | K19: Inwood | L19: 1244261 | M19: 248
A20: 21 St-Queensbridge | B20: M | C20: IND | D20: 63rd St Line | E20: ♿ | I20: 32810 | J20: Queens | K20: Long Island City | L20: 1751180 | M20: 184
A21: 23 St-Baruch College | B21: 6 | C21: IRT | D21: Lexington Av Line | E21: ♿ | I21: 1762 | J21: Manhattan | K21: Gramercy | L21: 5594512 | M21: 48
A22: 231 St | B22: 1 | C22: IRT | D22: Broadway-7 Av Line | E22: ♿ | I22: 2584 | J22: The Bronx | K22: Kingsbridge | L22: 1780122 | M22: 180
A23: 233 St | B23: 2 | C23: IRT | D23: White Plains Rd Line | E23: ♿ | I23: 6300 | J23: The Bronx | K23: Wakefield | L23: 725758 | M23: 342
A24: 3 Av-149 St | B24: 2,5 | C24: IRT | D24: White Plains Rd Line | E24: ♿ | I24: 2018 | J24: The Bronx | K24: Mott Haven | L24: 3698741 | M24: 87
A25: 34 St-Herald Sq | B25: N,Q,R,W | C25: BMT | D25: Broadway Line | E25: ♿ | G25: 1996 | I25: 6580 | J25: Manhattan | K25: Midtown | L25: 25012549 | M25: 3
A26: 34 St-Herald Sq | B26: B,D,F,M | C26: IND | D26: 6 Av Line | E26: ♿ | G26: 1996 | I26: 14960 | J26: Manhattan | K26: Midtown | L26: 25012549 | M26: 3
A27: 34 St-Hudson Yards | B27: 7 | C27: IRT | D27: Flushing Line | E27: ♿ | I27: 42260 | J27: Manhattan | K27: Hell's Kitchen | L27: 6082370 | M27: 39
A28: 34 St-Penn Station | B28: 1,2,3 | C28: IRT | D28: Broadway-7 Av Line | E28: ♿ | G28: 1990s | I28: 6364 | J28: Manhattan | K28: Midtown | L28: 16373975 | M28: 8
A29: 34 St-Penn Station | B29: A,C,E | C29: IND | D29: 8 Av Line | E29: ♿ | G29: 1990s | I29: 11942 | J29: Manhattan | K29: Midtown | L29: 18393456 | M29: 6
A30: 42 St-Port Authority Bus Terminal | B30: A,C,E | C30: IND | D30: 8 Av Line | E30: ♿ | G30: 1990s | I30: 11942 | J30: Manhattan | K30: Midtown | L30: 57743486 | M30: 1
A31: 47-50 Sts-Rockefeller Center | B31: B,D,F,M | C31: IND | D31: 6 Av Line | E31: ♿ | G31: 1994-1996 | I31: 14960 | J31: Manhattan | K31: Midtown | L31: 12514970 | M31: 13
A32: 5 Av/53 St | B32: E,F | C32: IND | D32: Queens Blvd Line | E32: ♿ | I32: 12359 | J32: Manhattan | K32: Midtown | L32: 4590651 | M32: 64
A33: 57 St-7 Av | B33: N,Q,R,W | C33: BMT | D33: Broadway Line | E33: ♿ | G33: June 1, 2021 | H33: Midtown Manhattan's 57 St NQRW Station Now Accessible to All Riders | MTA | I33: 7131 | J33: Manhattan | K33: Midtown | L33: 8342178 | M33: 24
A34: 59 St | B34: N,R | C34: BMT | D34: 4 Av Line | E34: ♿ | G34: November 9, 2020 | H34: MTA Unveils New Fully Accessible Station in Brooklyn | I34: 5652 | J34: Brooklyn | K34: Sunset Park | L34: 2952891 | M34: 112
A35: 59 St-Columbus Circle | B35: 1 | C35: IRT | D35: Broadway-7 Av Line | E35: ♿ | G35: 2011 | I35: 1762 | J35: Manhattan | K35: Midtown | L35: 16884912 | M35: 7
A36: 59 St-Columbus Circle | B36: A,B,C,D | C36: IND | D36: 8 Av Line | E36: ♿ | G36: 2011 | I36: 11942 | J36: Manhattan | K36: Midtown | L36: 16884912 | M36: 7
A37: 61 St-Woodside | B37: 7 | C37: IRT | D37: Flushing Line | E37: ♿ | I37: 6321 | J37: Queens | K37: Woodside | L37: 3808140 | M37: 83
A38: 62 St/New Utrecht Av | B38: N | C38: BMT | D38: Sea Beach Line | E38: ♿ | G38: July 19, 2019 | H38: New Utrecht Av/62 St ADA project | The Metropolitan Transpor… | Flickr | I38: 5652 | J38: Brooklyn | K38: Borough Park | L38: 1152489 | M38: 266
A39: 62 St/New Utrecht Av | B39: D | C39: BMT | D39: West End Line | E39: ♿ | G39: July 19, 2019 | H39: New Utrecht Av/62 St ADA project | The Metropolitan Transpor… | Flickr | I39: 6020 | J39: Brooklyn | K39: Borough Park | L39: 1152489 | M39: 266
A40: 66 St-Lincoln Center | B40: 1 | C40: IRT | D40: Broadway-7 Av Line | E40: ♿ | I40: 1762 | J40: Manhattan | K40: Upper West Side | L40: 4774721 | M40: 60
A41: 68 St-Hunter College | B41: 6 | C41: IRT | D41: Lexington Av Line | E41: ♿ | I41: 6773 | J41: Manhattan | K41: Upper East Side | L41: 5278269 | M41: 52
A42: 7 Av | B42: B,Q | C42: BMT | D42: Brighton Line | E42: ♿ | I42: 7519 | J42: Brooklyn | K42: Park Slope | L42: 2176497 | M42: 154
A43: 7 Av | B43: F,G | C43: IND | D43: Culver Line | E43: ♿ | I43: 12334 | J43: Brooklyn | K43: Park Slope | L43: 2790876 | M43: 125
A44: 72 St | B44: 1,2,3 | C44: IRT | D44: Broadway-7 Av Line | E44: ♿ | I44: 1762 | J44: Manhattan | K44: Upper West Side | L44: 9752193 | M44: 22
A45: 72 St | B45: Q | C45: IND | D45: 2 Av Line | E45: ♿ | G45: January 1, 2017 | H45: Second Avenue Subway Phase 1 | I45: 42736 | J45: Manhattan | K45: Upper East Side | L45: 6995154 | M45: 28
A46: 8 Av | B46: N | C46: BMT | D46: Sea Beach Line | E46: ♿ | I46: 5652 | J46: Brooklyn | K46: Sunset Park | L46: 2632321 | M46: 134
A47: 86 St | B47: R | C47: BMT | D47: 4 Av Line | E47: ♿ | G47: July 29, 2020 | H47: MTA Announces Completion of Four ADA-Accessible Stations Coinciding with 30th Anniversary of the Americans with Disabilities Act | I47: 5859 | J47: Brooklyn | K47: Bay Ridge | L47: 2580130 | M47: 135
A48: 86 St | B48: Q | C48: IND | D48: 2 Av Line | E48: ♿ | G48: January 1, 2017 | H48: Second Avenue Subway Phase 1 | I48: 42736 | J48: Manhattan | K48: Upper East Side | L48: 5719486 | M48: 46
A49: 96 St | B49: 1,2,3 | C49: IRT | D49: Broadway-7 Av Line | E49: ♿ | I49: 1762 | J49: Manhattan | K49: Upper West Side | L49: 8250940 | M49: 26
A50: 96 St | B50: 6 | C50: IRT | D50: Lexington Av Line | E50: ♿ | I50: 6773 | J50: Manhattan | K50: East Harlem | L50: 3844627 | M50: 81
A51: 96 St | B51: Q | C51: IND | D51: 2 Av Line | E51: ♿ | G51: January 1, 2017 | H51: Second Avenue Subway Phase 1 | I51: 42736 | J51: Manhattan | K51: Upper East Side | L51: 3995561 | M51: 79
A52: Aqueduct Racetrack | B52: A | C52: IND | D52: Rockaway Line | E52: ♿ | G52: August 13, 2013 | H52: Aqueduct Raceway Station Opens On the A Line | WFUV | I52: 21807 | J52: Queens | K52: Ozone Park | L52: 171518 | M52: 416
A53: Arthur Kill | B53: SIR | C53: SIR | D53: Staten Island Railway | E53: ♿ | I53: 42756 | J53: Staten Island | K53: Tottenville
A54: Astoria Blvd | B54: N,W | C54: BMT | D54: Astoria Line | E54: ♿ | G54: July 27, 2020 | H54: MTA Announces Completion of Four ADA-Accessible Stations Coinciding with 30th Anniversary of the Americans with Disabilities Act | I54: 6242 | J54: Queens | K54: Astoria | L54: 2470238 | M54: 139
A55: Atlantic Av-Barclays Center | B55: B,Q | C55: BMT | D55: Brighton Line | E55: ♿ | G55: Late 2004 | I55: 7519 | J55: Brooklyn | K55: Downtown Brooklyn | L55: 10108995 | M55: 20
A56: Atlantic Av-Barclays Center | B56: 2,3,4,5 | C56: IRT | D56: Eastern Pkwy Line | E56: ♿ | G56: Late 2004 | I56: 3044 | J56: Brooklyn | K56: Downtown Brooklyn | L56: 10108995 | M56: 20
A57: Atlantic Av-Barclays Center | B57: D,N,R | C57: BMT | D57: 4 Av Line | E57: ♿ | G57: Late 2004 | I57: 5652 | J57: Brooklyn | K57: Downtown Brooklyn | L57: 10108995 | M57: 20
A58: Av H | B58: Q | C58: BMT | D58: Brighton Line | E58: ♿ | I58: 2792 | J58: Brooklyn | K58: Midwood | L58: 676816 | M58: 349
A59: Bay Pkwy | B59: D | C59: BMT | D59: West End Line | E59: ♿ | G59: August 3, 2012 | H59: MTA completes seven station rehabilitation projects along D Line - Railway Track and Structures | I59: 6055 | J59: Brooklyn | K59: Bensonhurst | L59: 1691045 | M59: 195
A60: Bay Ridge-95 St | B60: R | C60: BMT | D60: 4 Av Line | E60: ♿ | G60: July 8, 2025 | H60: MTA Announces Two Elevators Open at Accessible Bay Ridge-95 St R Station | I60: 9436 | J60: Brooklyn | K60: Bay Ridge | L60: 1201642 | M60: 255
A61: Beach 67 St | B61: A | C61: IND | D61: Rockaway Line | E61: ♿ | G61: January 19, 2024 | H61: MTA Announces Beach 67 St A Station in Queens Now Fully Accessible | I61: 20634 | J61: Queens | K61: Arverne | L61: 473215 | M61: 389
A62: Bedford Av | B62: L | C62: BMT | D62: Canarsie Line | E62: ♿ | G62: August 6, 2020 | H62: MTA Officials Announce Opening of New Elevators at Two L Train Stations and Join Accessibility Advocates to Call for Urgently Needed Federal Funding | I62: 8948 | J62: Brooklyn | K62: Williamsburg | L62: 8764921 | M62: 23
A63: Bedford Park Blvd | B63: D | C63: IND | D63: Concourse Line | E63: ♿ | G63: October 15, 2020 | H63: MTA Announces Newly Accessible Bedford Park Blvd B/D Station in The Bronx | I63: 12236 | J63: The Bronx | K63: Bedford Park | L63: 1159574 | M63: 263
A64: Borough Hall/Court St | B64: 2,3 | C64: IRT | D64: Broadway-7 Av Line | E64: ♿ | G64: December 5, 2025 | H64: New ADA-Accessible Elevators and FULL ADA Accessibility at Borough Hall 4/5 Station #shorts - YouTube | I64: 7045 | J64: Brooklyn | K64: Downtown Brooklyn | L64: 6188561 | M64: 36
A65: Borough Hall/Court St | B65: 4,5 | C65: IRT | D65: Eastern Pkwy Line | E65: ♿ | I65: 2931 | J65: Brooklyn | K65: Downtown Brooklyn | L65: 6188561 | M65: 36
A66: Bowling Green | B66: 4,5 | C66: IRT | D66: Lexington Av Line | E66: ♿ | I66: 2018 | J66: Manhattan | K66: Financial District | L66: 4676646 | M66: 62
A67: Broadway-Lafayette St/Bleecker St | B67: 6 | C67: IRT | D67: Lexington Av Line | E67: ♿ | G67: September 25, 2012 | H67: NYCT_2190 | MTA Chairman & CEO Joseph J. Lhota and New York … | Flickr | I67: 1762 | J67: Manhattan | K67: Greenwich Village | L67: 9991286 | M67: 21
A68: Broadway-Lafayette St/Bleecker St | B68: B,D,F,M | C68: IND | D68: 6 Av Line | E68: ♿ | G68: September 25, 2012 | H68: NYCT_2190 | MTA Chairman & CEO Joseph J. Lhota and New York … | Flickr | I68: 13150 | J68: Manhattan | K68: Greenwich Village | L68: 9991286 | M68: 21
A69: Brooklyn Bridge-City Hall/Chambers St | B69: 4,5,6 | C69: IRT | D69: Lexington Av Line | E69: ♿ | I69: 1762 | J69: Manhattan | K69: Civic Center | L69: 5911226 | M69: 43
A70: Brooklyn Bridge-City Hall/Chambers St | B70: J | C70: BMT | D70: Nassau St Line | E70: ♿ | I70: 4965 | J70: Manhattan | K70: Civic Center | L70: 5911226 | M70: 43
A71: Canal St | B71: 6 | C71: IRT | D71: Lexington Av Line | E71: ♿ | I71: 1762 | J71: Manhattan | K71: Chinatown | L71: 11048920 | M71: 17
A72: Canarsie-Rockaway Pkwy | B72: L | C72: BMT | D72: Canarsie Line | E72: ♿ | I72: 2401 | J72: Brooklyn | K72: Canarsie | L72: 669667 | M72: 352
A73: Chambers St | B73: 1,2,3 | C73: IRT | D73: Broadway-7 Av Line | E73: ♿ | I73: 6757 | J73: Manhattan | K73: Financial District | L73: 3952229 | M73: 80
A74: Chambers St-World Trade Center/Park Place/Cortlandt St | B74: R,W | C74: BMT | D74: Broadway Line | E74: ♿ | G74: August 20, 2005 | I74: 6580 | J74: Manhattan | K74: Financial District | L74: 13399327 | M74: 11
A75: Chambers St-World Trade Center/Park Place/Cortlandt St | B75: 2,3 | C75: IRT | D75: Broadway-7 Av Line | E75: ♿ | G75: August 20, 2005 | I75: 6757 | J75: Manhattan | K75: Financial District | L75: 13399327 | M75: 11
A76: Chambers St-World Trade Center/Park Place/Cortlandt St | B76: A,C | C76: IND | D76: 8 Av Line | E76: ♿ | G76: August 20, 2005 | I76: 11942 | J76: Manhattan | K76: Financial District | L76: 13399327 | M76: 11
A77: Chambers St-World Trade Center/Park Place/Cortlandt St | B77: E | C77: IND | D77: 8 Av Line | E77: ♿ | G77: August 20, 2005 | I77: 11942 | J77: Manhattan | K77: Financial District | L77: 13399327 | M77: 11
A78: Church Av | B78: B,Q | C78: BMT | D78: Brighton Line | E78: ♿ | I78: 2792 | J78: Brooklyn | K78: Flatbush | L78: 2819621 | M78: 123
A79: Church Av | B79: F,G | C79: IND | D79: Culver Line | E79: ♿ | I79: 12334 | J79: Brooklyn | K79: Kensington | L79: 2029121 | M79: 161
A80: Church Av | B80: 2,5 | C80: IRT | D80: Nostrand Av Line | E80: ♿ | I80: 7541 | J80: Brooklyn | K80: East Flatbush | L80: 1880019 | M80: 173
A81: Coney Island-Stillwell Av | B81: D,F,N,Q | C81: BMT, IND | D81: Brighton Line, Culver Line,Sea Beach Line, West End Line | E81: ♿ | G81: May 1, 2005 | I81: 6458 | J81: Brooklyn | K81: Coney Island | L81: 3254148 | M81: 98
A82: Court Sq-23 St | B82: G | C82: IND | D82: Crosstown Line | E82: ♿ | I82: 12285 | J82: Queens | K82: Long Island City | L82: 6032857 | M82: 40
A83: Court Sq-23 St | B83: 7 | C83: IRT | D83: Flushing Line | E83: ♿ | I83: 6154 | J83: Queens | K83: Long Island City | L83: 6032857 | M83: 40
A84: Crown Heights-Utica Av | B84: 46085 | C84: IRT | D84: Eastern Pkwy Line | E84: ♿ | G84: May 24, 2014 | I84: 7541 | J84: Brooklyn | K84: Crown Heights | L84: 5144720 | M84: 55
A85: DeKalb Av | B85: L | C85: BMT | D85: Canarsie Line | E85: ♿ | G85: 2006 | I85: 10423 | J85: Brooklyn | K85: Bushwick | L85: 2931695 | M85: 113
A86: DeKalb Av | B86: B, Q, R | C86: BMT | D86: 4 Av Line,Brighton Line | E86: ♿ | G86: 2006 | I86: 5652 | J86: Brooklyn | K86: Downtown | L86: 4955471 | M86: 58
A87: Dongan Hills | B87: SIR | C87: SIR | D87: Staten Island Railway | E87: ♿ | I87: April 23, 1860 | J87: Staten Island | K87: Dongan Hills
A88: Dyckman St | B88: 1 | C88: IRT | D88: Broadway-7 Av Line | E88: ♿ | I88: 2263 | J88: Manhattan | K88: Inwood | L88: 1462682 | M88: 217
A89: East 149 St | B89: 6 | C89: IRT | D89: Pelham Line | E89: ♿ | I89: 6947 | J89: The Bronx | K89: Longwood | L89: 935029 | M89: 307
A90: East 180 St | B90: 46058 | C90: IRT | D90: White Plains Rd Line | E90: ♿ | I90: 6272 | J90: The Bronx | K90: Van Nest | L90: 1694993 | M90: 194
A91: Eastern Pkwy-Brooklyn Museum | B91: 46056 | C91: IRT | D91: Eastern Pkwy Line | E91: ♿ | I91: 7589 | J91: Brooklyn | K91: Prospect Heights | L91: 1168932 | M91: 261
A92: Euclid Av | B92: A, C | C92: IND | D92: Fulton St Line | E92: ♿ | G92: March 2006 | H92: https://web.archive.org/web/20060409080402/http://mta.info/nyct/maps/subwaymap.pdf | I92: 17865 | J92: Brooklyn | K92: East New York | L92: 2166608 | M92: 155
A93: Far Rockaway-Mott Av | B93: A | C93: IND | D93: Rockaway Line | E93: ♿ | G93: May 11, 2012 | I93: 21201 | J93: Queens | K93: Far Rockaway | L93: 961694 | M93: 302
A94: Flatbush Av-Brooklyn College | B94: 46058 | C94: IRT | D94: Nostrand Av Line | E94: ♿ | I94: 7541 | J94: Brooklyn | K94: Flatbush | L94: 3662300 | M94: 88
A95: Flushing Av | B95: J, M | C95: BMT | D95: Jamaica Line | E95: ♿ | I95: June 25, 1888 | J95: Brooklyn | K95: Williamsburg | L95: 1658300 | M95: 200
A96: Flushing-Main St | B96: 7 | C96: IRT | D96: Flushing Line | E96: ♿ | I96: 10248 | J96: Queens | K96: Flushing | L96: 14592853 | M96: 10
A97: Fordham Rd | B97: 4 | C97: IRT | D97: Jerome Av Line | E97: ♿ | I97: 6363 | J97: The Bronx | K97: University Heights | L97: 1885625 | M97: 172
A98: Forest Hills-71 Av | B98: E, F, M, R | C98: IND | D98: Queens Blvd Line | E98: ♿ | I98: 13515 | J98: Queens | K98: Forest Hills | L98: 5697461 | M98: 47
A99: Franklin Av | B99: SF | C99: BMT | D99: Franklin Av Line | E99: ♿ | G99: October 17, 1999 | I99: August 15, 1896 | J99: Brooklyn | K99: Bedford-Stuyvesant | L99: 1288429 | M99: 244
A100: Franklin Av | B100: A, C | C100: IND | D100: Fulton St Line | E100: ♿ | G100: October 17, 1999 | I100: 13249 | J100: Brooklyn | K100: Bedford-Stuyvesant | L100: 1288429 | M100: 244
...

Sheet Escalators
A1: Station | B1: Line | C1: Borough | D1: Neighborhood | E1: Opened | F1: Ridership (2024) | G1: Rank | H1: ↗️ / ❌ | I1: Original Installation Date | J1: Latest Installation Date | K1: Service Life | L1: NYCT Owned | M1: Maintained By | N1: Installer | O1: Revenue Machine | P1: Street Access | Q1: Exposed to Weather | R1: Escalator Rise | S1: Escalator Number of Steps | T1: Escalator Step Width | U1: Notes | V1: Georeference
A2: =IFERROR(__xludf.DUMMYFUNCTION("FILTER(ARRAYFORMULA({SUBSTITUTE(Sheet5!D2:D1494, "" - Station"", """"), IFERROR(VLOOKUP(SUBSTITUTE(Sheet5!D2:D1494, "" - Station"", """"), Elevators!A:M, 4, FALSE), """"), IFERROR(VLOOKUP(SUBSTITUTE(Sheet5!D2:D1494, "" - Station"", """"), Elevators!A:M, 1"&"0, FALSE), """"), IFERROR(VLOOKUP(SUBSTITUTE(Sheet5!D2:D1494, "" - Station"", """"), Elevators!A:M, 11, FALSE), """"), IFERROR(VLOOKUP(SUBSTITUTE(Sheet5!D2:D1494, "" - Station"", """"), Elevators!A:M, 9, FALSE), """"), IFERROR(VLOOKUP(SUBSTITUTE(Sheet5!D2"&":D1494, "" - Station"", """"), Elevators!A:M, 12, FALSE), """"), IFERROR(VLOOKUP(SUBSTITUTE(Sheet5!D2:D1494, "" - Station"", """"), Elevators!A:M, 13, FALSE), """"), IF(Sheet5!L2:L1494=""Removed-Non Functioning-Out of Service"", ""❌"", ""↗️""), Sheet5!I2:"&"I1494, Sheet5!J2:J1494, Sheet5!M2:M1494, Sheet5!N2:N1494, Sheet5!O2:O1494, Sheet5!P2:P1494, Sheet5!Q2:Q1494, Sheet5!S2:S1494, Sheet5!T2:T1494, Sheet5!U2:U1494, Sheet5!Z2:Z1494, Sheet5!AA2:AA1494, Sheet5!AG2:AG1494, Sheet5!AN2:AN1494}), Sheet5!B2:B1494=""E"&"scalator"")"),"Lexington Av/53 St") -> Lexington Av/53 St | B2: =IFERROR(__xludf.DUMMYFUNCTION("""COMPUTED_VALUE"""),"") | C2: =IFERROR(__xludf.DUMMYFUNCTION("""COMPUTED_VALUE"""),"") | D2: =IFERROR(__xludf.DUMMYFUNCTION("""COMPUTED_VALUE"""),"") | E2: =IFERROR(__xludf.DUMMYFUNCTION("""COMPUTED_VALUE"""),"") | F2: =IFERROR(__xludf.DUMMYFUNCTION("""COMPUTED_VALUE"""),"") | G2: =IFERROR(__xludf.DUMMYFUNCTION("""COMPUTED_VALUE"""),"") | H2: =IFERROR(__xludf.DUMMYFUNCTION("""COMPUTED_VALUE"""),"↗️") -> ↗️ | J2: =IFERROR(__xludf.DUMMYFUNCTION("""COMPUTED_VALUE"""),3.0) -> 3 | K2: =IFERROR(__xludf.DUMMYFUNCTION("""COMPUTED_VALUE"""),22.0) -> 22 | L2: =IFERROR(__xludf.DUMMYFUNCTION("""COMPUTED_VALUE"""),"NO") -> NO | M2: =IFERROR(__xludf.DUMMYFUNCTION("""COMPUTED_VALUE"""),"Private Contractor") -> Private Contractor | N2: =IFERROR(__xludf.DUMMYFUNCTION("""COMPUTED_VALUE"""),"AM") -> AM | O2: =IFERROR(__xludf.DUMMYFUNCTION("""COMPUTED_VALUE"""),"YES") -> YES | P2: =IFERROR(__xludf.DUMMYFUNCTION("""COMPUTED_VALUE"""),"NO") -> NO | Q2: =IFERROR(__xludf.DUMMYFUNCTION("""COMPUTED_VALUE"""),"NO") -> NO | U2: =IFERROR(__xludf.DUMMYFUNCTION("""COMPUTED_VALUE"""),"6/E/F mezzanine to 52 St & Lexington Av (NE corner).") -> 6/E/F mezzanine to 52 St & Lexington Av (NE corner). | V2: =IFERROR(__xludf.DUMMYFUNCTION("""COMPUTED_VALUE"""),"POINT (-73.970924 40.75814)") -> POINT (-73.970924 40.75814)
A3: =IFERROR(__xludf.DUMMYFUNCTION("""COMPUTED_VALUE"""),"34 St-Hudson Yards") -> 34 St-Hudson Yards | B3: =IFERROR(__xludf.DUMMYFUNCTION("""COMPUTED_VALUE"""),"Flushing Line") -> Flushing Line | C3: =IFERROR(__xludf.DUMMYFUNCTION("""COMPUTED_VALUE"""),"Manhattan") -> Manhattan | D3: =IFERROR(__xludf.DUMMYFUNCTION("""COMPUTED_VALUE"""),"Hell's Kitchen") -> Hell's Kitchen | E3: =IFERROR(__xludf.DUMMYFUNCTION("""COMPUTED_VALUE"""),42260.0) -> 42260 | F3: =IFERROR(__xludf.DUMMYFUNCTION("""COMPUTED_VALUE"""),6082370.0) -> 6082370 | G3: =IFERROR(__xludf.DUMMYFUNCTION("""COMPUTED_VALUE"""),39.0) -> 39 | H3: =IFERROR(__xludf.DUMMYFUNCTION("""COMPUTED_VALUE"""),"↗️") -> ↗️ | I3: =IFERROR(__xludf.DUMMYFUNCTION("""COMPUTED_VALUE"""),42260.0) -> 42260 | J3: =IFERROR(__xludf.DUMMYFUNCTION("""COMPUTED_VALUE"""),42260.0) -> 42260 | K3: =IFERROR(__xludf.DUMMYFUNCTION("""COMPUTED_VALUE"""),22.0) -> 22 | L3: =IFERROR(__xludf.DUMMYFUNCTION("""COMPUTED_VALUE"""),"YES") -> YES | M3: =IFERROR(__xludf.DUMMYFUNCTION("""COMPUTED_VALUE"""),"NYCT") -> NYCT | N3: =IFERROR(__xludf.DUMMYFUNCTION("""COMPUTED_VALUE"""),"KONE") -> KONE | O3: =IFERROR(__xludf.DUMMYFUNCTION("""COMPUTED_VALUE"""),"YES") -> YES | P3: =IFERROR(__xludf.DUMMYFUNCTION("""COMPUTED_VALUE"""),"YES") -> YES | Q3: =IFERROR(__xludf.DUMMYFUNCTION("""COMPUTED_VALUE"""),"YES") -> YES | R3: =IFERROR(__xludf.DUMMYFUNCTION("""COMPUTED_VALUE"""),"30'") -> 30' | S3: =IFERROR(__xludf.DUMMYFUNCTION("""COMPUTED_VALUE"""),110.0) -> 110 | T3: =IFERROR(__xludf.DUMMYFUNCTION("""COMPUTED_VALUE"""),24.0) -> 24 | U3: =IFERROR(__xludf.DUMMYFUNCTION("""COMPUTED_VALUE"""),"Hudson Blvd E (between 33 St & 34 St) to upper mezzanine") -> Hudson Blvd E (between 33 St & 34 St) to upper mezzanine | V3: =IFERROR(__xludf.DUMMYFUNCTION("""COMPUTED_VALUE"""),"POINT (-74.00103 40.754982)") -> POINT (-74.00103 40.754982)
A4: =IFERROR(__xludf.DUMMYFUNCTION("""COMPUTED_VALUE"""),"Fulton St") -> Fulton St | B4: =IFERROR(__xludf.DUMMYFUNCTION("""COMPUTED_VALUE"""),"Broadway-7 Av Line") -> Broadway-7 Av Line | C4: =IFERROR(__xludf.DUMMYFUNCTION("""COMPUTED_VALUE"""),"Manhattan") -> Manhattan | D4: =IFERROR(__xludf.DUMMYFUNCTION("""COMPUTED_VALUE"""),"Financial District") -> Financial District | E4: =IFERROR(__xludf.DUMMYFUNCTION("""COMPUTED_VALUE"""),6757.0) -> 6757 | F4: =IFERROR(__xludf.DUMMYFUNCTION("""COMPUTED_VALUE"""),1.9221396E7) -> 19221396 | G4: =IFERROR(__xludf.DUMMYFUNCTION("""COMPUTED_VALUE"""),5.0) -> 5 | H4: =IFERROR(__xludf.DUMMYFUNCTION("""COMPUTED_VALUE"""),"↗️") -> ↗️ | J4: =IFERROR(__xludf.DUMMYFUNCTION("""COMPUTED_VALUE"""),41110.0) -> 41110 | K4: =IFERROR(__xludf.DUMMYFUNCTION("""COMPUTED_VALUE"""),22.0) -> 22 | L4: =IFERROR(__xludf.DUMMYFUNCTION("""COMPUTED_VALUE"""),"NO") -> NO | M4: =IFERROR(__xludf.DUMMYFUNCTION("""COMPUTED_VALUE"""),"Private Contractor") -> Private Contractor | N4: =IFERROR(__xludf.DUMMYFUNCTION("""COMPUTED_VALUE"""),"OTIS") -> OTIS | O4: =IFERROR(__xludf.DUMMYFUNCTION("""COMPUTED_VALUE"""),"YES") -> YES | P4: =IFERROR(__xludf.DUMMYFUNCTION("""COMPUTED_VALUE"""),"NO") -> NO | Q4: =IFERROR(__xludf.DUMMYFUNCTION("""COMPUTED_VALUE"""),"NO") -> NO | U4: =IFERROR(__xludf.DUMMYFUNCTION("""COMPUTED_VALUE"""),"Broad St-bound J/Z platform to Nassau St (between Maiden Lane & John St)") -> Broad St-bound J/Z platform to Nassau St (between Maiden Lane & John St) | V4: =IFERROR(__xludf.DUMMYFUNCTION("""COMPUTED_VALUE"""),"POINT (-74.008354 40.70928)") -> POINT (-74.008354 40.70928)
A5: =IFERROR(__xludf.DUMMYFUNCTION("""COMPUTED_VALUE"""),"96 St") -> 96 St | B5: =IFERROR(__xludf.DUMMYFUNCTION("""COMPUTED_VALUE"""),"Broadway-7 Av Line") -> Broadway-7 Av Line | C5: =IFERROR(__xludf.DUMMYFUNCTION("""COMPUTED_VALUE"""),"Manhattan") -> Manhattan | D5: =IFERROR(__xludf.DUMMYFUNCTION("""COMPUTED_VALUE"""),"Upper West Side") -> Upper West Side | E5: =IFERROR(__xludf.DUMMYFUNCTION("""COMPUTED_VALUE"""),1762.0) -> 1762 | F5: =IFERROR(__xludf.DUMMYFUNCTION("""COMPUTED_VALUE"""),8250940.0) -> 8250940 | G5: =IFERROR(__xludf.DUMMYFUNCTION("""COMPUTED_VALUE"""),26.0) -> 26 | H5: =IFERROR(__xludf.DUMMYFUNCTION("""COMPUTED_VALUE"""),"↗️") -> ↗️ | I5: =IFERROR(__xludf.DUMMYFUNCTION("""COMPUTED_VALUE"""),42736.0) -> 42736 | J5: =IFERROR(__xludf.DUMMYFUNCTION("""COMPUTED_VALUE"""),42736.0) -> 42736 | K5: =IFERROR(__xludf.DUMMYFUNCTION("""COMPUTED_VALUE"""),22.0) -> 22 | L5: =IFERROR(__xludf.DUMMYFUNCTION("""COMPUTED_VALUE"""),"YES") -> YES | M5: =IFERROR(__xludf.DUMMYFUNCTION("""COMPUTED_VALUE"""),"NYCT") -> NYCT | N5: =IFERROR(__xludf.DUMMYFUNCTION("""COMPUTED_VALUE"""),"KONE") -> KONE | O5: =IFERROR(__xludf.DUMMYFUNCTION("""COMPUTED_VALUE"""),"YES") -> YES | P5: =IFERROR(__xludf.DUMMYFUNCTION("""COMPUTED_VALUE"""),"NO") -> NO | Q5: =IFERROR(__xludf.DUMMYFUNCTION("""COMPUTED_VALUE"""),"NO") -> NO | R5: =IFERROR(__xludf.DUMMYFUNCTION("""COMPUTED_VALUE"""),"5042mm (16' 6 1/2in)") -> 5042mm (16' 6 1/2in) | S5: =IFERROR(__xludf.DUMMYFUNCTION("""COMPUTED_VALUE"""),76.0) -> 76 | T5: =IFERROR(__xludf.DUMMYFUNCTION("""COMPUTED_VALUE"""),"1000 mm (39 3/8in)") -> 1000 mm (39 3/8in) | U5: =IFERROR(__xludf.DUMMYFUNCTION("""COMPUTED_VALUE"""),"platform to mezzanine") -> platform to mezzanine | V5: =IFERROR(__xludf.DUMMYFUNCTION("""COMPUTED_VALUE"""),"POINT (-73.94761 40.783447)") -> POINT (-73.94761 40.783447)
A6: =IFERROR(__xludf.DUMMYFUNCTION("""COMPUTED_VALUE"""),"Roosevelt Island") -> Roosevelt Island | B6: =IFERROR(__xludf.DUMMYFUNCTION("""COMPUTED_VALUE"""),"63rd St Line") -> 63rd St Line | C6: =IFERROR(__xludf.DUMMYFUNCTION("""COMPUTED_VALUE"""),"Manhattan") -> Manhattan | D6: =IFERROR(__xludf.DUMMYFUNCTION("""COMPUTED_VALUE"""),"Roosevelt Island") -> Roosevelt Island | E6: =IFERROR(__xludf.DUMMYFUNCTION("""COMPUTED_VALUE"""),32810.0) -> 32810 | F6: =IFERROR(__xludf.DUMMYFUNCTION("""COMPUTED_VALUE"""),1885823.0) -> 1885823 | G6: =IFERROR(__xludf.DUMMYFUNCTION("""COMPUTED_VALUE"""),171.0) -> 171 | H6: =IFERROR(__xludf.DUMMYFUNCTION("""COMPUTED_VALUE"""),"↗️") -> ↗️ | I6: =IFERROR(__xludf.DUMMYFUNCTION("""COMPUTED_VALUE"""),32782.0) -> 32782 | J6: =IFERROR(__xludf.DUMMYFUNCTION("""COMPUTED_VALUE"""),39405.0) -> 39405 | K6: =IFERROR(__xludf.DUMMYFUNCTION("""COMPUTED_VALUE"""),22.0) -> 22 | L6: =IFERROR(__xludf.DUMMYFUNCTION("""COMPUTED_VALUE"""),"YES") -> YES | M6: =IFERROR(__xludf.DUMMYFUNCTION("""COMPUTED_VALUE"""),"NYCT") -> NYCT | N6: =IFERROR(__xludf.DUMMYFUNCTION("""COMPUTED_VALUE"""),"KONE") -> KONE | O6: =IFERROR(__xludf.DUMMYFUNCTION("""COMPUTED_VALUE"""),"YES") -> YES | P6: =IFERROR(__xludf.DUMMYFUNCTION("""COMPUTED_VALUE"""),"NO") -> NO | Q6: =IFERROR(__xludf.DUMMYFUNCTION("""COMPUTED_VALUE"""),"NO") -> NO | R6: =IFERROR(__xludf.DUMMYFUNCTION("""COMPUTED_VALUE"""),"36'") -> 36' | S6: =IFERROR(__xludf.DUMMYFUNCTION("""COMPUTED_VALUE"""),129.0) -> 129 | T6: =IFERROR(__xludf.DUMMYFUNCTION("""COMPUTED_VALUE"""),40.0) -> 40 | U6: =IFERROR(__xludf.DUMMYFUNCTION("""COMPUTED_VALUE"""),"intermediate mezzanine to lower mezzanine") -> intermediate mezzanine to lower mezzanine | V6: =IFERROR(__xludf.DUMMYFUNCTION("""COMPUTED_VALUE"""),"POINT (-73.952866 40.7589)") -> POINT (-73.952866 40.7589)
A7: =IFERROR(__xludf.DUMMYFUNCTION("""COMPUTED_VALUE"""),"Bowling Green") -> Bowling Green | B7: =IFERROR(__xludf.DUMMYFUNCTION("""COMPUTED_VALUE"""),"Lexington Av Line") -> Lexington Av Line | C7: =IFERROR(__xludf.DUMMYFUNCTION("""COMPUTED_VALUE"""),"Manhattan") -> Manhattan | D7: =IFERROR(__xludf.DUMMYFUNCTION("""COMPUTED_VALUE"""),"Financial District") -> Financial District | E7: =IFERROR(__xludf.DUMMYFUNCTION("""COMPUTED_VALUE"""),2018.0) -> 2018 | F7: =IFERROR(__xludf.DUMMYFUNCTION("""COMPUTED_VALUE"""),4676646.0) -> 4676646 | G7: =IFERROR(__xludf.DUMMYFUNCTION("""COMPUTED_VALUE"""),62.0) -> 62 | H7: =IFERROR(__xludf.DUMMYFUNCTION("""COMPUTED_VALUE"""),"↗️") -> ↗️ | I7: =IFERROR(__xludf.DUMMYFUNCTION("""COMPUTED_VALUE"""),28216.0) -> 28216 | J7: =IFERROR(__xludf.DUMMYFUNCTION("""COMPUTED_VALUE"""),38062.0) -> 38062 | K7: =IFERROR(__xludf.DUMMYFUNCTION("""COMPUTED_VALUE"""),22.0) -> 22 | L7: =IFERROR(__xludf.DUMMYFUNCTION("""COMPUTED_VALUE"""),"YES") -> YES | M7: =IFERROR(__xludf.DUMMYFUNCTION("""COMPUTED_VALUE"""),"NYCT") -> NYCT | N7: =IFERROR(__xludf.DUMMYFUNCTION("""COMPUTED_VALUE"""),"FUJITEC") -> FUJITEC | O7: =IFERROR(__xludf.DUMMYFUNCTION("""COMPUTED_VALUE"""),"YES") -> YES | P7: =IFERROR(__xludf.DUMMYFUNCTION("""COMPUTED_VALUE"""),"NO") -> NO | Q7: =IFERROR(__xludf.DUMMYFUNCTION("""COMPUTED_VALUE"""),"NO") -> NO | R7: =IFERROR(__xludf.DUMMYFUNCTION("""COMPUTED_VALUE"""),"20'") -> 20' | S7: =IFERROR(__xludf.DUMMYFUNCTION("""COMPUTED_VALUE"""),80.0) -> 80 | T7: =IFERROR(__xludf.DUMMYFUNCTION("""COMPUTED_VALUE"""),40.0) -> 40 | U7: =IFERROR(__xludf.DUMMYFUNCTION("""COMPUTED_VALUE"""),"lower mezzanine to upper mezzanine for Battery Pl & Broadway exit") -> lower mezzanine to upper mezzanine for Battery Pl & Broadway exit | V7: =IFERROR(__xludf.DUMMYFUNCTION("""COMPUTED_VALUE"""),"POINT (-74.01438 40.70474)") -> POINT (-74.01438 40.70474)
A8: =IFERROR(__xludf.DUMMYFUNCTION("""COMPUTED_VALUE"""),"Times Sq-42 St") -> Times Sq-42 St | B8: =IFERROR(__xludf.DUMMYFUNCTION("""COMPUTED_VALUE"""),"42nd St Line") -> 42nd St Line | C8: =IFERROR(__xludf.DUMMYFUNCTION("""COMPUTED_VALUE"""),"Manhattan") -> Manhattan | D8: =IFERROR(__xludf.DUMMYFUNCTION("""COMPUTED_VALUE"""),"Times Square") -> Times Square | E8: =IFERROR(__xludf.DUMMYFUNCTION("""COMPUTED_VALUE"""),1762.0) -> 1762 | F8: =IFERROR(__xludf.DUMMYFUNCTION("""COMPUTED_VALUE"""),5.7743486E7) -> 57743486 | G8: =IFERROR(__xludf.DUMMYFUNCTION("""COMPUTED_VALUE"""),1.0) -> 1 | H8: =IFERROR(__xludf.DUMMYFUNCTION("""COMPUTED_VALUE"""),"↗️") -> ↗️ | I8: =IFERROR(__xludf.DUMMYFUNCTION("""COMPUTED_VALUE"""),9935.0) -> 9935 | J8: =IFERROR(__xludf.DUMMYFUNCTION("""COMPUTED_VALUE"""),38934.0) -> 38934 | K8: =IFERROR(__xludf.DUMMYFUNCTION("""COMPUTED_VALUE"""),22.0) -> 22 | L8: =IFERROR(__xludf.DUMMYFUNCTION("""COMPUTED_VALUE"""),"YES") -> YES | M8: =IFERROR(__xludf.DUMMYFUNCTION("""COMPUTED_VALUE"""),"NYCT") -> NYCT | N8: =IFERROR(__xludf.DUMMYFUNCTION("""COMPUTED_VALUE"""),"KONE") -> KONE | O8: =IFERROR(__xludf.DUMMYFUNCTION("""COMPUTED_VALUE"""),"YES") -> YES | P8: =IFERROR(__xludf.DUMMYFUNCTION("""COMPUTED_VALUE"""),"NO") -> NO | Q8: =IFERROR(__xludf.DUMMYFUNCTION("""COMPUTED_VALUE"""),"NO") -> NO | R8: =IFERROR(__xludf.DUMMYFUNCTION("""COMPUTED_VALUE"""),"37'") -> 37' | S8: =IFERROR(__xludf.DUMMYFUNCTION("""COMPUTED_VALUE"""),134.0) -> 134 | T8: =IFERROR(__xludf.DUMMYFUNCTION("""COMPUTED_VALUE"""),40.0) -> 40 | U8: =IFERROR(__xludf.DUMMYFUNCTION("""COMPUTED_VALUE"""),"upper mezzanine (41 St & 7 Ave) to 7 platform for service in both directions") -> upper mezzanine (41 St & 7 Ave) to 7 platform for service in both directions | V8: =IFERROR(__xludf.DUMMYFUNCTION("""COMPUTED_VALUE"""),"POINT (-73.98772 40.755516)") -> POINT (-73.98772 40.755516)
A9: =IFERROR(__xludf.DUMMYFUNCTION("""COMPUTED_VALUE"""),"34 St-Herald Sq") -> 34 St-Herald Sq | B9: =IFERROR(__xludf.DUMMYFUNCTION("""COMPUTED_VALUE"""),"Broadway Line") -> Broadway Line | C9: =IFERROR(__xludf.DUMMYFUNCTION("""COMPUTED_VALUE"""),"Manhattan") -> Manhattan | D9: =IFERROR(__xludf.DUMMYFUNCTION("""COMPUTED_VALUE"""),"Midtown") -> Midtown | E9: =IFERROR(__xludf.DUMMYFUNCTION("""COMPUTED_VALUE"""),6580.0) -> 6580 | F9: =IFERROR(__xludf.DUMMYFUNCTION("""COMPUTED_VALUE"""),2.5012549E7) -> 25012549 | G9: =IFERROR(__xludf.DUMMYFUNCTION("""COMPUTED_VALUE"""),3.0) -> 3 | H9: =IFERROR(__xludf.DUMMYFUNCTION("""COMPUTED_VALUE"""),"↗️") -> ↗️ | I9: =IFERROR(__xludf.DUMMYFUNCTION("""COMPUTED_VALUE"""),14960.0) -> 14960 | J9: =IFERROR(__xludf.DUMMYFUNCTION("""COMPUTED_VALUE"""),39044.0) -> 39044 | K9: =IFERROR(__xludf.DUMMYFUNCTION("""COMPUTED_VALUE"""),22.0) -> 22 | L9: =IFERROR(__xludf.DUMMYFUNCTION("""COMPUTED_VALUE"""),"YES") -> YES | M9: =IFERROR(__xludf.DUMMYFUNCTION("""COMPUTED_VALUE"""),"NYCT") -> NYCT | N9: =IFERROR(__xludf.DUMMYFUNCTION("""COMPUTED_VALUE"""),"FUJITEC") -> FUJITEC | O9: =IFERROR(__xludf.DUMMYFUNCTION("""COMPUTED_VALUE"""),"YES") -> YES | P9: =IFERROR(__xludf.DUMMYFUNCTION("""COMPUTED_VALUE"""),"NO") -> NO | Q9: =IFERROR(__xludf.DUMMYFUNCTION("""COMPUTED_VALUE"""),"NO") -> NO | R9: =IFERROR(__xludf.DUMMYFUNCTION("""COMPUTED_VALUE"""),"30'") -> 30' | S9: =IFERROR(__xludf.DUMMYFUNCTION("""COMPUTED_VALUE"""),110.0) -> 110 | T9: =IFERROR(__xludf.DUMMYFUNCTION("""COMPUTED_VALUE"""),24.0) -> 24 | U9: =IFERROR(__xludf.DUMMYFUNCTION("""COMPUTED_VALUE"""),"N/Q/R/W mezzanine to uptown B/D/F/M platform") -> N/Q/R/W mezzanine to uptown B/D/F/M platform | V9: =IFERROR(__xludf.DUMMYFUNCTION("""COMPUTED_VALUE"""),"POINT (-73.98773 40.749763)") -> POINT (-73.98773 40.749763)
A10: =IFERROR(__xludf.DUMMYFUNCTION("""COMPUTED_VALUE"""),"Broadway Junction") -> Broadway Junction | B10: =IFERROR(__xludf.DUMMYFUNCTION("""COMPUTED_VALUE"""),"Canarsie Line") -> Canarsie Line | C10: =IFERROR(__xludf.DUMMYFUNCTION("""COMPUTED_VALUE"""),"Brooklyn") -> Brooklyn | D10: =IFERROR(__xludf.DUMMYFUNCTION("""COMPUTED_VALUE"""),"East New York") -> East New York | E10: =IFERROR(__xludf.DUMMYFUNCTION("""COMPUTED_VALUE"""),10423.0) -> 10423 | F10: =IFERROR(__xludf.DUMMYFUNCTION("""COMPUTED_VALUE"""),1808472.0) -> 1808472 | G10: =IFERROR(__xludf.DUMMYFUNCTION("""COMPUTED_VALUE"""),176.0) -> 176 | H10: =IFERROR(__xludf.DUMMYFUNCTION("""COMPUTED_VALUE"""),"↗️") -> ↗️ | I10: =IFERROR(__xludf.DUMMYFUNCTION("""COMPUTED_VALUE"""),17715.0) -> 17715 | J10: =IFERROR(__xludf.DUMMYFUNCTION("""COMPUTED_VALUE"""),35384.0) -> 35384 | K10: =IFERROR(__xludf.DUMMYFUNCTION("""COMPUTED_VALUE"""),22.0) -> 22 | L10: =IFERROR(__xludf.DUMMYFUNCTION("""COMPUTED_VALUE"""),"YES") -> YES | M10: =IFERROR(__xludf.DUMMYFUNCTION("""COMPUTED_VALUE"""),"NYCT") -> NYCT | N10: =IFERROR(__xludf.DUMMYFUNCTION("""COMPUTED_VALUE"""),"OK") -> OK | O10: =IFERROR(__xludf.DUMMYFUNCTION("""COMPUTED_VALUE"""),"YES") -> YES | P10: =IFERROR(__xludf.DUMMYFUNCTION("""COMPUTED_VALUE"""),"YES") -> YES | Q10: =IFERROR(__xludf.DUMMYFUNCTION("""COMPUTED_VALUE"""),"NO") -> NO | R10: =IFERROR(__xludf.DUMMYFUNCTION("""COMPUTED_VALUE"""),"44'") -> 44' | S10: =IFERROR(__xludf.DUMMYFUNCTION("""COMPUTED_VALUE"""),153.0) -> 153 | T10: =IFERROR(__xludf.DUMMYFUNCTION("""COMPUTED_VALUE"""),32.0) -> 32 | U10: =IFERROR(__xludf.DUMMYFUNCTION("""COMPUTED_VALUE"""),"A/C mezzanine (Van Sinderen Ave) to upper mezzanine for J/Z and L service") -> A/C mezzanine (Van Sinderen Ave) to upper mezzanine for J/Z and L service | V10: =IFERROR(__xludf.DUMMYFUNCTION("""COMPUTED_VALUE"""),"POINT (-73.90394 40.678566)") -> POINT (-73.90394 40.678566)
A11: =IFERROR(__xludf.DUMMYFUNCTION("""COMPUTED_VALUE"""),"Jamaica Van Wyck") -> Jamaica Van Wyck | B11: =IFERROR(__xludf.DUMMYFUNCTION("""COMPUTED_VALUE"""),"") | C11: =IFERROR(__xludf.DUMMYFUNCTION("""COMPUTED_VALUE"""),"") | D11: =IFERROR(__xludf.DUMMYFUNCTION("""COMPUTED_VALUE"""),"") | E11: =IFERROR(__xludf.DUMMYFUNCTION("""COMPUTED_VALUE"""),"") | F11: =IFERROR(__xludf.DUMMYFUNCTION("""COMPUTED_VALUE"""),"") | G11: =IFERROR(__xludf.DUMMYFUNCTION("""COMPUTED_VALUE"""),"") | H11: =IFERROR(__xludf.DUMMYFUNCTION("""COMPUTED_VALUE"""),"↗️") -> ↗️ | I11: =IFERROR(__xludf.DUMMYFUNCTION("""COMPUTED_VALUE"""),32478.0) -> 32478 | J11: =IFERROR(__xludf.DUMMYFUNCTION("""COMPUTED_VALUE"""),39584.0) -> 39584 | K11: =IFERROR(__xludf.DUMMYFUNCTION("""COMPUTED_VALUE"""),22.0) -> 22 | L11: =IFERROR(__xludf.DUMMYFUNCTION("""COMPUTED_VALUE"""),"YES") -> YES | M11: =IFERROR(__xludf.DUMMYFUNCTION("""COMPUTED_VALUE"""),"NYCT") -> NYCT | N11: =IFERROR(__xludf.DUMMYFUNCTION("""COMPUTED_VALUE"""),"KONE") -> KONE | O11: =IFERROR(__xludf.DUMMYFUNCTION("""COMPUTED_VALUE"""),"YES") -> YES | P11: =IFERROR(__xludf.DUMMYFUNCTION("""COMPUTED_VALUE"""),"YES") -> YES | Q11: =IFERROR(__xludf.DUMMYFUNCTION("""COMPUTED_VALUE"""),"YES") -> YES | R11: =IFERROR(__xludf.DUMMYFUNCTION("""COMPUTED_VALUE"""),"28'") -> 28' | S11: =IFERROR(__xludf.DUMMYFUNCTION("""COMPUTED_VALUE"""),106.0) -> 106 | T11: =IFERROR(__xludf.DUMMYFUNCTION("""COMPUTED_VALUE"""),"32in") -> 32in | U11: =IFERROR(__xludf.DUMMYFUNCTION("""COMPUTED_VALUE"""),"mezzanine to 89 Ave & Van Wyck Expressway (SW corner)") -> mezzanine to 89 Ave & Van Wyck Expressway (SW corner) | V11: =IFERROR(__xludf.DUMMYFUNCTION("""COMPUTED_VALUE"""),"POINT (-73.8164 40.70101)") -> POINT (-73.8164 40.70101)
A12: =IFERROR(__xludf.DUMMYFUNCTION("""COMPUTED_VALUE"""),"72 St") -> 72 St | B12: =IFERROR(__xludf.DUMMYFUNCTION("""COMPUTED_VALUE"""),"Broadway-7 Av Line") -> Broadway-7 Av Line | C12: =IFERROR(__xludf.DUMMYFUNCTION("""COMPUTED_VALUE"""),"Manhattan") -> Manhattan | D12: =IFERROR(__xludf.DUMMYFUNCTION("""COMPUTED_VALUE"""),"Upper West Side") -> Upper West Side | E12: =IFERROR(__xludf.DUMMYFUNCTION("""COMPUTED_VALUE"""),1762.0) -> 1762 | F12: =IFERROR(__xludf.DUMMYFUNCTION("""COMPUTED_VALUE"""),9752193.0) -> 9752193 | G12: =IFERROR(__xludf.DUMMYFUNCTION("""COMPUTED_VALUE"""),22.0) -> 22 | H12: =IFERROR(__xludf.DUMMYFUNCTION("""COMPUTED_VALUE"""),"↗️") -> ↗️ | I12: =IFERROR(__xludf.DUMMYFUNCTION("""COMPUTED_VALUE"""),42736.0) -> 42736 | J12: =IFERROR(__xludf.DUMMYFUNCTION("""COMPUTED_VALUE"""),42736.0) -> 42736 | K12: =IFERROR(__xludf.DUMMYFUNCTION("""COMPUTED_VALUE"""),22.0) -> 22 | L12: =IFERROR(__xludf.DUMMYFUNCTION("""COMPUTED_VALUE"""),"YES") -> YES | M12: =IFERROR(__xludf.DUMMYFUNCTION("""COMPUTED_VALUE"""),"NYCT") -> NYCT | N12: =IFERROR(__xludf.DUMMYFUNCTION("""COMPUTED_VALUE"""),"SCHINDLER") -> SCHINDLER | O12: =IFERROR(__xludf.DUMMYFUNCTION("""COMPUTED_VALUE"""),"YES") -> YES | P12: =IFERROR(__xludf.DUMMYFUNCTION("""COMPUTED_VALUE"""),"NO") -> NO | Q12: =IFERROR(__xludf.DUMMYFUNCTION("""COMPUTED_VALUE"""),"NO") -> NO | R12: =IFERROR(__xludf.DUMMYFUNCTION("""COMPUTED_VALUE"""),"20828 mm (68'4in)") -> 20828 mm (68'4in) | S12: =IFERROR(__xludf.DUMMYFUNCTION("""COMPUTED_VALUE"""),0.0) -> 0 | U12: =IFERROR(__xludf.DUMMYFUNCTION("""COMPUTED_VALUE"""),"69 St & 2nd Ave (NE corner) to upper mezzanine") -> 69 St & 2nd Ave (NE corner) to upper mezzanine | V12: =IFERROR(__xludf.DUMMYFUNCTION("""COMPUTED_VALUE"""),"POINT (-73.95921 40.76722)") -> POINT (-73.95921 40.76722)
A13: =IFERROR(__xludf.DUMMYFUNCTION("""COMPUTED_VALUE"""),"Sutphin Blvd-Archer Av-JFK Airport") -> Sutphin Blvd-Archer Av-JFK Airport | B13: =IFERROR(__xludf.DUMMYFUNCTION("""COMPUTED_VALUE"""),"Archer Av Line") -> Archer Av Line | C13: =IFERROR(__xludf.DUMMYFUNCTION("""COMPUTED_VALUE"""),"Queens") -> Queens | D13: =IFERROR(__xludf.DUMMYFUNCTION("""COMPUTED_VALUE"""),"Jamaica") -> Jamaica | E13: =IFERROR(__xludf.DUMMYFUNCTION("""COMPUTED_VALUE"""),32488.0) -> 32488 | F13: =IFERROR(__xludf.DUMMYFUNCTION("""COMPUTED_VALUE"""),6496357.0) -> 6496357 | G13: =IFERROR(__xludf.DUMMYFUNCTION("""COMPUTED_VALUE"""),32.0) -> 32 | H13: =IFERROR(__xludf.DUMMYFUNCTION("""COMPUTED_VALUE"""),"↗️") -> ↗️ | J13: =IFERROR(__xludf.DUMMYFUNCTION("""COMPUTED_VALUE"""),40760.0) -> 40760 | K13: =IFERROR(__xludf.DUMMYFUNCTION("""COMPUTED_VALUE"""),22.0) -> 22 | L13: =IFERROR(__xludf.DUMMYFUNCTION("""COMPUTED_VALUE"""),"NO") -> NO | M13: =IFERROR(__xludf.DUMMYFUNCTION("""COMPUTED_VALUE"""),"Private Contractor") -> Private Contractor | N13: =IFERROR(__xludf.DUMMYFUNCTION("""COMPUTED_VALUE"""),"KONE") -> KONE | O13: =IFERROR(__xludf.DUMMYFUNCTION("""COMPUTED_VALUE"""),"YES") -> YES | P13: =IFERROR(__xludf.DUMMYFUNCTION("""COMPUTED_VALUE"""),"NO") -> NO | Q13: =IFERROR(__xludf.DUMMYFUNCTION("""COMPUTED_VALUE"""),"NO") -> NO | U13: =IFERROR(__xludf.DUMMYFUNCTION("""COMPUTED_VALUE"""),"mezzanine to Sutphin Blvd & Archer Ave (SW corner) for connection to LIRR and AirTrain") -> mezzanine to Sutphin Blvd & Archer Ave (SW corner) for connection to LIRR and AirTrain | V13: =IFERROR(__xludf.DUMMYFUNCTION("""COMPUTED_VALUE"""),"POINT (-73.80781 40.700127)") -> POINT (-73.80781 40.700127)
A14: =IFERROR(__xludf.DUMMYFUNCTION("""COMPUTED_VALUE"""),"5 Av/53 St") -> 5 Av/53 St | B14: =IFERROR(__xludf.DUMMYFUNCTION("""COMPUTED_VALUE"""),"Queens Blvd Line") -> Queens Blvd Line | C14: =IFERROR(__xludf.DUMMYFUNCTION("""COMPUTED_VALUE"""),"Manhattan") -> Manhattan | D14: =IFERROR(__xludf.DUMMYFUNCTION("""COMPUTED_VALUE"""),"Midtown") -> Midtown | E14: =IFERROR(__xludf.DUMMYFUNCTION("""COMPUTED_VALUE"""),12359.0) -> 12359 | F14: =IFERROR(__xludf.DUMMYFUNCTION("""COMPUTED_VALUE"""),4590651.0) -> 4590651 | G14: =IFERROR(__xludf.DUMMYFUNCTION("""COMPUTED_VALUE"""),64.0) -> 64 | H14: =IFERROR(__xludf.DUMMYFUNCTION("""COMPUTED_VALUE"""),"↗️") -> ↗️ | I14: =IFERROR(__xludf.DUMMYFUNCTION("""COMPUTED_VALUE"""),22087.0) -> 22087 | J14: =IFERROR(__xludf.DUMMYFUNCTION("""COMPUTED_VALUE"""),46000.0) -> 46000 | K14: =IFERROR(__xludf.DUMMYFUNCTION("""COMPUTED_VALUE"""),22.0) -> 22 | L14: =IFERROR(__xludf.DUMMYFUNCTION("""COMPUTED_VALUE"""),"YES") -> YES | M14: =IFERROR(__xludf.DUMMYFUNCTION("""COMPUTED_VALUE"""),"NYCT") -> NYCT | N14: =IFERROR(__xludf.DUMMYFUNCTION("""COMPUTED_VALUE"""),"KONE") -> KONE | O14: =IFERROR(__xludf.DUMMYFUNCTION("""COMPUTED_VALUE"""),"YES") -> YES | P14: =IFERROR(__xludf.DUMMYFUNCTION("""COMPUTED_VALUE"""),"NO") -> NO | Q14: =IFERROR(__xludf.DUMMYFUNCTION("""COMPUTED_VALUE"""),"NO") -> NO | R14: =IFERROR(__xludf.DUMMYFUNCTION("""COMPUTED_VALUE"""),"48'") -> 48' | S14: =IFERROR(__xludf.DUMMYFUNCTION("""COMPUTED_VALUE"""),166.0) -> 166 | T14: =IFERROR(__xludf.DUMMYFUNCTION("""COMPUTED_VALUE"""),40.0) -> 40 | U14: =IFERROR(__xludf.DUMMYFUNCTION("""COMPUTED_VALUE"""),"downtown platform to mezzanine for 5th Ave & 53 St exit") -> downtown platform to mezzanine for 5th Ave & 53 St exit | V14: =IFERROR(__xludf.DUMMYFUNCTION("""COMPUTED_VALUE"""),"POINT (-73.97628 40.76059)") -> POINT (-73.97628 40.76059)
A15: =IFERROR(__xludf.DUMMYFUNCTION("""COMPUTED_VALUE"""),"Lexington Av/53 St") -> Lexington Av/53 St | B15: =IFERROR(__xludf.DUMMYFUNCTION("""COMPUTED_VALUE"""),"") | C15: =IFERROR(__xludf.DUMMYFUNCTION("""COMPUTED_VALUE"""),"") | D15: =IFERROR(__xludf.DUMMYFUNCTION("""COMPUTED_VALUE"""),"") | E15: =IFERROR(__xludf.DUMMYFUNCTION("""COMPUTED_VALUE"""),"") | F15: =IFERROR(__xludf.DUMMYFUNCTION("""COMPUTED_VALUE"""),"") | G15: =IFERROR(__xludf.DUMMYFUNCTION("""COMPUTED_VALUE"""),"") | H15: =IFERROR(__xludf.DUMMYFUNCTION("""COMPUTED_VALUE"""),"↗️") -> ↗️ | I15: =IFERROR(__xludf.DUMMYFUNCTION("""COMPUTED_VALUE"""),3.0) -> 3 | J15: =IFERROR(__xludf.DUMMYFUNCTION("""COMPUTED_VALUE"""),40700.0) -> 40700 | K15: =IFERROR(__xludf.DUMMYFUNCTION("""COMPUTED_VALUE"""),22.0) -> 22 | L15: =IFERROR(__xludf.DUMMYFUNCTION("""COMPUTED_VALUE"""),"NO") -> NO | M15: =IFERROR(__xludf.DUMMYFUNCTION("""COMPUTED_VALUE"""),"Private Contractor") -> Private Contractor | N15: =IFERROR(__xludf.DUMMYFUNCTION("""COMPUTED_VALUE"""),"AM") -> AM | O15: =IFERROR(__xludf.DUMMYFUNCTION("""COMPUTED_VALUE"""),"YES") -> YES | P15: =IFERROR(__xludf.DUMMYFUNCTION("""COMPUTED_VALUE"""),"NO") -> NO | Q15: =IFERROR(__xludf.DUMMYFUNCTION("""COMPUTED_VALUE"""),"NO") -> NO | U15: =IFERROR(__xludf.DUMMYFUNCTION("""COMPUTED_VALUE"""),"Downtown 6 underpass to mezzanine for E/F service and 52 St & Lexington Av exit.") -> Downtown 6 underpass to mezzanine for E/F service and 52 St & Lexington Av exit. | V15: =IFERROR(__xludf.DUMMYFUNCTION("""COMPUTED_VALUE"""),"POINT (-73.97133 40.757572)") -> POINT (-73.97133 40.757572)
A16: =IFERROR(__xludf.DUMMYFUNCTION("""COMPUTED_VALUE"""),"Pelham Pkwy") -> Pelham Pkwy | B16: =IFERROR(__xludf.DUMMYFUNCTION("""COMPUTED_VALUE"""),"White Plains Rd Line") -> White Plains Rd Line | C16: =IFERROR(__xludf.DUMMYFUNCTION("""COMPUTED_VALUE"""),"The Bronx") -> The Bronx | D16: =IFERROR(__xludf.DUMMYFUNCTION("""COMPUTED_VALUE"""),"Pelham Parkway") -> Pelham Parkway | E16: =IFERROR(__xludf.DUMMYFUNCTION("""COMPUTED_VALUE"""),6272.0) -> 6272 | F16: =IFERROR(__xludf.DUMMYFUNCTION("""COMPUTED_VALUE"""),1514724.0) -> 1514724 | G16: =IFERROR(__xludf.DUMMYFUNCTION("""COMPUTED_VALUE"""),212.0) -> 212 | H16: =IFERROR(__xludf.DUMMYFUNCTION("""COMPUTED_VALUE"""),"↗️") -> ↗️ | I16: =IFERROR(__xludf.DUMMYFUNCTION("""COMPUTED_VALUE"""),35405.0) -> 35405 | J16: =IFERROR(__xludf.DUMMYFUNCTION("""COMPUTED_VALUE"""),44987.0) -> 44987 | K16: =IFERROR(__xludf.DUMMYFUNCTION("""COMPUTED_VALUE"""),22.0) -> 22 | L16: =IFERROR(__xludf.DUMMYFUNCTION("""COMPUTED_VALUE"""),"YES") -> YES | M16: =IFERROR(__xludf.DUMMYFUNCTION("""COMPUTED_VALUE"""),"NYCT") -> NYCT | N16: =IFERROR(__xludf.DUMMYFUNCTION("""COMPUTED_VALUE"""),"KONE") -> KONE | O16: =IFERROR(__xludf.DUMMYFUNCTION("""COMPUTED_VALUE"""),"YES") -> YES | P16: =IFERROR(__xludf.DUMMYFUNCTION("""COMPUTED_VALUE"""),"NO") -> NO | Q16: =IFERROR(__xludf.DUMMYFUNCTION("""COMPUTED_VALUE"""),"YES") -> YES | R16: =IFERROR(__xludf.DUMMYFUNCTION("""COMPUTED_VALUE"""),"3518 mm (11'-6 1/2in)") -> 3518 mm (11'-6 1/2in) | S16: =IFERROR(__xludf.DUMMYFUNCTION("""COMPUTED_VALUE"""),74.0) -> 74 | T16: =IFERROR(__xludf.DUMMYFUNCTION("""COMPUTED_VALUE"""),"1000mm (40in NOMINAL)") -> 1000mm (40in NOMINAL) | U16: =IFERROR(__xludf.DUMMYFUNCTION("""COMPUTED_VALUE"""),"mezzanine to Manhattan-bound platform") -> mezzanine to Manhattan-bound platform | V16: =IFERROR(__xludf.DUMMYFUNCTION("""COMPUTED_VALUE"""),"POINT (-73.86772 40.856728)") -> POINT (-73.86772 40.856728)
A17: =IFERROR(__xludf.DUMMYFUNCTION("""COMPUTED_VALUE"""),"59 St-Columbus Circle") -> 59 St-Columbus Circle | B17: =IFERROR(__xludf.DUMMYFUNCTION("""COMPUTED_VALUE"""),"Broadway-7 Av Line") -> Broadway-7 Av Line | C17: =IFERROR(__xludf.DUMMYFUNCTION("""COMPUTED_VALUE"""),"Manhattan") -> Manhattan | D17: =IFERROR(__xludf.DUMMYFUNCTION("""COMPUTED_VALUE"""),"Midtown") -> Midtown | E17: =IFERROR(__xludf.DUMMYFUNCTION("""COMPUTED_VALUE"""),1762.0) -> 1762 | F17: =IFERROR(__xludf.DUMMYFUNCTION("""COMPUTED_VALUE"""),1.6884912E7) -> 16884912 | G17: =IFERROR(__xludf.DUMMYFUNCTION("""COMPUTED_VALUE"""),7.0) -> 7 | H17: =IFERROR(__xludf.DUMMYFUNCTION("""COMPUTED_VALUE"""),"↗️") -> ↗️ | I17: =IFERROR(__xludf.DUMMYFUNCTION("""COMPUTED_VALUE"""),3.0) -> 3 | J17: =IFERROR(__xludf.DUMMYFUNCTION("""COMPUTED_VALUE"""),40664.0) -> 40664 | K17: =IFERROR(__xludf.DUMMYFUNCTION("""COMPUTED_VALUE"""),22.0) -> 22 | L17: =IFERROR(__xludf.DUMMYFUNCTION("""COMPUTED_VALUE"""),"NO") -> NO | M17: =IFERROR(__xludf.DUMMYFUNCTION("""COMPUTED_VALUE"""),"Private Contractor") -> Private Contractor | N17: =IFERROR(__xludf.DUMMYFUNCTION("""COMPUTED_VALUE"""),"OK") -> OK | O17: =IFERROR(__xludf.DUMMYFUNCTION("""COMPUTED_VALUE"""),"YES") -> YES | P17: =IFERROR(__xludf.DUMMYFUNCTION("""COMPUTED_VALUE"""),"NO") -> NO | Q17: =IFERROR(__xludf.DUMMYFUNCTION("""COMPUTED_VALUE"""),"NO") -> NO | S17: =IFERROR(__xludf.DUMMYFUNCTION("""COMPUTED_VALUE"""),0.0) -> 0 | U17: =IFERROR(__xludf.DUMMYFUNCTION("""COMPUTED_VALUE"""),"A/B/C/D mezzanine to 8th Ave & 58 St (NW corner)") -> A/B/C/D mezzanine to 8th Ave & 58 St (NW corner) | V17: =IFERROR(__xludf.DUMMYFUNCTION("""COMPUTED_VALUE"""),"POINT (-73.98249 40.767677)") -> POINT (-73.98249 40.767677)
A18: =IFERROR(__xludf.DUMMYFUNCTION("""COMPUTED_VALUE"""),"Roosevelt Island") -> Roosevelt Island | B18: =IFERROR(__xludf.DUMMYFUNCTION("""COMPUTED_VALUE"""),"63rd St Line") -> 63rd St Line | C18: =IFERROR(__xludf.DUMMYFUNCTION("""COMPUTED_VALUE"""),"Manhattan") -> Manhattan | D18: =IFERROR(__xludf.DUMMYFUNCTION("""COMPUTED_VALUE"""),"Roosevelt Island") -> Roosevelt Island | E18: =IFERROR(__xludf.DUMMYFUNCTION("""COMPUTED_VALUE"""),32810.0) -> 32810 | F18: =IFERROR(__xludf.DUMMYFUNCTION("""COMPUTED_VALUE"""),1885823.0) -> 1885823 | G18: =IFERROR(__xludf.DUMMYFUNCTION("""COMPUTED_VALUE"""),171.0) -> 171 | H18: =IFERROR(__xludf.DUMMYFUNCTION("""COMPUTED_VALUE"""),"↗️") -> ↗️ | I18: =IFERROR(__xludf.DUMMYFUNCTION("""COMPUTED_VALUE"""),32782.0) -> 32782 | J18: =IFERROR(__xludf.DUMMYFUNCTION("""COMPUTED_VALUE"""),39647.0) -> 39647 | K18: =IFERROR(__xludf.DUMMYFUNCTION("""COMPUTED_VALUE"""),22.0) -> 22 | L18: =IFERROR(__xludf.DUMMYFUNCTION("""COMPUTED_VALUE"""),"YES") -> YES | M18: =IFERROR(__xludf.DUMMYFUNCTION("""COMPUTED_VALUE"""),"NYCT") -> NYCT | N18: =IFERROR(__xludf.DUMMYFUNCTION("""COMPUTED_VALUE"""),"KONE") -> KONE | O18: =IFERROR(__xludf.DUMMYFUNCTION("""COMPUTED_VALUE"""),"YES") -> YES | P18: =IFERROR(__xludf.DUMMYFUNCTION("""COMPUTED_VALUE"""),"NO") -> NO | Q18: =IFERROR(__xludf.DUMMYFUNCTION("""COMPUTED_VALUE"""),"NO") -> NO | R18: =IFERROR(__xludf.DUMMYFUNCTION("""COMPUTED_VALUE"""),"14'") -> 14' | S18: =IFERROR(__xludf.DUMMYFUNCTION("""COMPUTED_VALUE"""),56.0) -> 56 | T18: =IFERROR(__xludf.DUMMYFUNCTION("""COMPUTED_VALUE"""),40.0) -> 40 | U18: =IFERROR(__xludf.DUMMYFUNCTION("""COMPUTED_VALUE"""),"Manhattan-bound platform to lower mezzanine") -> Manhattan-bound platform to lower mezzanine | V18: =IFERROR(__xludf.DUMMYFUNCTION("""COMPUTED_VALUE"""),"POINT (-73.952354 40.75876)") -> POINT (-73.952354 40.75876)
A19: =IFERROR(__xludf.DUMMYFUNCTION("""COMPUTED_VALUE"""),"Bowling Green") -> Bowling Green | B19: =IFERROR(__xludf.DUMMYFUNCTION("""COMPUTED_VALUE"""),"Lexington Av Line") -> Lexington Av Line | C19: =IFERROR(__xludf.DUMMYFUNCTION("""COMPUTED_VALUE"""),"Manhattan") -> Manhattan | D19: =IFERROR(__xludf.DUMMYFUNCTION("""COMPUTED_VALUE"""),"Financial District") -> Financial District | E19: =IFERROR(__xludf.DUMMYFUNCTION("""COMPUTED_VALUE"""),2018.0) -> 2018 | F19: =IFERROR(__xludf.DUMMYFUNCTION("""COMPUTED_VALUE"""),4676646.0) -> 4676646 | G19: =IFERROR(__xludf.DUMMYFUNCTION("""COMPUTED_VALUE"""),62.0) -> 62 | H19: =IFERROR(__xludf.DUMMYFUNCTION("""COMPUTED_VALUE"""),"↗️") -> ↗️ | I19: =IFERROR(__xludf.DUMMYFUNCTION("""COMPUTED_VALUE"""),28216.0) -> 28216 | J19: =IFERROR(__xludf.DUMMYFUNCTION("""COMPUTED_VALUE"""),38430.0) -> 38430 | K19: =IFERROR(__xludf.DUMMYFUNCTION("""COMPUTED_VALUE"""),22.0) -> 22 | L19: =IFERROR(__xludf.DUMMYFUNCTION("""COMPUTED_VALUE"""),"YES") -> YES | M19: =IFERROR(__xludf.DUMMYFUNCTION("""COMPUTED_VALUE"""),"NYCT") -> NYCT | N19: =IFERROR(__xludf.DUMMYFUNCTION("""COMPUTED_VALUE"""),"FUJITEC") -> FUJITEC | O19: =IFERROR(__xludf.DUMMYFUNCTION("""COMPUTED_VALUE"""),"YES") -> YES | P19: =IFERROR(__xludf.DUMMYFUNCTION("""COMPUTED_VALUE"""),"NO") -> NO | Q19: =IFERROR(__xludf.DUMMYFUNCTION("""COMPUTED_VALUE"""),"NO") -> NO | R19: =IFERROR(__xludf.DUMMYFUNCTION("""COMPUTED_VALUE"""),"23'") -> 23' | S19: =IFERROR(__xludf.DUMMYFUNCTION("""COMPUTED_VALUE"""),92.0) -> 92 | T19: =IFERROR(__xludf.DUMMYFUNCTION("""COMPUTED_VALUE"""),40.0) -> 40 | U19: =IFERROR(__xludf.DUMMYFUNCTION("""COMPUTED_VALUE"""),"lower mezzanine to uptown 4/5 platform") -> lower mezzanine to uptown 4/5 platform | V19: =IFERROR(__xludf.DUMMYFUNCTION("""COMPUTED_VALUE"""),"POINT (-74.01387 40.704838)") -> POINT (-74.01387 40.704838)
A20: =IFERROR(__xludf.DUMMYFUNCTION("""COMPUTED_VALUE"""),"72 St") -> 72 St | B20: =IFERROR(__xludf.DUMMYFUNCTION("""COMPUTED_VALUE"""),"Broadway-7 Av Line") -> Broadway-7 Av Line | C20: =IFERROR(__xludf.DUMMYFUNCTION("""COMPUTED_VALUE"""),"Manhattan") -> Manhattan | D20: =IFERROR(__xludf.DUMMYFUNCTION("""COMPUTED_VALUE"""),"Upper West Side") -> Upper West Side | E20: =IFERROR(__xludf.DUMMYFUNCTION("""COMPUTED_VALUE"""),1762.0) -> 1762 | F20: =IFERROR(__xludf.DUMMYFUNCTION("""COMPUTED_VALUE"""),9752193.0) -> 9752193 | G20: =IFERROR(__xludf.DUMMYFUNCTION("""COMPUTED_VALUE"""),22.0) -> 22 | H20: =IFERROR(__xludf.DUMMYFUNCTION("""COMPUTED_VALUE"""),"↗️") -> ↗️ | I20: =IFERROR(__xludf.DUMMYFUNCTION("""COMPUTED_VALUE"""),42736.0) -> 42736 | J20: =IFERROR(__xludf.DUMMYFUNCTION("""COMPUTED_VALUE"""),42736.0) -> 42736 | K20: =IFERROR(__xludf.DUMMYFUNCTION("""COMPUTED_VALUE"""),22.0) -> 22 | L20: =IFERROR(__xludf.DUMMYFUNCTION("""COMPUTED_VALUE"""),"YES") -> YES | M20: =IFERROR(__xludf.DUMMYFUNCTION("""COMPUTED_VALUE"""),"NYCT") -> NYCT | N20: =IFERROR(__xludf.DUMMYFUNCTION("""COMPUTED_VALUE"""),"SCHINDLER") -> SCHINDLER | O20: =IFERROR(__xludf.DUMMYFUNCTION("""COMPUTED_VALUE"""),"YES") -> YES | P20: =IFERROR(__xludf.DUMMYFUNCTION("""COMPUTED_VALUE"""),"YES") -> YES | Q20: =IFERROR(__xludf.DUMMYFUNCTION("""COMPUTED_VALUE"""),"YES") -> YES | R20: =IFERROR(__xludf.DUMMYFUNCTION("""COMPUTED_VALUE"""),"21577 mm (70' 9 1/2in)") -> 21577 mm (70' 9 1/2in) | S20: =IFERROR(__xludf.DUMMYFUNCTION("""COMPUTED_VALUE"""),0.0) -> 0 | U20: =IFERROR(__xludf.DUMMYFUNCTION("""COMPUTED_VALUE"""),"lower mezzanine to 72 St & 2nd Ave (NW corner)") -> lower mezzanine to 72 St & 2nd Ave (NW corner) | V20: =IFERROR(__xludf.DUMMYFUNCTION("""COMPUTED_VALUE"""),"POINT (-73.95847 40.76906)") -> POINT (-73.95847 40.76906)
A21: =IFERROR(__xludf.DUMMYFUNCTION("""COMPUTED_VALUE"""),"181 St") -> 181 St | B21: =IFERROR(__xludf.DUMMYFUNCTION("""COMPUTED_VALUE"""),"8 Av Line") -> 8 Av Line | C21: =IFERROR(__xludf.DUMMYFUNCTION("""COMPUTED_VALUE"""),"Manhattan") -> Manhattan | D21: =IFERROR(__xludf.DUMMYFUNCTION("""COMPUTED_VALUE"""),"Washington Heights") -> Washington Heights | E21: =IFERROR(__xludf.DUMMYFUNCTION("""COMPUTED_VALUE"""),11942.0) -> 11942 | F21: =IFERROR(__xludf.DUMMYFUNCTION("""COMPUTED_VALUE"""),2042771.0) -> 2042771 | G21: =IFERROR(__xludf.DUMMYFUNCTION("""COMPUTED_VALUE"""),160.0) -> 160 | H21: =IFERROR(__xludf.DUMMYFUNCTION("""COMPUTED_VALUE"""),"↗️") -> ↗️ | I21: =IFERROR(__xludf.DUMMYFUNCTION("""COMPUTED_VALUE"""),35517.0) -> 35517 | J21: =IFERROR(__xludf.DUMMYFUNCTION("""COMPUTED_VALUE"""),45016.0) -> 45016 | K21: =IFERROR(__xludf.DUMMYFUNCTION("""COMPUTED_VALUE"""),22.0) -> 22 | L21: =IFERROR(__xludf.DUMMYFUNCTION("""COMPUTED_VALUE"""),"YES") -> YES | M21: =IFERROR(__xludf.DUMMYFUNCTION("""COMPUTED_VALUE"""),"NYCT") -> NYCT | N21: =IFERROR(__xludf.DUMMYFUNCTION("""COMPUTED_VALUE"""),"KONE") -> KONE | O21: =IFERROR(__xludf.DUMMYFUNCTION("""COMPUTED_VALUE"""),"YES") -> YES | P21: =IFERROR(__xludf.DUMMYFUNCTION("""COMPUTED_VALUE"""),"NO") -> NO | Q21: =IFERROR(__xludf.DUMMYFUNCTION("""COMPUTED_VALUE"""),"NO") -> NO | R21: =IFERROR(__xludf.DUMMYFUNCTION("""COMPUTED_VALUE"""),"15824 mm (51'-11in)") -> 15824 mm (51'-11in) | S21: =IFERROR(__xludf.DUMMYFUNCTION("""COMPUTED_VALUE"""),112.0) -> 112 | T21: =IFERROR(__xludf.DUMMYFUNCTION("""COMPUTED_VALUE"""),"800 mm (32in NOMINAL)") -> 800 mm (32in NOMINAL) | U21: =IFERROR(__xludf.DUMMYFUNCTION("""COMPUTED_VALUE"""),"lower mezzanine to upper mezzanine for 181 St & Fort Washington Ave exit") -> lower mezzanine to upper mezzanine for 181 St & Fort Washington Ave exit | V21: =IFERROR(__xludf.DUMMYFUNCTION("""COMPUTED_VALUE"""),"POINT (-73.938095 40.851116)") -> POINT (-73.938095 40.851116)
A22: =IFERROR(__xludf.DUMMYFUNCTION("""COMPUTED_VALUE"""),"34 St-Hudson Yards") -> 34 St-Hudson Yards | B22: =IFERROR(__xludf.DUMMYFUNCTION("""COMPUTED_VALUE"""),"Flushing Line") -> Flushing Line | C22: =IFERROR(__xludf.DUMMYFUNCTION("""COMPUTED_VALUE"""),"Manhattan") -> Manhattan | D22: =IFERROR(__xludf.DUMMYFUNCTION("""COMPUTED_VALUE"""),"Hell's Kitchen") -> Hell's Kitchen | E22: =IFERROR(__xludf.DUMMYFUNCTION("""COMPUTED_VALUE"""),42260.0) -> 42260 | F22: =IFERROR(__xludf.DUMMYFUNCTION("""COMPUTED_VALUE"""),6082370.0) -> 6082370 | G22: =IFERROR(__xludf.DUMMYFUNCTION("""COMPUTED_VALUE"""),39.0) -> 39 | H22: =IFERROR(__xludf.DUMMYFUNCTION("""COMPUTED_VALUE"""),"↗️") -> ↗️ | I22: =IFERROR(__xludf.DUMMYFUNCTION("""COMPUTED_VALUE"""),43343.0) -> 43343 | J22: =IFERROR(__xludf.DUMMYFUNCTION("""COMPUTED_VALUE"""),43343.0) -> 43343 | K22: =IFERROR(__xludf.DUMMYFUNCTION("""COMPUTED_VALUE"""),22.0) -> 22 | L22: =IFERROR(__xludf.DUMMYFUNCTION("""COMPUTED_VALUE"""),"YES") -> YES | M22: =IFERROR(__xludf.DUMMYFUNCTION("""COMPUTED_VALUE"""),"NYCT") -> NYCT | N22: =IFERROR(__xludf.DUMMYFUNCTION("""COMPUTED_VALUE"""),"SCHINDLER") -> SCHINDLER | O22: =IFERROR(__xludf.DUMMYFUNCTION("""COMPUTED_VALUE"""),"YES") -> YES | P22: =IFERROR(__xludf.DUMMYFUNCTION("""COMPUTED_VALUE"""),"NO") -> NO | Q22: =IFERROR(__xludf.DUMMYFUNCTION("""COMPUTED_VALUE"""),"NO") -> NO | R22: =IFERROR(__xludf.DUMMYFUNCTION("""COMPUTED_VALUE"""),"24'") -> 24' | S22: =IFERROR(__xludf.DUMMYFUNCTION("""COMPUTED_VALUE"""),90.0) -> 90 | T22: =IFERROR(__xludf.DUMMYFUNCTION("""COMPUTED_VALUE"""),40.0) -> 40 | U22: =IFERROR(__xludf.DUMMYFUNCTION("""COMPUTED_VALUE"""),"lower mezzanine to upper mezzanine for Hudson Blvd E & 35 St exit") -> lower mezzanine to upper mezzanine for Hudson Blvd E & 35 St exit | V22: =IFERROR(__xludf.DUMMYFUNCTION("""COMPUTED_VALUE"""),"POINT (-74.00111 40.75609)") -> POINT (-74.00111 40.75609)
A23: =IFERROR(__xludf.DUMMYFUNCTION("""COMPUTED_VALUE"""),"Jamaica Center-Parsons/Archer") -> Jamaica Center-Parsons/Archer | B23: =IFERROR(__xludf.DUMMYFUNCTION("""COMPUTED_VALUE"""),"Archer Av Line") -> Archer Av Line | C23: =IFERROR(__xludf.DUMMYFUNCTION("""COMPUTED_VALUE"""),"Queens") -> Queens | D23: =IFERROR(__xludf.DUMMYFUNCTION("""COMPUTED_VALUE"""),"Jamaica") -> Jamaica | E23: =IFERROR(__xludf.DUMMYFUNCTION("""COMPUTED_VALUE"""),32488.0) -> 32488 | F23: =IFERROR(__xludf.DUMMYFUNCTION("""COMPUTED_VALUE"""),6137267.0) -> 6137267 | G23: =IFERROR(__xludf.DUMMYFUNCTION("""COMPUTED_VALUE"""),38.0) -> 38 | H23: =IFERROR(__xludf.DUMMYFUNCTION("""COMPUTED_VALUE"""),"↗️") -> ↗️ | I23: =IFERROR(__xludf.DUMMYFUNCTION("""COMPUTED_VALUE"""),32478.0) -> 32478 | J23: =IFERROR(__xludf.DUMMYFUNCTION("""COMPUTED_VALUE"""),39420.0) -> 39420 | K23: =IFERROR(__xludf.DUMMYFUNCTION("""COMPUTED_VALUE"""),22.0) -> 22 | L23: =IFERROR(__xludf.DUMMYFUNCTION("""COMPUTED_VALUE"""),"YES") -> YES | M23: =IFERROR(__xludf.DUMMYFUNCTION("""COMPUTED_VALUE"""),"NYCT") -> NYCT | N23: =IFERROR(__xludf.DUMMYFUNCTION("""COMPUTED_VALUE"""),"KONE") -> KONE | O23: =IFERROR(__xludf.DUMMYFUNCTION("""COMPUTED_VALUE"""),"YES") -> YES | P23: =IFERROR(__xludf.DUMMYFUNCTION("""COMPUTED_VALUE"""),"NO") -> NO | Q23: =IFERROR(__xludf.DUMMYFUNCTION("""COMPUTED_VALUE"""),"NO") -> NO | R23: =IFERROR(__xludf.DUMMYFUNCTION("""COMPUTED_VALUE"""),"28'") -> 28' | S23: =IFERROR(__xludf.DUMMYFUNCTION("""COMPUTED_VALUE"""),106.0) -> 106 | T23: =IFERROR(__xludf.DUMMYFUNCTION("""COMPUTED_VALUE"""),"32in") -> 32in | U23: =IFERROR(__xludf.DUMMYFUNCTION("""COMPUTED_VALUE"""),"mezzanine (153 St & Archer Ave) to J/Z platform for Brooklyn-bound service") -> mezzanine (153 St & Archer Ave) to J/Z platform for Brooklyn-bound service | V23: =IFERROR(__xludf.DUMMYFUNCTION("""COMPUTED_VALUE"""),"POINT (-73.801926 40.70198)") -> POINT (-73.801926 40.70198)
A24: =IFERROR(__xludf.DUMMYFUNCTION("""COMPUTED_VALUE"""),"14 St-Union Sq") -> 14 St-Union Sq | B24: =IFERROR(__xludf.DUMMYFUNCTION("""COMPUTED_VALUE"""),"Broadway Line") -> Broadway Line | C24: =IFERROR(__xludf.DUMMYFUNCTION("""COMPUTED_VALUE"""),"Manhattan") -> Manhattan | D24: =IFERROR(__xludf.DUMMYFUNCTION("""COMPUTED_VALUE"""),"Union Square") -> Union Square | E24: =IFERROR(__xludf.DUMMYFUNCTION("""COMPUTED_VALUE"""),6457.0) -> 6457 | F24: =IFERROR(__xludf.DUMMYFUNCTION("""COMPUTED_VALUE"""),2.2811597E7) -> 22811597 | G24: =IFERROR(__xludf.DUMMYFUNCTION("""COMPUTED_VALUE"""),4.0) -> 4 | H24: =IFERROR(__xludf.DUMMYFUNCTION("""COMPUTED_VALUE"""),"↗️") -> ↗️ | J24: =IFERROR(__xludf.DUMMYFUNCTION("""COMPUTED_VALUE"""),41071.0) -> 41071 | K24: =IFERROR(__xludf.DUMMYFUNCTION("""COMPUTED_VALUE"""),22.0) -> 22 | L24: =IFERROR(__xludf.DUMMYFUNCTION("""COMPUTED_VALUE"""),"NO") -> NO | M24: =IFERROR(__xludf.DUMMYFUNCTION("""COMPUTED_VALUE"""),"Private Contractor") -> Private Contractor | N24: =IFERROR(__xludf.DUMMYFUNCTION("""COMPUTED_VALUE"""),"AM") -> AM | O24: =IFERROR(__xludf.DUMMYFUNCTION("""COMPUTED_VALUE"""),"YES") -> YES | P24: =IFERROR(__xludf.DUMMYFUNCTION("""COMPUTED_VALUE"""),"NO") -> NO | Q24: =IFERROR(__xludf.DUMMYFUNCTION("""COMPUTED_VALUE"""),"NO") -> NO | U24: =IFERROR(__xludf.DUMMYFUNCTION("""COMPUTED_VALUE"""),"14 St & 4th Ave (NE corner) to mezzanine for 4/5/6/L service and access to N/Q/R/W") -> 14 St & 4th Ave (NE corner) to mezzanine for 4/5/6/L service and access to N/Q/R/W | V24: =IFERROR(__xludf.DUMMYFUNCTION("""COMPUTED_VALUE"""),"POINT (-73.98946 40.73445)") -> POINT (-73.98946 40.73445)
A25: =IFERROR(__xludf.DUMMYFUNCTION("""COMPUTED_VALUE"""),"34 St-Herald Sq") -> 34 St-Herald Sq | B25: =IFERROR(__xludf.DUMMYFUNCTION("""COMPUTED_VALUE"""),"Broadway Line") -> Broadway Line | C25: =IFERROR(__xludf.DUMMYFUNCTION("""COMPUTED_VALUE"""),"Manhattan") -> Manhattan | D25: =IFERROR(__xludf.DUMMYFUNCTION("""COMPUTED_VALUE"""),"Midtown") -> Midtown | E25: =IFERROR(__xludf.DUMMYFUNCTION("""COMPUTED_VALUE"""),6580.0) -> 6580 | F25: =IFERROR(__xludf.DUMMYFUNCTION("""COMPUTED_VALUE"""),2.5012549E7) -> 25012549 | G25: =IFERROR(__xludf.DUMMYFUNCTION("""COMPUTED_VALUE"""),3.0) -> 3 | H25: =IFERROR(__xludf.DUMMYFUNCTION("""COMPUTED_VALUE"""),"↗️") -> ↗️ | I25: =IFERROR(__xludf.DUMMYFUNCTION("""COMPUTED_VALUE"""),14960.0) -> 14960 | J25: =IFERROR(__xludf.DUMMYFUNCTION("""COMPUTED_VALUE"""),39044.0) -> 39044 | K25: =IFERROR(__xludf.DUMMYFUNCTION("""COMPUTED_VALUE"""),22.0) -> 22 | L25: =IFERROR(__xludf.DUMMYFUNCTION("""COMPUTED_VALUE"""),"YES") -> YES | M25: =IFERROR(__xludf.DUMMYFUNCTION("""COMPUTED_VALUE"""),"NYCT") -> NYCT | N25: =IFERROR(__xludf.DUMMYFUNCTION("""COMPUTED_VALUE"""),"FUJITEC") -> FUJITEC | O25: =IFERROR(__xludf.DUMMYFUNCTION("""COMPUTED_VALUE"""),"YES") -> YES | P25: =IFERROR(__xludf.DUMMYFUNCTION("""COMPUTED_VALUE"""),"NO") -> NO | Q25: =IFERROR(__xludf.DUMMYFUNCTION("""COMPUTED_VALUE"""),"NO") -> NO | R25: =IFERROR(__xludf.DUMMYFUNCTION("""COMPUTED_VALUE"""),"30'") -> 30' | S25: =IFERROR(__xludf.DUMMYFUNCTION("""COMPUTED_VALUE"""),109.0) -> 109 | T25: =IFERROR(__xludf.DUMMYFUNCTION("""COMPUTED_VALUE"""),24.0) -> 24 | U25: =IFERROR(__xludf.DUMMYFUNCTION("""COMPUTED_VALUE"""),"downtown B/D/F/M platform to mezzanine for access to street and N/Q/R/W service") -> downtown B/D/F/M platform to mezzanine for access to street and N/Q/R/W service | V25: =IFERROR(__xludf.DUMMYFUNCTION("""COMPUTED_VALUE"""),"POINT (-73.987686 40.75006)") -> POINT (-73.987686 40.75006)
A26: =IFERROR(__xludf.DUMMYFUNCTION("""COMPUTED_VALUE"""),"Lexington Av/63 St") -> Lexington Av/63 St | B26: =IFERROR(__xludf.DUMMYFUNCTION("""COMPUTED_VALUE"""),"") | C26: =IFERROR(__xludf.DUMMYFUNCTION("""COMPUTED_VALUE"""),"") | D26: =IFERROR(__xludf.DUMMYFUNCTION("""COMPUTED_VALUE"""),"") | E26: =IFERROR(__xludf.DUMMYFUNCTION("""COMPUTED_VALUE"""),"") | F26: =IFERROR(__xludf.DUMMYFUNCTION("""COMPUTED_VALUE"""),"") | G26: =IFERROR(__xludf.DUMMYFUNCTION("""COMPUTED_VALUE"""),"") | H26: =IFERROR(__xludf.DUMMYFUNCTION("""COMPUTED_VALUE"""),"↗️") -> ↗️ | I26: =IFERROR(__xludf.DUMMYFUNCTION("""COMPUTED_VALUE"""),32782.0) -> 32782 | J26: =IFERROR(__xludf.DUMMYFUNCTION("""COMPUTED_VALUE"""),46107.0) -> 46107 | K26: =IFERROR(__xludf.DUMMYFUNCTION("""COMPUTED_VALUE"""),22.0) -> 22 | L26: =IFERROR(__xludf.DUMMYFUNCTION("""COMPUTED_VALUE"""),"YES") -> YES | M26: =IFERROR(__xludf.DUMMYFUNCTION("""COMPUTED_VALUE"""),"NYCT") -> NYCT | N26: =IFERROR(__xludf.DUMMYFUNCTION("""COMPUTED_VALUE"""),"KONE") -> KONE | O26: =IFERROR(__xludf.DUMMYFUNCTION("""COMPUTED_VALUE"""),"YES") -> YES | P26: =IFERROR(__xludf.DUMMYFUNCTION("""COMPUTED_VALUE"""),"NO") -> NO | Q26: =IFERROR(__xludf.DUMMYFUNCTION("""COMPUTED_VALUE"""),"NO") -> NO | R26: =IFERROR(__xludf.DUMMYFUNCTION("""COMPUTED_VALUE"""),"25'11 3/4") -> 25'11 3/4 | S26: =IFERROR(__xludf.DUMMYFUNCTION("""COMPUTED_VALUE"""),91.0) -> 91 | T26: =IFERROR(__xludf.DUMMYFUNCTION("""COMPUTED_VALUE"""),"40'") -> 40' | U26: =IFERROR(__xludf.DUMMYFUNCTION("""COMPUTED_VALUE"""),"intermediate mezzanine (Lexington Ave & 63 St) to lower mezzanine") -> intermediate mezzanine (Lexington Ave & 63 St) to lower mezzanine | V26: =IFERROR(__xludf.DUMMYFUNCTION("""COMPUTED_VALUE"""),"POINT (-73.967285 40.76518)") -> POINT (-73.967285 40.76518)
A27: =IFERROR(__xludf.DUMMYFUNCTION("""COMPUTED_VALUE"""),"Lexington Av/63 St") -> Lexington Av/63 St | B27: =IFERROR(__xludf.DUMMYFUNCTION("""COMPUTED_VALUE"""),"") | C27: =IFERROR(__xludf.DUMMYFUNCTION("""COMPUTED_VALUE"""),"") | D27: =IFERROR(__xludf.DUMMYFUNCTION("""COMPUTED_VALUE"""),"") | E27: =IFERROR(__xludf.DUMMYFUNCTION("""COMPUTED_VALUE"""),"") | F27: =IFERROR(__xludf.DUMMYFUNCTION("""COMPUTED_VALUE"""),"") | G27: =IFERROR(__xludf.DUMMYFUNCTION("""COMPUTED_VALUE"""),"") | H27: =IFERROR(__xludf.DUMMYFUNCTION("""COMPUTED_VALUE"""),"↗️") -> ↗️ | I27: =IFERROR(__xludf.DUMMYFUNCTION("""COMPUTED_VALUE"""),32782.0) -> 32782 | J27: =IFERROR(__xludf.DUMMYFUNCTION("""COMPUTED_VALUE"""),46107.0) -> 46107 | K27: =IFERROR(__xludf.DUMMYFUNCTION("""COMPUTED_VALUE"""),22.0) -> 22 | L27: =IFERROR(__xludf.DUMMYFUNCTION("""COMPUTED_VALUE"""),"YES") -> YES | M27: =IFERROR(__xludf.DUMMYFUNCTION("""COMPUTED_VALUE"""),"NYCT") -> NYCT | N27: =IFERROR(__xludf.DUMMYFUNCTION("""COMPUTED_VALUE"""),"KONE") -> KONE | O27: =IFERROR(__xludf.DUMMYFUNCTION("""COMPUTED_VALUE"""),"YES") -> YES | P27: =IFERROR(__xludf.DUMMYFUNCTION("""COMPUTED_VALUE"""),"NO") -> NO | Q27: =IFERROR(__xludf.DUMMYFUNCTION("""COMPUTED_VALUE"""),"NO") -> NO | R27: =IFERROR(__xludf.DUMMYFUNCTION("""COMPUTED_VALUE"""),"18'10 5/8") -> 18'10 5/8 | S27: =IFERROR(__xludf.DUMMYFUNCTION("""COMPUTED_VALUE"""),65.0) -> 65 | T27: =IFERROR(__xludf.DUMMYFUNCTION("""COMPUTED_VALUE"""),"40'") -> 40' | U27: =IFERROR(__xludf.DUMMYFUNCTION("""COMPUTED_VALUE"""),"lower mezzanine (Lexington Ave & 63 St) to downtown platform") -> lower mezzanine (Lexington Ave & 63 St) to downtown platform | V27: =IFERROR(__xludf.DUMMYFUNCTION("""COMPUTED_VALUE"""),"POINT (-73.96745 40.765236)") -> POINT (-73.96745 40.765236)
A28: =IFERROR(__xludf.DUMMYFUNCTION("""COMPUTED_VALUE"""),"59 St") -> 59 St | B28: =IFERROR(__xludf.DUMMYFUNCTION("""COMPUTED_VALUE"""),"4 Av Line") -> 4 Av Line | C28: =IFERROR(__xludf.DUMMYFUNCTION("""COMPUTED_VALUE"""),"Brooklyn") -> Brooklyn | D28: =IFERROR(__xludf.DUMMYFUNCTION("""COMPUTED_VALUE"""),"Sunset Park") -> Sunset Park | E28: =IFERROR(__xludf.DUMMYFUNCTION("""COMPUTED_VALUE"""),5652.0) -> 5652 | F28: =IFERROR(__xludf.DUMMYFUNCTION("""COMPUTED_VALUE"""),2952891.0) -> 2952891 | G28: =IFERROR(__xludf.DUMMYFUNCTION("""COMPUTED_VALUE"""),112.0) -> 112 | H28: =IFERROR(__xludf.DUMMYFUNCTION("""COMPUTED_VALUE"""),"↗️") -> ↗️ | I28: =IFERROR(__xludf.DUMMYFUNCTION("""COMPUTED_VALUE"""),22965.0) -> 22965 | J28: =IFERROR(__xludf.DUMMYFUNCTION("""COMPUTED_VALUE"""),45519.0) -> 45519 | K28: =IFERROR(__xludf.DUMMYFUNCTION("""COMPUTED_VALUE"""),22.0) -> 22 | L28: =IFERROR(__xludf.DUMMYFUNCTION("""COMPUTED_VALUE"""),"YES") -> YES | M28: =IFERROR(__xludf.DUMMYFUNCTION("""COMPUTED_VALUE"""),"NYCT") -> NYCT | N28: =IFERROR(__xludf.DUMMYFUNCTION("""COMPUTED_VALUE"""),"OK") -> OK | O28: =IFERROR(__xludf.DUMMYFUNCTION("""COMPUTED_VALUE"""),"YES") -> YES | P28: =IFERROR(__xludf.DUMMYFUNCTION("""COMPUTED_VALUE"""),"NO") -> NO | Q28: =IFERROR(__xludf.DUMMYFUNCTION("""COMPUTED_VALUE"""),"NO") -> NO | R28: =IFERROR(__xludf.DUMMYFUNCTION("""COMPUTED_VALUE"""),"50'") -> 50' | S28: =IFERROR(__xludf.DUMMYFUNCTION("""COMPUTED_VALUE"""),172.0) -> 172 | T28: =IFERROR(__xludf.DUMMYFUNCTION("""COMPUTED_VALUE"""),40.0) -> 40 | U28: =IFERROR(__xludf.DUMMYFUNCTION("""COMPUTED_VALUE"""),"uptown 4/5 platform to uptown 6 platform") -> uptown 4/5 platform to uptown 6 platform | V28: =IFERROR(__xludf.DUMMYFUNCTION("""COMPUTED_VALUE"""),"POINT (-73.968254 40.762287)") -> POINT (-73.968254 40.762287)
A29: =IFERROR(__xludf.DUMMYFUNCTION("""COMPUTED_VALUE"""),"South Ferry") -> South Ferry | B29: =IFERROR(__xludf.DUMMYFUNCTION("""COMPUTED_VALUE"""),"") | C29: =IFERROR(__xludf.DUMMYFUNCTION("""COMPUTED_VALUE"""),"") | D29: =IFERROR(__xludf.DUMMYFUNCTION("""COMPUTED_VALUE"""),"") | E29: =IFERROR(__xludf.DUMMYFUNCTION("""COMPUTED_VALUE"""),"") | F29: =IFERROR(__xludf.DUMMYFUNCTION("""COMPUTED_VALUE"""),"") | G29: =IFERROR(__xludf.DUMMYFUNCTION("""COMPUTED_VALUE"""),"") | H29: =IFERROR(__xludf.DUMMYFUNCTION("""COMPUTED_VALUE"""),"↗️") -> ↗️ | I29: =IFERROR(__xludf.DUMMYFUNCTION("""COMPUTED_VALUE"""),39888.0) -> 39888 | J29: =IFERROR(__xludf.DUMMYFUNCTION("""COMPUTED_VALUE"""),42913.0) -> 42913 | K29: =IFERROR(__xludf.DUMMYFUNCTION("""COMPUTED_VALUE"""),22.0) -> 22 | L29: =IFERROR(__xludf.DUMMYFUNCTION("""COMPUTED_VALUE"""),"YES") -> YES | M29: =IFERROR(__xludf.DUMMYFUNCTION("""COMPUTED_VALUE"""),"NYCT") -> NYCT | N29: =IFERROR(__xludf.DUMMYFUNCTION("""COMPUTED_VALUE"""),"KONE") -> KONE | O29: =IFERROR(__xludf.DUMMYFUNCTION("""COMPUTED_VALUE"""),"YES") -> YES | P29: =IFERROR(__xludf.DUMMYFUNCTION("""COMPUTED_VALUE"""),"NO") -> NO | Q29: =IFERROR(__xludf.DUMMYFUNCTION("""COMPUTED_VALUE"""),"NO") -> NO | R29: =IFERROR(__xludf.DUMMYFUNCTION("""COMPUTED_VALUE"""),"8030 mm (26' 4 1/8in)") -> 8030 mm (26' 4 1/8in) | S29: =IFERROR(__xludf.DUMMYFUNCTION("""COMPUTED_VALUE"""),109.0) -> 109 | T29: =IFERROR(__xludf.DUMMYFUNCTION("""COMPUTED_VALUE"""),"40in (NOMINAL), 996 mm") -> 40in (NOMINAL), 996 mm | U29: =IFERROR(__xludf.DUMMYFUNCTION("""COMPUTED_VALUE"""),"1/R/W mezzanine to platform for uptown 1 service") -> 1/R/W mezzanine to platform for uptown 1 service | V29: =IFERROR(__xludf.DUMMYFUNCTION("""COMPUTED_VALUE"""),"POINT (-74.013084 40.701675)") -> POINT (-74.013084 40.701675)
A30: =IFERROR(__xludf.DUMMYFUNCTION("""COMPUTED_VALUE"""),"Grand Central-42 St") -> Grand Central-42 St | B30: =IFERROR(__xludf.DUMMYFUNCTION("""COMPUTED_VALUE"""),"42nd St Line") -> 42nd St Line | C30: =IFERROR(__xludf.DUMMYFUNCTION("""COMPUTED_VALUE"""),"Manhattan") -> Manhattan | D30: =IFERROR(__xludf.DUMMYFUNCTION("""COMPUTED_VALUE"""),"Midtown") -> Midtown | E30: =IFERROR(__xludf.DUMMYFUNCTION("""COMPUTED_VALUE"""),1762.0) -> 1762 | F30: =IFERROR(__xludf.DUMMYFUNCTION("""COMPUTED_VALUE"""),3.3496874E7) -> 33496874 | G30: =IFERROR(__xludf.DUMMYFUNCTION("""COMPUTED_VALUE"""),2.0) -> 2 | H30: =IFERROR(__xludf.DUMMYFUNCTION("""COMPUTED_VALUE"""),"↗️") -> ↗️ | I30: =IFERROR(__xludf.DUMMYFUNCTION("""COMPUTED_VALUE"""),19937.0) -> 19937 | J30: =IFERROR(__xludf.DUMMYFUNCTION("""COMPUTED_VALUE"""),45430.0) -> 45430 | K30: =IFERROR(__xludf.DUMMYFUNCTION("""COMPUTED_VALUE"""),22.0) -> 22 | L30: =IFERROR(__xludf.DUMMYFUNCTION("""COMPUTED_VALUE"""),"YES") -> YES | M30: =IFERROR(__xludf.DUMMYFUNCTION("""COMPUTED_VALUE"""),"NYCT") -> NYCT | N30: =IFERROR(__xludf.DUMMYFUNCTION("""COMPUTED_VALUE"""),"OK") -> OK | O30: =IFERROR(__xludf.DUMMYFUNCTION("""COMPUTED_VALUE"""),"YES") -> YES | P30: =IFERROR(__xludf.DUMMYFUNCTION("""COMPUTED_VALUE"""),"NO") -> NO | Q30: =IFERROR(__xludf.DUMMYFUNCTION("""COMPUTED_VALUE"""),"NO") -> NO | R30: =IFERROR(__xludf.DUMMYFUNCTION("""COMPUTED_VALUE"""),"40'") -> 40' | S30: =IFERROR(__xludf.DUMMYFUNCTION("""COMPUTED_VALUE"""),123.0) -> 123 | T30: =IFERROR(__xludf.DUMMYFUNCTION("""COMPUTED_VALUE"""),40.0) -> 40 | U30: =IFERROR(__xludf.DUMMYFUNCTION("""COMPUTED_VALUE"""),"main mezzanine to central mezzanine above 7 platform") -> main mezzanine to central mezzanine above 7 platform | V30: =IFERROR(__xludf.DUMMYFUNCTION("""COMPUTED_VALUE"""),"POINT (-73.97644 40.7515)") -> POINT (-73.97644 40.7515)
A31: =IFERROR(__xludf.DUMMYFUNCTION("""COMPUTED_VALUE"""),"Grand Central-42 St") -> Grand Central-42 St | B31: =IFERROR(__xludf.DUMMYFUNCTION("""COMPUTED_VALUE"""),"42nd St Line") -> 42nd St Line | C31: =IFERROR(__xludf.DUMMYFUNCTION("""COMPUTED_VALUE"""),"Manhattan") -> Manhattan | D31: =IFERROR(__xludf.DUMMYFUNCTION("""COMPUTED_VALUE"""),"Midtown") -> Midtown | E31: =IFERROR(__xludf.DUMMYFUNCTION("""COMPUTED_VALUE"""),1762.0) -> 1762 | F31: =IFERROR(__xludf.DUMMYFUNCTION("""COMPUTED_VALUE"""),3.3496874E7) -> 33496874 | G31: =IFERROR(__xludf.DUMMYFUNCTION("""COMPUTED_VALUE"""),2.0) -> 2 | H31: =IFERROR(__xludf.DUMMYFUNCTION("""COMPUTED_VALUE"""),"↗️") -> ↗️ | I31: =IFERROR(__xludf.DUMMYFUNCTION("""COMPUTED_VALUE"""),32690.0) -> 32690 | J31: =IFERROR(__xludf.DUMMYFUNCTION("""COMPUTED_VALUE"""),43987.0) -> 43987 | K31: =IFERROR(__xludf.DUMMYFUNCTION("""COMPUTED_VALUE"""),22.0) -> 22 | L31: =IFERROR(__xludf.DUMMYFUNCTION("""COMPUTED_VALUE"""),"YES") -> YES | M31: =IFERROR(__xludf.DUMMYFUNCTION("""COMPUTED_VALUE"""),"NYCT") -> NYCT | N31: =IFERROR(__xludf.DUMMYFUNCTION("""COMPUTED_VALUE"""),"OK") -> OK | O31: =IFERROR(__xludf.DUMMYFUNCTION("""COMPUTED_VALUE"""),"YES") -> YES | P31: =IFERROR(__xludf.DUMMYFUNCTION("""COMPUTED_VALUE"""),"YES") -> YES | Q31: =IFERROR(__xludf.DUMMYFUNCTION("""COMPUTED_VALUE"""),"NO") -> NO | R31: =IFERROR(__xludf.DUMMYFUNCTION("""COMPUTED_VALUE"""),"18'") -> 18' | S31: =IFERROR(__xludf.DUMMYFUNCTION("""COMPUTED_VALUE"""),77.0) -> 77 | T31: =IFERROR(__xludf.DUMMYFUNCTION("""COMPUTED_VALUE"""),40.0) -> 40 | U31: =IFERROR(__xludf.DUMMYFUNCTION("""COMPUTED_VALUE"""),"42 St (between Park Ave & Lexington Ave) to main mezzanine for access to 4/5/6/7/S service") -> 42 St (between Park Ave & Lexington Ave) to main mezzanine for access to 4/5/6/7/S service | V31: =IFERROR(__xludf.DUMMYFUNCTION("""COMPUTED_VALUE"""),"POINT (-73.97695 40.752)") -> POINT (-73.97695 40.752)
A32: =IFERROR(__xludf.DUMMYFUNCTION("""COMPUTED_VALUE"""),"Roosevelt Island") -> Roosevelt Island | B32: =IFERROR(__xludf.DUMMYFUNCTION("""COMPUTED_VALUE"""),"63rd St Line") -> 63rd St Line | C32: =IFERROR(__xludf.DUMMYFUNCTION("""COMPUTED_VALUE"""),"Manhattan") -> Manhattan | D32: =IFERROR(__xludf.DUMMYFUNCTION("""COMPUTED_VALUE"""),"Roosevelt Island") -> Roosevelt Island | E32: =IFERROR(__xludf.DUMMYFUNCTION("""COMPUTED_VALUE"""),32810.0) -> 32810 | F32: =IFERROR(__xludf.DUMMYFUNCTION("""COMPUTED_VALUE"""),1885823.0) -> 1885823 | G32: =IFERROR(__xludf.DUMMYFUNCTION("""COMPUTED_VALUE"""),171.0) -> 171 | H32: =IFERROR(__xludf.DUMMYFUNCTION("""COMPUTED_VALUE"""),"↗️") -> ↗️ | I32: =IFERROR(__xludf.DUMMYFUNCTION("""COMPUTED_VALUE"""),32782.0) -> 32782 | J32: =IFERROR(__xludf.DUMMYFUNCTION("""COMPUTED_VALUE"""),39379.0) -> 39379 | K32: =IFERROR(__xludf.DUMMYFUNCTION("""COMPUTED_VALUE"""),22.0) -> 22 | L32: =IFERROR(__xludf.DUMMYFUNCTION("""COMPUTED_VALUE"""),"YES") -> YES | M32: =IFERROR(__xludf.DUMMYFUNCTION("""COMPUTED_VALUE"""),"NYCT") -> NYCT | N32: =IFERROR(__xludf.DUMMYFUNCTION("""COMPUTED_VALUE"""),"KONE") -> KONE | O32: =IFERROR(__xludf.DUMMYFUNCTION("""COMPUTED_VALUE"""),"YES") -> YES | P32: =IFERROR(__xludf.DUMMYFUNCTION("""COMPUTED_VALUE"""),"NO") -> NO | Q32: =IFERROR(__xludf.DUMMYFUNCTION("""COMPUTED_VALUE"""),"NO") -> NO | R32: =IFERROR(__xludf.DUMMYFUNCTION("""COMPUTED_VALUE"""),"14'") -> 14' | S32: =IFERROR(__xludf.DUMMYFUNCTION("""COMPUTED_VALUE"""),56.0) -> 56 | T32: =IFERROR(__xludf.DUMMYFUNCTION("""COMPUTED_VALUE"""),40.0) -> 40 | U32: =IFERROR(__xludf.DUMMYFUNCTION("""COMPUTED_VALUE"""),"Jamaica 179 St-bound platform to lower mezzanine") -> Jamaica 179 St-bound platform to lower mezzanine | V32: =IFERROR(__xludf.DUMMYFUNCTION("""COMPUTED_VALUE"""),"POINT (-73.952415 40.75867)") -> POINT (-73.952415 40.75867)
A33: =IFERROR(__xludf.DUMMYFUNCTION("""COMPUTED_VALUE"""),"34 St-Hudson Yards") -> 34 St-Hudson Yards | B33: =IFERROR(__xludf.DUMMYFUNCTION("""COMPUTED_VALUE"""),"Flushing Line") -> Flushing Line | C33: =IFERROR(__xludf.DUMMYFUNCTION("""COMPUTED_VALUE"""),"Manhattan") -> Manhattan | D33: =IFERROR(__xludf.DUMMYFUNCTION("""COMPUTED_VALUE"""),"Hell's Kitchen") -> Hell's Kitchen | E33: =IFERROR(__xludf.DUMMYFUNCTION("""COMPUTED_VALUE"""),42260.0) -> 42260 | F33: =IFERROR(__xludf.DUMMYFUNCTION("""COMPUTED_VALUE"""),6082370.0) -> 6082370 | G33: =IFERROR(__xludf.DUMMYFUNCTION("""COMPUTED_VALUE"""),39.0) -> 39 | H33: =IFERROR(__xludf.DUMMYFUNCTION("""COMPUTED_VALUE"""),"↗️") -> ↗️ | I33: =IFERROR(__xludf.DUMMYFUNCTION("""COMPUTED_VALUE"""),42260.0) -> 42260 | J33: =IFERROR(__xludf.DUMMYFUNCTION("""COMPUTED_VALUE"""),42260.0) -> 42260 | K33: =IFERROR(__xludf.DUMMYFUNCTION("""COMPUTED_VALUE"""),22.0) -> 22 | L33: =IFERROR(__xludf.DUMMYFUNCTION("""COMPUTED_VALUE"""),"YES") -> YES | M33: =IFERROR(__xludf.DUMMYFUNCTION("""COMPUTED_VALUE"""),"NYCT") -> NYCT | N33: =IFERROR(__xludf.DUMMYFUNCTION("""COMPUTED_VALUE"""),"KONE") -> KONE | O33: =IFERROR(__xludf.DUMMYFUNCTION("""COMPUTED_VALUE"""),"YES") -> YES | P33: =IFERROR(__xludf.DUMMYFUNCTION("""COMPUTED_VALUE"""),"NO") -> NO | Q33: =IFERROR(__xludf.DUMMYFUNCTION("""COMPUTED_VALUE"""),"NO") -> NO | R33: =IFERROR(__xludf.DUMMYFUNCTION("""COMPUTED_VALUE"""),"24,892 mm (81' 8in)") -> 24,892 mm (81' 8in) | S33: =IFERROR(__xludf.DUMMYFUNCTION("""COMPUTED_VALUE"""),283.0) -> 283 | T33: =IFERROR(__xludf.DUMMYFUNCTION("""COMPUTED_VALUE"""),"1000 mm (40in)") -> 1000 mm (40in) | U33: =IFERROR(__xludf.DUMMYFUNCTION("""COMPUTED_VALUE"""),"lower mezzanine to upper mezzanine for Hudson Blvd E exit (between 33 St & 34 St)") -> lower mezzanine to upper mezzanine for Hudson Blvd E exit (between 33 St & 34 St) | V33: =IFERROR(__xludf.DUMMYFUNCTION("""COMPUTED_VALUE"""),"POINT (-74.00191 40.755207)") -> POINT (-74.00191 40.755207)
A34: =IFERROR(__xludf.DUMMYFUNCTION("""COMPUTED_VALUE"""),"Brighton Beach") -> Brighton Beach | B34: =IFERROR(__xludf.DUMMYFUNCTION("""COMPUTED_VALUE"""),"Brighton Line") -> Brighton Line | C34: =IFERROR(__xludf.DUMMYFUNCTION("""COMPUTED_VALUE"""),"Brooklyn") -> Brooklyn | D34: =IFERROR(__xludf.DUMMYFUNCTION("""COMPUTED_VALUE"""),"Brighton Beach") -> Brighton Beach | E34: =IFERROR(__xludf.DUMMYFUNCTION("""COMPUTED_VALUE"""),2792.0) -> 2792 | F34: =IFERROR(__xludf.DUMMYFUNCTION("""COMPUTED_VALUE"""),2493646.0) -> 2493646 | G34: =IFERROR(__xludf.DUMMYFUNCTION("""COMPUTED_VALUE"""),137.0) -> 137 | H34: =IFERROR(__xludf.DUMMYFUNCTION("""COMPUTED_VALUE"""),"↗️") -> ↗️ | I34: =IFERROR(__xludf.DUMMYFUNCTION("""COMPUTED_VALUE"""),29677.0) -> 29677 | J34: =IFERROR(__xludf.DUMMYFUNCTION("""COMPUTED_VALUE"""),37504.0) -> 37504 | K34: =IFERROR(__xludf.DUMMYFUNCTION("""COMPUTED_VALUE"""),22.0) -> 22 | L34: =IFERROR(__xludf.DUMMYFUNCTION("""COMPUTED_VALUE"""),"YES") -> YES | M34: =IFERROR(__xludf.DUMMYFUNCTION("""COMPUTED_VALUE"""),"NYCT") -> NYCT | N34: =IFERROR(__xludf.DUMMYFUNCTION("""COMPUTED_VALUE"""),"FUJITEC") -> FUJITEC | O34: =IFERROR(__xludf.DUMMYFUNCTION("""COMPUTED_VALUE"""),"YES") -> YES | P34: =IFERROR(__xludf.DUMMYFUNCTION("""COMPUTED_VALUE"""),"YES") -> YES | Q34: =IFERROR(__xludf.DUMMYFUNCTION("""COMPUTED_VALUE"""),"YES") -> YES | R34: =IFERROR(__xludf.DUMMYFUNCTION("""COMPUTED_VALUE"""),"14'") -> 14' | S34: =IFERROR(__xludf.DUMMYFUNCTION("""COMPUTED_VALUE"""),59.0) -> 59 | T34: =IFERROR(__xludf.DUMMYFUNCTION("""COMPUTED_VALUE"""),24.0) -> 24 | U34: =IFERROR(__xludf.DUMMYFUNCTION("""COMPUTED_VALUE"""),"Brighton 7 St & Brighton Beach Ave (NE corner) to mezzanine") -> Brighton 7 St & Brighton Beach Ave (NE corner) to mezzanine | V34: =IFERROR(__xludf.DUMMYFUNCTION("""COMPUTED_VALUE"""),"POINT (-73.96028 40.57797)") -> POINT (-73.96028 40.57797)
A35: =IFERROR(__xludf.DUMMYFUNCTION("""COMPUTED_VALUE"""),"Jay St-Metro Tech") -> Jay St-Metro Tech | B35: =IFERROR(__xludf.DUMMYFUNCTION("""COMPUTED_VALUE"""),"") | C35: =IFERROR(__xludf.DUMMYFUNCTION("""COMPUTED_VALUE"""),"") | D35: =IFERROR(__xludf.DUMMYFUNCTION("""COMPUTED_VALUE"""),"") | E35: =IFERROR(__xludf.DUMMYFUNCTION("""COMPUTED_VALUE"""),"") | F35: =IFERROR(__xludf.DUMMYFUNCTION("""COMPUTED_VALUE"""),"") | G35: =IFERROR(__xludf.DUMMYFUNCTION("""COMPUTED_VALUE"""),"") | H35: =IFERROR(__xludf.DUMMYFUNCTION("""COMPUTED_VALUE"""),"↗️") -> ↗️ | I35: =IFERROR(__xludf.DUMMYFUNCTION("""COMPUTED_VALUE"""),21306.0) -> 21306 | J35: =IFERROR(__xludf.DUMMYFUNCTION("""COMPUTED_VALUE"""),44273.0) -> 44273 | K35: =IFERROR(__xludf.DUMMYFUNCTION("""COMPUTED_VALUE"""),22.0) -> 22 | L35: =IFERROR(__xludf.DUMMYFUNCTION("""COMPUTED_VALUE"""),"YES") -> YES | M35: =IFERROR(__xludf.DUMMYFUNCTION("""COMPUTED_VALUE"""),"NYCT") -> NYCT | N35: =IFERROR(__xludf.DUMMYFUNCTION("""COMPUTED_VALUE"""),"OK") -> OK | O35: =IFERROR(__xludf.DUMMYFUNCTION("""COMPUTED_VALUE"""),"YES") -> YES | P35: =IFERROR(__xludf.DUMMYFUNCTION("""COMPUTED_VALUE"""),"YES") -> YES | Q35: =IFERROR(__xludf.DUMMYFUNCTION("""COMPUTED_VALUE"""),"YES") -> YES | R35: =IFERROR(__xludf.DUMMYFUNCTION("""COMPUTED_VALUE"""),"21'") -> 21' | S35: =IFERROR(__xludf.DUMMYFUNCTION("""COMPUTED_VALUE"""),78.0) -> 78 | T35: =IFERROR(__xludf.DUMMYFUNCTION("""COMPUTED_VALUE"""),40.0) -> 40 | U35: =IFERROR(__xludf.DUMMYFUNCTION("""COMPUTED_VALUE"""),"A/C/F/R mezzanine to Jay St & Willoughby St (NW corner)") -> A/C/F/R mezzanine to Jay St & Willoughby St (NW corner) | V35: =IFERROR(__xludf.DUMMYFUNCTION("""COMPUTED_VALUE"""),"POINT (-73.98754 40.6924)") -> POINT (-73.98754 40.6924)
A36: =IFERROR(__xludf.DUMMYFUNCTION("""COMPUTED_VALUE"""),"Bowling Green") -> Bowling Green | B36: =IFERROR(__xludf.DUMMYFUNCTION("""COMPUTED_VALUE"""),"Lexington Av Line") -> Lexington Av Line | C36: =IFERROR(__xludf.DUMMYFUNCTION("""COMPUTED_VALUE"""),"Manhattan") -> Manhattan | D36: =IFERROR(__xludf.DUMMYFUNCTION("""COMPUTED_VALUE"""),"Financial District") -> Financial District | E36: =IFERROR(__xludf.DUMMYFUNCTION("""COMPUTED_VALUE"""),2018.0) -> 2018 | F36: =IFERROR(__xludf.DUMMYFUNCTION("""COMPUTED_VALUE"""),4676646.0) -> 4676646 | G36: =IFERROR(__xludf.DUMMYFUNCTION("""COMPUTED_VALUE"""),62.0) -> 62 | H36: =IFERROR(__xludf.DUMMYFUNCTION("""COMPUTED_VALUE"""),"↗️") -> ↗️ | I36: =IFERROR(__xludf.DUMMYFUNCTION("""COMPUTED_VALUE"""),28216.0) -> 28216 | J36: =IFERROR(__xludf.DUMMYFUNCTION("""COMPUTED_VALUE"""),45231.0) -> 45231 | K36: =IFERROR(__xludf.DUMMYFUNCTION("""COMPUTED_VALUE"""),22.0) -> 22 | L36: =IFERROR(__xludf.DUMMYFUNCTION("""COMPUTED_VALUE"""),"YES") -> YES | M36: =IFERROR(__xludf.DUMMYFUNCTION("""COMPUTED_VALUE"""),"NYCT") -> NYCT | N36: =IFERROR(__xludf.DUMMYFUNCTION("""COMPUTED_VALUE"""),"KONE") -> KONE | O36: =IFERROR(__xludf.DUMMYFUNCTION("""COMPUTED_VALUE"""),"YES") -> YES | P36: =IFERROR(__xludf.DUMMYFUNCTION("""COMPUTED_VALUE"""),"YES") -> YES | Q36: =IFERROR(__xludf.DUMMYFUNCTION("""COMPUTED_VALUE"""),"YES") -> YES | R36: =IFERROR(__xludf.DUMMYFUNCTION("""COMPUTED_VALUE"""),"16'") -> 16' | S36: =IFERROR(__xludf.DUMMYFUNCTION("""COMPUTED_VALUE"""),67.0) -> 67 | T36: =IFERROR(__xludf.DUMMYFUNCTION("""COMPUTED_VALUE"""),40.0) -> 40 | U36: =IFERROR(__xludf.DUMMYFUNCTION("""COMPUTED_VALUE"""),"uptown 4/5 mezzanine to Bowling Green Park on Whitehall St") -> uptown 4/5 mezzanine to Bowling Green Park on Whitehall St | V36: =IFERROR(__xludf.DUMMYFUNCTION("""COMPUTED_VALUE"""),"POINT (-74.01359 40.70465)") -> POINT (-74.01359 40.70465)
A37: =IFERROR(__xludf.DUMMYFUNCTION("""COMPUTED_VALUE"""),"34 St-Hudson Yards") -> 34 St-Hudson Yards | B37: =IFERROR(__xludf.DUMMYFUNCTION("""COMPUTED_VALUE"""),"Flushing Line") -> Flushing Line | C37: =IFERROR(__xludf.DUMMYFUNCTION("""COMPUTED_VALUE"""),"Manhattan") -> Manhattan | D37: =IFERROR(__xludf.DUMMYFUNCTION("""COMPUTED_VALUE"""),"Hell's Kitchen") -> Hell's Kitchen | E37: =IFERROR(__xludf.DUMMYFUNCTION("""COMPUTED_VALUE"""),42260.0) -> 42260 | F37: =IFERROR(__xludf.DUMMYFUNCTION("""COMPUTED_VALUE"""),6082370.0) -> 6082370 | G37: =IFERROR(__xludf.DUMMYFUNCTION("""COMPUTED_VALUE"""),39.0) -> 39 | H37: =IFERROR(__xludf.DUMMYFUNCTION("""COMPUTED_VALUE"""),"↗️") -> ↗️ | I37: =IFERROR(__xludf.DUMMYFUNCTION("""COMPUTED_VALUE"""),43343.0) -> 43343 | J37: =IFERROR(__xludf.DUMMYFUNCTION("""COMPUTED_VALUE"""),43343.0) -> 43343 | K37: =IFERROR(__xludf.DUMMYFUNCTION("""COMPUTED_VALUE"""),22.0) -> 22 | L37: =IFERROR(__xludf.DUMMYFUNCTION("""COMPUTED_VALUE"""),"YES") -> YES | M37: =IFERROR(__xludf.DUMMYFUNCTION("""COMPUTED_VALUE"""),"NYCT") -> NYCT | N37: =IFERROR(__xludf.DUMMYFUNCTION("""COMPUTED_VALUE"""),"SCHINDLER") -> SCHINDLER | O37: =IFERROR(__xludf.DUMMYFUNCTION("""COMPUTED_VALUE"""),"YES") -> YES | P37: =IFERROR(__xludf.DUMMYFUNCTION("""COMPUTED_VALUE"""),"NO") -> NO | Q37: =IFERROR(__xludf.DUMMYFUNCTION("""COMPUTED_VALUE"""),"NO") -> NO | R37: =IFERROR(__xludf.DUMMYFUNCTION("""COMPUTED_VALUE"""),"28'") -> 28' | S37: =IFERROR(__xludf.DUMMYFUNCTION("""COMPUTED_VALUE"""),109.0) -> 109 | T37: =IFERROR(__xludf.DUMMYFUNCTION("""COMPUTED_VALUE"""),24.0) -> 24 | U37: =IFERROR(__xludf.DUMMYFUNCTION("""COMPUTED_VALUE"""),"upper mezzanine (Hudson Blvd E & 35 St) to lower mezzanine") -> upper mezzanine (Hudson Blvd E & 35 St) to lower mezzanine | V37: =IFERROR(__xludf.DUMMYFUNCTION("""COMPUTED_VALUE"""),"POINT (-74.001144 40.75607)") -> POINT (-74.001144 40.75607)
A38: =IFERROR(__xludf.DUMMYFUNCTION("""COMPUTED_VALUE"""),"President St-Medgar Evers College") -> President St-Medgar Evers College | B38: =IFERROR(__xludf.DUMMYFUNCTION("""COMPUTED_VALUE"""),"Nostrand Av Line") -> Nostrand Av Line | C38: =IFERROR(__xludf.DUMMYFUNCTION("""COMPUTED_VALUE"""),"Brooklyn") -> Brooklyn | D38: =IFERROR(__xludf.DUMMYFUNCTION("""COMPUTED_VALUE"""),"Crown Heights") -> Crown Heights | E38: =IFERROR(__xludf.DUMMYFUNCTION("""COMPUTED_VALUE"""),7541.0) -> 7541 | F38: =IFERROR(__xludf.DUMMYFUNCTION("""COMPUTED_VALUE"""),749838.0) -> 749838 | G38: =IFERROR(__xludf.DUMMYFUNCTION("""COMPUTED_VALUE"""),338.0) -> 338 | H38: =IFERROR(__xludf.DUMMYFUNCTION("""COMPUTED_VALUE"""),"↗️") -> ↗️ | I38: =IFERROR(__xludf.DUMMYFUNCTION("""COMPUTED_VALUE"""),14255.0) -> 14255 | J38: =IFERROR(__xludf.DUMMYFUNCTION("""COMPUTED_VALUE"""),37336.0) -> 37336 | K38: =IFERROR(__xludf.DUMMYFUNCTION("""COMPUTED_VALUE"""),22.0) -> 22 | L38: =IFERROR(__xludf.DUMMYFUNCTION("""COMPUTED_VALUE"""),"YES") -> YES | M38: =IFERROR(__xludf.DUMMYFUNCTION("""COMPUTED_VALUE"""),"NYCT") -> NYCT | N38: =IFERROR(__xludf.DUMMYFUNCTION("""COMPUTED_VALUE"""),"FUJITEC") -> FUJITEC | O38: =IFERROR(__xludf.DUMMYFUNCTION("""COMPUTED_VALUE"""),"YES") -> YES | P38: =IFERROR(__xludf.DUMMYFUNCTION("""COMPUTED_VALUE"""),"NO") -> NO | Q38: =IFERROR(__xludf.DUMMYFUNCTION("""COMPUTED_VALUE"""),"NO") -> NO | R38: =IFERROR(__xludf.DUMMYFUNCTION("""COMPUTED_VALUE"""),"23'") -> 23' | S38: =IFERROR(__xludf.DUMMYFUNCTION("""COMPUTED_VALUE"""),84.0) -> 84 | T38: =IFERROR(__xludf.DUMMYFUNCTION("""COMPUTED_VALUE"""),40.0) -> 40 | U38: =IFERROR(__xludf.DUMMYFUNCTION("""COMPUTED_VALUE"""),"platform to mezzanine for President St & Nostrand Ave exit") -> platform to mezzanine for President St & Nostrand Ave exit | V38: =IFERROR(__xludf.DUMMYFUNCTION("""COMPUTED_VALUE"""),"POINT (-73.95068 40.667908)") -> POINT (-73.95068 40.667908)
A39: =IFERROR(__xludf.DUMMYFUNCTION("""COMPUTED_VALUE"""),"86 St") -> 86 St | B39: =IFERROR(__xludf.DUMMYFUNCTION("""COMPUTED_VALUE"""),"4 Av Line") -> 4 Av Line | C39: =IFERROR(__xludf.DUMMYFUNCTION("""COMPUTED_VALUE"""),"Brooklyn") -> Brooklyn | D39: =IFERROR(__xludf.DUMMYFUNCTION("""COMPUTED_VALUE"""),"Bay Ridge") -> Bay Ridge | E39: =IFERROR(__xludf.DUMMYFUNCTION("""COMPUTED_VALUE"""),5859.0) -> 5859 | F39: =IFERROR(__xludf.DUMMYFUNCTION("""COMPUTED_VALUE"""),2580130.0) -> 2580130 | G39: =IFERROR(__xludf.DUMMYFUNCTION("""COMPUTED_VALUE"""),135.0) -> 135 | H39: =IFERROR(__xludf.DUMMYFUNCTION("""COMPUTED_VALUE"""),"↗️") -> ↗️ | I39: =IFERROR(__xludf.DUMMYFUNCTION("""COMPUTED_VALUE"""),42736.0) -> 42736 | J39: =IFERROR(__xludf.DUMMYFUNCTION("""COMPUTED_VALUE"""),42736.0) -> 42736 | K39: =IFERROR(__xludf.DUMMYFUNCTION("""COMPUTED_VALUE"""),22.0) -> 22 | L39: =IFERROR(__xludf.DUMMYFUNCTION("""COMPUTED_VALUE"""),"YES") -> YES | M39: =IFERROR(__xludf.DUMMYFUNCTION("""COMPUTED_VALUE"""),"NYCT") -> NYCT | N39: =IFERROR(__xludf.DUMMYFUNCTION("""COMPUTED_VALUE"""),"KONE") -> KONE | O39: =IFERROR(__xludf.DUMMYFUNCTION("""COMPUTED_VALUE"""),"YES") -> YES | P39: =IFERROR(__xludf.DUMMYFUNCTION("""COMPUTED_VALUE"""),"NO") -> NO | Q39: =IFERROR(__xludf.DUMMYFUNCTION("""COMPUTED_VALUE"""),"NO") -> NO | R39: =IFERROR(__xludf.DUMMYFUNCTION("""COMPUTED_VALUE"""),"13719 mm (45' 0 1/8in)") -> 13719 mm (45' 0 1/8in) | S39: =IFERROR(__xludf.DUMMYFUNCTION("""COMPUTED_VALUE"""),164.0) -> 164 | T39: =IFERROR(__xludf.DUMMYFUNCTION("""COMPUTED_VALUE"""),"40in (NOMINAL), 996 mm") -> 40in (NOMINAL), 996 mm | U39: =IFERROR(__xludf.DUMMYFUNCTION("""COMPUTED_VALUE"""),"upper mezzanine (86 St & 2nd Ave) to lower mezzanine") -> upper mezzanine (86 St & 2nd Ave) to lower mezzanine | V39: =IFERROR(__xludf.DUMMYFUNCTION("""COMPUTED_VALUE"""),"POINT (-73.951416 40.77767)") -> POINT (-73.951416 40.77767)
A40: =IFERROR(__xludf.DUMMYFUNCTION("""COMPUTED_VALUE"""),"72 St") -> 72 St | B40: =IFERROR(__xludf.DUMMYFUNCTION("""COMPUTED_VALUE"""),"Broadway-7 Av Line") -> Broadway-7 Av Line | C40: =IFERROR(__xludf.DUMMYFUNCTION("""COMPUTED_VALUE"""),"Manhattan") -> Manhattan | D40: =IFERROR(__xludf.DUMMYFUNCTION("""COMPUTED_VALUE"""),"Upper West Side") -> Upper West Side | E40: =IFERROR(__xludf.DUMMYFUNCTION("""COMPUTED_VALUE"""),1762.0) -> 1762 | F40: =IFERROR(__xludf.DUMMYFUNCTION("""COMPUTED_VALUE"""),9752193.0) -> 9752193 | G40: =IFERROR(__xludf.DUMMYFUNCTION("""COMPUTED_VALUE"""),22.0) -> 22 | H40: =IFERROR(__xludf.DUMMYFUNCTION("""COMPUTED_VALUE"""),"↗️") -> ↗️ | I40: =IFERROR(__xludf.DUMMYFUNCTION("""COMPUTED_VALUE"""),42736.0) -> 42736 | J40: =IFERROR(__xludf.DUMMYFUNCTION("""COMPUTED_VALUE"""),42736.0) -> 42736 | K40: =IFERROR(__xludf.DUMMYFUNCTION("""COMPUTED_VALUE"""),22.0) -> 22 | L40: =IFERROR(__xludf.DUMMYFUNCTION("""COMPUTED_VALUE"""),"YES") -> YES | M40: =IFERROR(__xludf.DUMMYFUNCTION("""COMPUTED_VALUE"""),"NYCT") -> NYCT | N40: =IFERROR(__xludf.DUMMYFUNCTION("""COMPUTED_VALUE"""),"SCHINDLER") -> SCHINDLER | O40: =IFERROR(__xludf.DUMMYFUNCTION("""COMPUTED_VALUE"""),"YES") -> YES | P40: =IFERROR(__xludf.DUMMYFUNCTION("""COMPUTED_VALUE"""),"NO") -> NO | Q40: =IFERROR(__xludf.DUMMYFUNCTION("""COMPUTED_VALUE"""),"NO") -> NO | R40: =IFERROR(__xludf.DUMMYFUNCTION("""COMPUTED_VALUE"""),"4953 mm (16' 1/4in)") -> 4953 mm (16' 1/4in) | S40: =IFERROR(__xludf.DUMMYFUNCTION("""COMPUTED_VALUE"""),0.0) -> 0 | U40: =IFERROR(__xludf.DUMMYFUNCTION("""COMPUTED_VALUE"""),"platform to lower mezzanine") -> platform to lower mezzanine | V40: =IFERROR(__xludf.DUMMYFUNCTION("""COMPUTED_VALUE"""),"POINT (-73.959206 40.76762)") -> POINT (-73.959206 40.76762)
A41: =IFERROR(__xludf.DUMMYFUNCTION("""COMPUTED_VALUE"""),"34 St-Herald Sq") -> 34 St-Herald Sq | B41: =IFERROR(__xludf.DUMMYFUNCTION("""COMPUTED_VALUE"""),"Broadway Line") -> Broadway Line | C41: =IFERROR(__xludf.DUMMYFUNCTION("""COMPUTED_VALUE"""),"Manhattan") -> Manhattan | D41: =IFERROR(__xludf.DUMMYFUNCTION("""COMPUTED_VALUE"""),"Midtown") -> Midtown | E41: =IFERROR(__xludf.DUMMYFUNCTION("""COMPUTED_VALUE"""),6580.0) -> 6580 | F41: =IFERROR(__xludf.DUMMYFUNCTION("""COMPUTED_VALUE"""),2.5012549E7) -> 25012549 | G41: =IFERROR(__xludf.DUMMYFUNCTION("""COMPUTED_VALUE"""),3.0) -> 3 | H41: =IFERROR(__xludf.DUMMYFUNCTION("""COMPUTED_VALUE"""),"↗️") -> ↗️ | I41: =IFERROR(__xludf.DUMMYFUNCTION("""COMPUTED_VALUE"""),14960.0) -> 14960 | J41: =IFERROR(__xludf.DUMMYFUNCTION("""COMPUTED_VALUE"""),39046.0) -> 39046 | K41: =IFERROR(__xludf.DUMMYFUNCTION("""COMPUTED_VALUE"""),22.0) -> 22 | L41: =IFERROR(__xludf.DUMMYFUNCTION("""COMPUTED_VALUE"""),"YES") -> YES | M41: =IFERROR(__xludf.DUMMYFUNCTION("""COMPUTED_VALUE"""),"NYCT") -> NYCT | N41: =IFERROR(__xludf.DUMMYFUNCTION("""COMPUTED_VALUE"""),"FUJITEC") -> FUJITEC | O41: =IFERROR(__xludf.DUMMYFUNCTION("""COMPUTED_VALUE"""),"YES") -> YES | P41: =IFERROR(__xludf.DUMMYFUNCTION("""COMPUTED_VALUE"""),"NO") -> NO | Q41: =IFERROR(__xludf.DUMMYFUNCTION("""COMPUTED_VALUE"""),"NO") -> NO | R41: =IFERROR(__xludf.DUMMYFUNCTION("""COMPUTED_VALUE"""),"12'") -> 12' | S41: =IFERROR(__xludf.DUMMYFUNCTION("""COMPUTED_VALUE"""),55.0) -> 55 | T41: =IFERROR(__xludf.DUMMYFUNCTION("""COMPUTED_VALUE"""),24.0) -> 24 | U41: =IFERROR(__xludf.DUMMYFUNCTION("""COMPUTED_VALUE"""),"PATH mezzanine to intermediate mezzanine for 32 St & 6th Ave exit") -> PATH mezzanine to intermediate mezzanine for 32 St & 6th Ave exit | V41: =IFERROR(__xludf.DUMMYFUNCTION("""COMPUTED_VALUE"""),"POINT (-73.98867 40.748997)") -> POINT (-73.98867 40.748997)
A42: =IFERROR(__xludf.DUMMYFUNCTION("""COMPUTED_VALUE"""),"Court St") -> Court St | B42: =IFERROR(__xludf.DUMMYFUNCTION("""COMPUTED_VALUE"""),"") | C42: =IFERROR(__xludf.DUMMYFUNCTION("""COMPUTED_VALUE"""),"") | D42: =IFERROR(__xludf.DUMMYFUNCTION("""COMPUTED_VALUE"""),"") | E42: =IFERROR(__xludf.DUMMYFUNCTION("""COMPUTED_VALUE"""),"") | F42: =IFERROR(__xludf.DUMMYFUNCTION("""COMPUTED_VALUE"""),"") | G42: =IFERROR(__xludf.DUMMYFUNCTION("""COMPUTED_VALUE"""),"") | H42: =IFERROR(__xludf.DUMMYFUNCTION("""COMPUTED_VALUE"""),"↗️") -> ↗️ | I42: =IFERROR(__xludf.DUMMYFUNCTION("""COMPUTED_VALUE"""),8192.0) -> 8192 | J42: =IFERROR(__xludf.DUMMYFUNCTION("""COMPUTED_VALUE"""),37819.0) -> 37819 | K42: =IFERROR(__xludf.DUMMYFUNCTION("""COMPUTED_VALUE"""),22.0) -> 22 | L42: =IFERROR(__xludf.DUMMYFUNCTION("""COMPUTED_VALUE"""),"YES") -> YES | M42: =IFERROR(__xludf.DUMMYFUNCTION("""COMPUTED_VALUE"""),"NYCT") -> NYCT | N42: =IFERROR(__xludf.DUMMYFUNCTION("""COMPUTED_VALUE"""),"FUJITEC") -> FUJITEC | O42: =IFERROR(__xludf.DUMMYFUNCTION("""COMPUTED_VALUE"""),"YES") -> YES | P42: =IFERROR(__xludf.DUMMYFUNCTION("""COMPUTED_VALUE"""),"NO") -> NO | Q42: =IFERROR(__xludf.DUMMYFUNCTION("""COMPUTED_VALUE"""),"NO") -> NO | R42: =IFERROR(__xludf.DUMMYFUNCTION("""COMPUTED_VALUE"""),"22'") -> 22' | S42: =IFERROR(__xludf.DUMMYFUNCTION("""COMPUTED_VALUE"""),84.0) -> 84 | T42: =IFERROR(__xludf.DUMMYFUNCTION("""COMPUTED_VALUE"""),40.0) -> 40 | U42: =IFERROR(__xludf.DUMMYFUNCTION("""COMPUTED_VALUE"""),"2/3 mezzanine (Court St & Montague St) to lower mezzanine for R service in both directions") -> 2/3 mezzanine (Court St & Montague St) to lower mezzanine for R service in both directions | V42: =IFERROR(__xludf.DUMMYFUNCTION("""COMPUTED_VALUE"""),"POINT (-73.99118 40.69393)") -> POINT (-73.99118 40.69393)
A43: =IFERROR(__xludf.DUMMYFUNCTION("""COMPUTED_VALUE"""),"Lexington Av/59 St") -> Lexington Av/59 St | B43: =IFERROR(__xludf.DUMMYFUNCTION("""COMPUTED_VALUE"""),"Broadway Line") -> Broadway Line | C43: =IFERROR(__xludf.DUMMYFUNCTION("""COMPUTED_VALUE"""),"Manhattan") -> Manhattan | D43: =IFERROR(__xludf.DUMMYFUNCTION("""COMPUTED_VALUE"""),"Midtown") -> Midtown | E43: =IFERROR(__xludf.DUMMYFUNCTION("""COMPUTED_VALUE"""),7184.0) -> 7184 | F43: =IFERROR(__xludf.DUMMYFUNCTION("""COMPUTED_VALUE"""),1.1961525E7) -> 11961525 | G43: =IFERROR(__xludf.DUMMYFUNCTION("""COMPUTED_VALUE"""),14.0) -> 14 | H43: =IFERROR(__xludf.DUMMYFUNCTION("""COMPUTED_VALUE"""),"↗️") -> ↗️ | I43: =IFERROR(__xludf.DUMMYFUNCTION("""COMPUTED_VALUE"""),26967.0) -> 26967 | J43: =IFERROR(__xludf.DUMMYFUNCTION("""COMPUTED_VALUE"""),37738.0) -> 37738 | K43: =IFERROR(__xludf.DUMMYFUNCTION("""COMPUTED_VALUE"""),22.0) -> 22 | L43: =IFERROR(__xludf.DUMMYFUNCTION("""COMPUTED_VALUE"""),"YES") -> YES | M43: =IFERROR(__xludf.DUMMYFUNCTION("""COMPUTED_VALUE"""),"NYCT") -> NYCT | N43: =IFERROR(__xludf.DUMMYFUNCTION("""COMPUTED_VALUE"""),"FUJITEC") -> FUJITEC | O43: =IFERROR(__xludf.DUMMYFUNCTION("""COMPUTED_VALUE"""),"YES") -> YES | P43: =IFERROR(__xludf.DUMMYFUNCTION("""COMPUTED_VALUE"""),"NO") -> NO | Q43: =IFERROR(__xludf.DUMMYFUNCTION("""COMPUTED_VALUE"""),"NO") -> NO | R43: =IFERROR(__xludf.DUMMYFUNCTION("""COMPUTED_VALUE"""),"33'") -> 33' | S43: =IFERROR(__xludf.DUMMYFUNCTION("""COMPUTED_VALUE"""),117.0) -> 117 | T43: =IFERROR(__xludf.DUMMYFUNCTION("""COMPUTED_VALUE"""),40.0) -> 40 | U43: =IFERROR(__xludf.DUMMYFUNCTION("""COMPUTED_VALUE"""),"N/R/W platform to mezzanine for 3rd Ave & 60 St exit") -> N/R/W platform to mezzanine for 3rd Ave & 60 St exit | V43: =IFERROR(__xludf.DUMMYFUNCTION("""COMPUTED_VALUE"""),"POINT (-73.96629 40.762234)") -> POINT (-73.96629 40.762234)
A44: =IFERROR(__xludf.DUMMYFUNCTION("""COMPUTED_VALUE"""),"Atlantic Av-Barclays Ctr") -> Atlantic Av-Barclays Ctr | B44: =IFERROR(__xludf.DUMMYFUNCTION("""COMPUTED_VALUE"""),"") | C44: =IFERROR(__xludf.DUMMYFUNCTION("""COMPUTED_VALUE"""),"") | D44: =IFERROR(__xludf.DUMMYFUNCTION("""COMPUTED_VALUE"""),"") | E44: =IFERROR(__xludf.DUMMYFUNCTION("""COMPUTED_VALUE"""),"") | F44: =IFERROR(__xludf.DUMMYFUNCTION("""COMPUTED_VALUE"""),"") | G44: =IFERROR(__xludf.DUMMYFUNCTION("""COMPUTED_VALUE"""),"") | H44: =IFERROR(__xludf.DUMMYFUNCTION("""COMPUTED_VALUE"""),"↗️") -> ↗️ | J44: =IFERROR(__xludf.DUMMYFUNCTION("""COMPUTED_VALUE"""),41187.0) -> 41187 | K44: =IFERROR(__xludf.DUMMYFUNCTION("""COMPUTED_VALUE"""),22.0) -> 22 | L44: =IFERROR(__xludf.DUMMYFUNCTION("""COMPUTED_VALUE"""),"NO") -> NO | M44: =IFERROR(__xludf.DUMMYFUNCTION("""COMPUTED_VALUE"""),"Private Contractor") -> Private Contractor | N44: =IFERROR(__xludf.DUMMYFUNCTION("""COMPUTED_VALUE"""),"SCHINDLER") -> SCHINDLER | O44: =IFERROR(__xludf.DUMMYFUNCTION("""COMPUTED_VALUE"""),"YES") -> YES | P44: =IFERROR(__xludf.DUMMYFUNCTION("""COMPUTED_VALUE"""),"NO") -> NO | Q44: =IFERROR(__xludf.DUMMYFUNCTION("""COMPUTED_VALUE"""),"NO") -> NO | U44: =IFERROR(__xludf.DUMMYFUNCTION("""COMPUTED_VALUE"""),"B/Q mezzanine to Barclays Center plaza (SE corner of Atlantic Ave & Flatbush Ave)") -> B/Q mezzanine to Barclays Center plaza (SE corner of Atlantic Ave & Flatbush Ave) | V44: =IFERROR(__xludf.DUMMYFUNCTION("""COMPUTED_VALUE"""),"POINT (-73.9766 40.683598)") -> POINT (-73.9766 40.683598)
A45: =IFERROR(__xludf.DUMMYFUNCTION("""COMPUTED_VALUE"""),"South Ferry") -> South Ferry | B45: =IFERROR(__xludf.DUMMYFUNCTION("""COMPUTED_VALUE"""),"") | C45: =IFERROR(__xludf.DUMMYFUNCTION("""COMPUTED_VALUE"""),"") | D45: =IFERROR(__xludf.DUMMYFUNCTION("""COMPUTED_VALUE"""),"") | E45: =IFERROR(__xludf.DUMMYFUNCTION("""COMPUTED_VALUE"""),"") | F45: =IFERROR(__xludf.DUMMYFUNCTION("""COMPUTED_VALUE"""),"") | G45: =IFERROR(__xludf.DUMMYFUNCTION("""COMPUTED_VALUE"""),"") | H45: =IFERROR(__xludf.DUMMYFUNCTION("""COMPUTED_VALUE"""),"↗️") -> ↗️ | I45: =IFERROR(__xludf.DUMMYFUNCTION("""COMPUTED_VALUE"""),39888.0) -> 39888 | J45: =IFERROR(__xludf.DUMMYFUNCTION("""COMPUTED_VALUE"""),42913.0) -> 42913 | K45: =IFERROR(__xludf.DUMMYFUNCTION("""COMPUTED_VALUE"""),22.0) -> 22 | L45: =IFERROR(__xludf.DUMMYFUNCTION("""COMPUTED_VALUE"""),"YES") -> YES | M45: =IFERROR(__xludf.DUMMYFUNCTION("""COMPUTED_VALUE"""),"NYCT") -> NYCT | N45: =IFERROR(__xludf.DUMMYFUNCTION("""COMPUTED_VALUE"""),"SCHINDLER") -> SCHINDLER | O45: =IFERROR(__xludf.DUMMYFUNCTION("""COMPUTED_VALUE"""),"YES") -> YES | P45: =IFERROR(__xludf.DUMMYFUNCTION("""COMPUTED_VALUE"""),"YES") -> YES | Q45: =IFERROR(__xludf.DUMMYFUNCTION("""COMPUTED_VALUE"""),"YES") -> YES | R45: =IFERROR(__xludf.DUMMYFUNCTION("""COMPUTED_VALUE"""),"20'") -> 20' | S45: =IFERROR(__xludf.DUMMYFUNCTION("""COMPUTED_VALUE"""),80.0) -> 80 | T45: =IFERROR(__xludf.DUMMYFUNCTION("""COMPUTED_VALUE"""),"48in") -> 48in | U45: =IFERROR(__xludf.DUMMYFUNCTION("""COMPUTED_VALUE"""),"1/R/W mezzanine to Peter Minuit Plaza in front of South Ferry Terminal") -> 1/R/W mezzanine to Peter Minuit Plaza in front of South Ferry Terminal | V45: =IFERROR(__xludf.DUMMYFUNCTION("""COMPUTED_VALUE"""),"POINT (-74.01293 40.701744)") -> POINT (-74.01293 40.701744)
A46: =IFERROR(__xludf.DUMMYFUNCTION("""COMPUTED_VALUE"""),"Court Sq") -> Court Sq | B46: =IFERROR(__xludf.DUMMYFUNCTION("""COMPUTED_VALUE"""),"") | C46: =IFERROR(__xludf.DUMMYFUNCTION("""COMPUTED_VALUE"""),"") | D46: =IFERROR(__xludf.DUMMYFUNCTION("""COMPUTED_VALUE"""),"") | E46: =IFERROR(__xludf.DUMMYFUNCTION("""COMPUTED_VALUE"""),"") | F46: =IFERROR(__xludf.DUMMYFUNCTION("""COMPUTED_VALUE"""),"") | G46: =IFERROR(__xludf.DUMMYFUNCTION("""COMPUTED_VALUE"""),"") | H46: =IFERROR(__xludf.DUMMYFUNCTION("""COMPUTED_VALUE"""),"↗️") -> ↗️ | I46: =IFERROR(__xludf.DUMMYFUNCTION("""COMPUTED_VALUE"""),3.0) -> 3 | J46: =IFERROR(__xludf.DUMMYFUNCTION("""COMPUTED_VALUE"""),40330.0) -> 40330 | K46: =IFERROR(__xludf.DUMMYFUNCTION("""COMPUTED_VALUE"""),22.0) -> 22 | L46: =IFERROR(__xludf.DUMMYFUNCTION("""COMPUTED_VALUE"""),"NO") -> NO | M46: =IFERROR(__xludf.DUMMYFUNCTION("""COMPUTED_VALUE"""),"Private Contractor") -> Private Contractor | N46: =IFERROR(__xludf.DUMMYFUNCTION("""COMPUTED_VALUE"""),"AM") -> AM | O46: =IFERROR(__xludf.DUMMYFUNCTION("""COMPUTED_VALUE"""),"YES") -> YES | P46: =IFERROR(__xludf.DUMMYFUNCTION("""COMPUTED_VALUE"""),"NO") -> NO | Q46: =IFERROR(__xludf.DUMMYFUNCTION("""COMPUTED_VALUE"""),"NO") -> NO | U46: =IFERROR(__xludf.DUMMYFUNCTION("""COMPUTED_VALUE"""),"45 St & Jackson Ave to mezzanine for E/F & G service and access to 7") -> 45 St & Jackson Ave to mezzanine for E/F & G service and access to 7 | V46: =IFERROR(__xludf.DUMMYFUNCTION("""COMPUTED_VALUE"""),"POINT (-73.94432 40.74722)") -> POINT (-73.94432 40.74722)
A47: =IFERROR(__xludf.DUMMYFUNCTION("""COMPUTED_VALUE"""),"Jamaica Center-Parsons/Archer") -> Jamaica Center-Parsons/Archer | B47: =IFERROR(__xludf.DUMMYFUNCTION("""COMPUTED_VALUE"""),"Archer Av Line") -> Archer Av Line | C47: =IFERROR(__xludf.DUMMYFUNCTION("""COMPUTED_VALUE"""),"Queens") -> Queens | D47: =IFERROR(__xludf.DUMMYFUNCTION("""COMPUTED_VALUE"""),"Jamaica") -> Jamaica | E47: =IFERROR(__xludf.DUMMYFUNCTION("""COMPUTED_VALUE"""),32488.0) -> 32488 | F47: =IFERROR(__xludf.DUMMYFUNCTION("""COMPUTED_VALUE"""),6137267.0) -> 6137267 | G47: =IFERROR(__xludf.DUMMYFUNCTION("""COMPUTED_VALUE"""),38.0) -> 38 | H47: =IFERROR(__xludf.DUMMYFUNCTION("""COMPUTED_VALUE"""),"↗️") -> ↗️ | I47: =IFERROR(__xludf.DUMMYFUNCTION("""COMPUTED_VALUE"""),32478.0) -> 32478 | J47: =IFERROR(__xludf.DUMMYFUNCTION("""COMPUTED_VALUE"""),39954.0) -> 39954 | K47: =IFERROR(__xludf.DUMMYFUNCTION("""COMPUTED_VALUE"""),22.0) -> 22 | L47: =IFERROR(__xludf.DUMMYFUNCTION("""COMPUTED_VALUE"""),"YES") -> YES | M47: =IFERROR(__xludf.DUMMYFUNCTION("""COMPUTED_VALUE"""),"NYCT") -> NYCT | N47: =IFERROR(__xludf.DUMMYFUNCTION("""COMPUTED_VALUE"""),"KONE") -> KONE | O47: =IFERROR(__xludf.DUMMYFUNCTION("""COMPUTED_VALUE"""),"YES") -> YES | P47: =IFERROR(__xludf.DUMMYFUNCTION("""COMPUTED_VALUE"""),"YES") -> YES | Q47: =IFERROR(__xludf.DUMMYFUNCTION("""COMPUTED_VALUE"""),"YES") -> YES | R47: =IFERROR(__xludf.DUMMYFUNCTION("""COMPUTED_VALUE"""),"18'") -> 18' | S47: =IFERROR(__xludf.DUMMYFUNCTION("""COMPUTED_VALUE"""),74.0) -> 74 | T47: =IFERROR(__xludf.DUMMYFUNCTION("""COMPUTED_VALUE"""),"40in") -> 40in | U47: =IFERROR(__xludf.DUMMYFUNCTION("""COMPUTED_VALUE"""),"mezzanine to Parsons Blvd & Archer Ave (SW corner)") -> mezzanine to Parsons Blvd & Archer Ave (SW corner) | V47: =IFERROR(__xludf.DUMMYFUNCTION("""COMPUTED_VALUE"""),"POINT (-73.801895 40.701855)") -> POINT (-73.801895 40.701855)
A48: =IFERROR(__xludf.DUMMYFUNCTION("""COMPUTED_VALUE"""),"Fulton St") -> Fulton St | B48: =IFERROR(__xludf.DUMMYFUNCTION("""COMPUTED_VALUE"""),"Broadway-7 Av Line") -> Broadway-7 Av Line | C48: =IFERROR(__xludf.DUMMYFUNCTION("""COMPUTED_VALUE"""),"Manhattan") -> Manhattan | D48: =IFERROR(__xludf.DUMMYFUNCTION("""COMPUTED_VALUE"""),"Financial District") -> Financial District | E48: =IFERROR(__xludf.DUMMYFUNCTION("""COMPUTED_VALUE"""),6757.0) -> 6757 | F48: =IFERROR(__xludf.DUMMYFUNCTION("""COMPUTED_VALUE"""),1.9221396E7) -> 19221396 | G48: =IFERROR(__xludf.DUMMYFUNCTION("""COMPUTED_VALUE"""),5.0) -> 5 | H48: =IFERROR(__xludf.DUMMYFUNCTION("""COMPUTED_VALUE"""),"↗️") -> ↗️ | J48: =IFERROR(__xludf.DUMMYFUNCTION("""COMPUTED_VALUE"""),41953.0) -> 41953 | K48: =IFERROR(__xludf.DUMMYFUNCTION("""COMPUTED_VALUE"""),22.0) -> 22 | L48: =IFERROR(__xludf.DUMMYFUNCTION("""COMPUTED_VALUE"""),"NO") -> NO | M48: =IFERROR(__xludf.DUMMYFUNCTION("""COMPUTED_VALUE"""),"Private Contractor") -> Private Contractor | N48: =IFERROR(__xludf.DUMMYFUNCTION("""COMPUTED_VALUE"""),"SCHINDLER") -> SCHINDLER | O48: =IFERROR(__xludf.DUMMYFUNCTION("""COMPUTED_VALUE"""),"YES") -> YES | P48: =IFERROR(__xludf.DUMMYFUNCTION("""COMPUTED_VALUE"""),"NO") -> NO | Q48: =IFERROR(__xludf.DUMMYFUNCTION("""COMPUTED_VALUE"""),"NO") -> NO | U48: =IFERROR(__xludf.DUMMYFUNCTION("""COMPUTED_VALUE"""),"lower concourse to Transit Center exit (John St east of Broadway)") -> lower concourse to Transit Center exit (John St east of Broadway) | V48: =IFERROR(__xludf.DUMMYFUNCTION("""COMPUTED_VALUE"""),"POINT (-74.00936 40.71032)") -> POINT (-74.00936 40.71032)
A49: =IFERROR(__xludf.DUMMYFUNCTION("""COMPUTED_VALUE"""),"Fulton St") -> Fulton St | B49: =IFERROR(__xludf.DUMMYFUNCTION("""COMPUTED_VALUE"""),"Broadway-7 Av Line") -> Broadway-7 Av Line | C49: =IFERROR(__xludf.DUMMYFUNCTION("""COMPUTED_VALUE"""),"Manhattan") -> Manhattan | D49: =IFERROR(__xludf.DUMMYFUNCTION("""COMPUTED_VALUE"""),"Financial District") -> Financial District | E49: =IFERROR(__xludf.DUMMYFUNCTION("""COMPUTED_VALUE"""),6757.0) -> 6757 | F49: =IFERROR(__xludf.DUMMYFUNCTION("""COMPUTED_VALUE"""),1.9221396E7) -> 19221396 | G49: =IFERROR(__xludf.DUMMYFUNCTION("""COMPUTED_VALUE"""),5.0) -> 5 | H49: =IFERROR(__xludf.DUMMYFUNCTION("""COMPUTED_VALUE"""),"↗️") -> ↗️ | J49: =IFERROR(__xludf.DUMMYFUNCTION("""COMPUTED_VALUE"""),41953.0) -> 41953 | K49: =IFERROR(__xludf.DUMMYFUNCTION("""COMPUTED_VALUE"""),22.0) -> 22 | L49: =IFERROR(__xludf.DUMMYFUNCTION("""COMPUTED_VALUE"""),"NO") -> NO | M49: =IFERROR(__xludf.DUMMYFUNCTION("""COMPUTED_VALUE"""),"Private Contractor") -> Private Contractor | N49: =IFERROR(__xludf.DUMMYFUNCTION("""COMPUTED_VALUE"""),"THYSSEN-KRUPP") -> THYSSEN-KRUPP | O49: =IFERROR(__xludf.DUMMYFUNCTION("""COMPUTED_VALUE"""),"YES") -> YES | P49: =IFERROR(__xludf.DUMMYFUNCTION("""COMPUTED_VALUE"""),"NO") -> NO | Q49: =IFERROR(__xludf.DUMMYFUNCTION("""COMPUTED_VALUE"""),"NO") -> NO | U49: =IFERROR(__xludf.DUMMYFUNCTION("""COMPUTED_VALUE"""),"uptown 4/5 platform level to Transit Center exit (NE corner of John St & Broadway)") -> uptown 4/5 platform level to Transit Center exit (NE corner of John St & Broadway) | V49: =IFERROR(__xludf.DUMMYFUNCTION("""COMPUTED_VALUE"""),"POINT (-74.009094 40.710453)") -> POINT (-74.009094 40.710453)
A50: =IFERROR(__xludf.DUMMYFUNCTION("""COMPUTED_VALUE"""),"Jamaica Center-Parsons/Archer") -> Jamaica Center-Parsons/Archer | B50: =IFERROR(__xludf.DUMMYFUNCTION("""COMPUTED_VALUE"""),"Archer Av Line") -> Archer Av Line | C50: =IFERROR(__xludf.DUMMYFUNCTION("""COMPUTED_VALUE"""),"Queens") -> Queens | D50: =IFERROR(__xludf.DUMMYFUNCTION("""COMPUTED_VALUE"""),"Jamaica") -> Jamaica | E50: =IFERROR(__xludf.DUMMYFUNCTION("""COMPUTED_VALUE"""),32488.0) -> 32488 | F50: =IFERROR(__xludf.DUMMYFUNCTION("""COMPUTED_VALUE"""),6137267.0) -> 6137267 | G50: =IFERROR(__xludf.DUMMYFUNCTION("""COMPUTED_VALUE"""),38.0) -> 38 | H50: =IFERROR(__xludf.DUMMYFUNCTION("""COMPUTED_VALUE"""),"↗️") -> ↗️ | I50: =IFERROR(__xludf.DUMMYFUNCTION("""COMPUTED_VALUE"""),32478.0) -> 32478 | J50: =IFERROR(__xludf.DUMMYFUNCTION("""COMPUTED_VALUE"""),39953.0) -> 39953 | K50: =IFERROR(__xludf.DUMMYFUNCTION("""COMPUTED_VALUE"""),22.0) -> 22 | L50: =IFERROR(__xludf.DUMMYFUNCTION("""COMPUTED_VALUE"""),"YES") -> YES | M50: =IFERROR(__xludf.DUMMYFUNCTION("""COMPUTED_VALUE"""),"NYCT") -> NYCT | N50: =IFERROR(__xludf.DUMMYFUNCTION("""COMPUTED_VALUE"""),"KONE") -> KONE | O50: =IFERROR(__xludf.DUMMYFUNCTION("""COMPUTED_VALUE"""),"YES") -> YES | P50: =IFERROR(__xludf.DUMMYFUNCTION("""COMPUTED_VALUE"""),"NO") -> NO | Q50: =IFERROR(__xludf.DUMMYFUNCTION("""COMPUTED_VALUE"""),"NO") -> NO | R50: =IFERROR(__xludf.DUMMYFUNCTION("""COMPUTED_VALUE"""),"29'") -> 29' | S50: =IFERROR(__xludf.DUMMYFUNCTION("""COMPUTED_VALUE"""),107.0) -> 107 | T50: =IFERROR(__xludf.DUMMYFUNCTION("""COMPUTED_VALUE"""),"40in") -> 40in | U50: =IFERROR(__xludf.DUMMYFUNCTION("""COMPUTED_VALUE"""),"mezzanine (Parsons Blvd & Archer Ave) to J/Z platform for Brooklyn-bound service") -> mezzanine (Parsons Blvd & Archer Ave) to J/Z platform for Brooklyn-bound service | V50: =IFERROR(__xludf.DUMMYFUNCTION("""COMPUTED_VALUE"""),"POINT (-73.800316 40.70236)") -> POINT (-73.800316 40.70236)
A51: =IFERROR(__xludf.DUMMYFUNCTION("""COMPUTED_VALUE"""),"Grand Central-42 St") -> Grand Central-42 St | B51: =IFERROR(__xludf.DUMMYFUNCTION("""COMPUTED_VALUE"""),"42nd St Line") -> 42nd St Line | C51: =IFERROR(__xludf.DUMMYFUNCTION("""COMPUTED_VALUE"""),"Manhattan") -> Manhattan | D51: =IFERROR(__xludf.DUMMYFUNCTION("""COMPUTED_VALUE"""),"Midtown") -> Midtown | E51: =IFERROR(__xludf.DUMMYFUNCTION("""COMPUTED_VALUE"""),1762.0) -> 1762 | F51: =IFERROR(__xludf.DUMMYFUNCTION("""COMPUTED_VALUE"""),3.3496874E7) -> 33496874 | G51: =IFERROR(__xludf.DUMMYFUNCTION("""COMPUTED_VALUE"""),2.0) -> 2 | H51: =IFERROR(__xludf.DUMMYFUNCTION("""COMPUTED_VALUE"""),"↗️") -> ↗️ | I51: =IFERROR(__xludf.DUMMYFUNCTION("""COMPUTED_VALUE"""),44174.0) -> 44174 | J51: =IFERROR(__xludf.DUMMYFUNCTION("""COMPUTED_VALUE"""),44174.0) -> 44174 | K51: =IFERROR(__xludf.DUMMYFUNCTION("""COMPUTED_VALUE"""),22.0) -> 22 | L51: =IFERROR(__xludf.DUMMYFUNCTION("""COMPUTED_VALUE"""),"NO") -> NO | M51: =IFERROR(__xludf.DUMMYFUNCTION("""COMPUTED_VALUE"""),"Private Contractor") -> Private Contractor | O51: =IFERROR(__xludf.DUMMYFUNCTION("""COMPUTED_VALUE"""),"YES") -> YES | U51: =IFERROR(__xludf.DUMMYFUNCTION("""COMPUTED_VALUE"""),"Platform level for Shuttle service to 42 St and Vanderbilt Ave (NE Corner).") -> Platform level for Shuttle service to 42 St and Vanderbilt Ave (NE Corner). | V51: =IFERROR(__xludf.DUMMYFUNCTION("""COMPUTED_VALUE"""),"POINT (-73.93359 40.849506)") -> POINT (-73.93359 40.849506)
A52: =IFERROR(__xludf.DUMMYFUNCTION("""COMPUTED_VALUE"""),"21 St-Queensbridge") -> 21 St-Queensbridge | B52: =IFERROR(__xludf.DUMMYFUNCTION("""COMPUTED_VALUE"""),"63rd St Line") -> 63rd St Line | C52: =IFERROR(__xludf.DUMMYFUNCTION("""COMPUTED_VALUE"""),"Queens") -> Queens | D52: =IFERROR(__xludf.DUMMYFUNCTION("""COMPUTED_VALUE"""),"Long Island City") -> Long Island City | E52: =IFERROR(__xludf.DUMMYFUNCTION("""COMPUTED_VALUE"""),32810.0) -> 32810 | F52: =IFERROR(__xludf.DUMMYFUNCTION("""COMPUTED_VALUE"""),1751180.0) -> 1751180 | G52: =IFERROR(__xludf.DUMMYFUNCTION("""COMPUTED_VALUE"""),184.0) -> 184 | H52: =IFERROR(__xludf.DUMMYFUNCTION("""COMPUTED_VALUE"""),"↗️") -> ↗️ | I52: =IFERROR(__xludf.DUMMYFUNCTION("""COMPUTED_VALUE"""),32782.0) -> 32782 | J52: =IFERROR(__xludf.DUMMYFUNCTION("""COMPUTED_VALUE"""),46137.0) -> 46137 | K52: =IFERROR(__xludf.DUMMYFUNCTION("""COMPUTED_VALUE"""),22.0) -> 22 | L52: =IFERROR(__xludf.DUMMYFUNCTION("""COMPUTED_VALUE"""),"YES") -> YES | M52: =IFERROR(__xludf.DUMMYFUNCTION("""COMPUTED_VALUE"""),"NYCT") -> NYCT | N52: =IFERROR(__xludf.DUMMYFUNCTION("""COMPUTED_VALUE"""),"KONE") -> KONE | O52: =IFERROR(__xludf.DUMMYFUNCTION("""COMPUTED_VALUE"""),"YES") -> YES | P52: =IFERROR(__xludf.DUMMYFUNCTION("""COMPUTED_VALUE"""),"NO") -> NO | Q52: =IFERROR(__xludf.DUMMYFUNCTION("""COMPUTED_VALUE"""),"NO") -> NO | R52: =IFERROR(__xludf.DUMMYFUNCTION("""COMPUTED_VALUE"""),"11'") -> 11' | S52: =IFERROR(__xludf.DUMMYFUNCTION("""COMPUTED_VALUE"""),53.0) -> 53 | T52: =IFERROR(__xludf.DUMMYFUNCTION("""COMPUTED_VALUE"""),"40in") -> 40in | U52: =IFERROR(__xludf.DUMMYFUNCTION("""COMPUTED_VALUE"""),"mezzanine to Manhattan-bound platform") -> mezzanine to Manhattan-bound platform | V52: =IFERROR(__xludf.DUMMYFUNCTION("""COMPUTED_VALUE"""),"POINT (-73.94242 40.754124)") -> POINT (-73.94242 40.754124)
A53: =IFERROR(__xludf.DUMMYFUNCTION("""COMPUTED_VALUE"""),"South Ferry") -> South Ferry | B53: =IFERROR(__xludf.DUMMYFUNCTION("""COMPUTED_VALUE"""),"") | C53: =IFERROR(__xludf.DUMMYFUNCTION("""COMPUTED_VALUE"""),"") | D53: =IFERROR(__xludf.DUMMYFUNCTION("""COMPUTED_VALUE"""),"") | E53: =IFERROR(__xludf.DUMMYFUNCTION("""COMPUTED_VALUE"""),"") | F53: =IFERROR(__xludf.DUMMYFUNCTION("""COMPUTED_VALUE"""),"") | G53: =IFERROR(__xludf.DUMMYFUNCTION("""COMPUTED_VALUE"""),"") | H53: =IFERROR(__xludf.DUMMYFUNCTION("""COMPUTED_VALUE"""),"↗️") -> ↗️ | I53: =IFERROR(__xludf.DUMMYFUNCTION("""COMPUTED_VALUE"""),39888.0) -> 39888 | J53: =IFERROR(__xludf.DUMMYFUNCTION("""COMPUTED_VALUE"""),42913.0) -> 42913 | K53: =IFERROR(__xludf.DUMMYFUNCTION("""COMPUTED_VALUE"""),22.0) -> 22 | L53: =IFERROR(__xludf.DUMMYFUNCTION("""COMPUTED_VALUE"""),"YES") -> YES | M53: =IFERROR(__xludf.DUMMYFUNCTION("""COMPUTED_VALUE"""),"NYCT") -> NYCT | N53: =IFERROR(__xludf.DUMMYFUNCTION("""COMPUTED_VALUE"""),"KONE") -> KONE | O53: =IFERROR(__xludf.DUMMYFUNCTION("""COMPUTED_VALUE"""),"YES") -> YES | P53: =IFERROR(__xludf.DUMMYFUNCTION("""COMPUTED_VALUE"""),"NO") -> NO | Q53: =IFERROR(__xludf.DUMMYFUNCTION("""COMPUTED_VALUE"""),"NO") -> NO | R53: =IFERROR(__xludf.DUMMYFUNCTION("""COMPUTED_VALUE"""),"8030 mm (26' 4 1/8in)") -> 8030 mm (26' 4 1/8in) | S53: =IFERROR(__xludf.DUMMYFUNCTION("""COMPUTED_VALUE"""),109.0) -> 109 | T53: =IFERROR(__xludf.DUMMYFUNCTION("""COMPUTED_VALUE"""),"40in (NOMINAL), 996 mm") -> 40in (NOMINAL), 996 mm | U53: =IFERROR(__xludf.DUMMYFUNCTION("""COMPUTED_VALUE"""),"1 platform to mezzanine for Peter Minuit Plaza exit and R/W service") -> 1 platform to mezzanine for Peter Minuit Plaza exit and R/W service | V53: =IFERROR(__xludf.DUMMYFUNCTION("""COMPUTED_VALUE"""),"POINT (-74.0131 40.701656)") -> POINT (-74.0131 40.701656)
A54: =IFERROR(__xludf.DUMMYFUNCTION("""COMPUTED_VALUE"""),"DeKalb Av") -> DeKalb Av | B54: =IFERROR(__xludf.DUMMYFUNCTION("""COMPUTED_VALUE"""),"Canarsie Line") -> Canarsie Line | C54: =IFERROR(__xludf.DUMMYFUNCTION("""COMPUTED_VALUE"""),"Brooklyn") -> Brooklyn | D54: =IFERROR(__xludf.DUMMYFUNCTION("""COMPUTED_VALUE"""),"Bushwick") -> Bushwick | E54: =IFERROR(__xludf.DUMMYFUNCTION("""COMPUTED_VALUE"""),10423.0) -> 10423 | F54: =IFERROR(__xludf.DUMMYFUNCTION("""COMPUTED_VALUE"""),2931695.0) -> 2931695 | G54: =IFERROR(__xludf.DUMMYFUNCTION("""COMPUTED_VALUE"""),113.0) -> 113 | H54: =IFERROR(__xludf.DUMMYFUNCTION("""COMPUTED_VALUE"""),"↗️") -> ↗️ | I54: =IFERROR(__xludf.DUMMYFUNCTION("""COMPUTED_VALUE"""),22373.0) -> 22373 | J54: =IFERROR(__xludf.DUMMYFUNCTION("""COMPUTED_VALUE"""),45409.0) -> 45409 | K54: =IFERROR(__xludf.DUMMYFUNCTION("""COMPUTED_VALUE"""),22.0) -> 22 | L54: =IFERROR(__xludf.DUMMYFUNCTION("""COMPUTED_VALUE"""),"YES") -> YES | M54: =IFERROR(__xludf.DUMMYFUNCTION("""COMPUTED_VALUE"""),"NYCT") -> NYCT | N54: =IFERROR(__xludf.DUMMYFUNCTION("""COMPUTED_VALUE"""),"OK") -> OK | O54: =IFERROR(__xludf.DUMMYFUNCTION("""COMPUTED_VALUE"""),"YES") -> YES | P54: =IFERROR(__xludf.DUMMYFUNCTION("""COMPUTED_VALUE"""),"NO") -> NO | Q54: =IFERROR(__xludf.DUMMYFUNCTION("""COMPUTED_VALUE"""),"NO") -> NO | R54: =IFERROR(__xludf.DUMMYFUNCTION("""COMPUTED_VALUE"""),"20 feet 8 1/4 inch") -> 20 feet 8 1/4 inch | S54: =IFERROR(__xludf.DUMMYFUNCTION("""COMPUTED_VALUE"""),82.0) -> 82 | T54: =IFERROR(__xludf.DUMMYFUNCTION("""COMPUTED_VALUE"""),40.0) -> 40 | U54: =IFERROR(__xludf.DUMMYFUNCTION("""COMPUTED_VALUE"""),"Manhattan-bound platform to mezzanine for Flatbush Ave & Lafayette St exit") -> Manhattan-bound platform to mezzanine for Flatbush Ave & Lafayette St exit | V54: =IFERROR(__xludf.DUMMYFUNCTION("""COMPUTED_VALUE"""),"POINT (-73.98208 40.691376)") -> POINT (-73.98208 40.691376)
A55: =IFERROR(__xludf.DUMMYFUNCTION("""COMPUTED_VALUE"""),"Fulton St") -> Fulton St | B55: =IFERROR(__xludf.DUMMYFUNCTION("""COMPUTED_VALUE"""),"Broadway-7 Av Line") -> Broadway-7 Av Line | C55: =IFERROR(__xludf.DUMMYFUNCTION("""COMPUTED_VALUE"""),"Manhattan") -> Manhattan | D55: =IFERROR(__xludf.DUMMYFUNCTION("""COMPUTED_VALUE"""),"Financial District") -> Financial District | E55: =IFERROR(__xludf.DUMMYFUNCTION("""COMPUTED_VALUE"""),6757.0) -> 6757 | F55: =IFERROR(__xludf.DUMMYFUNCTION("""COMPUTED_VALUE"""),1.9221396E7) -> 19221396 | G55: =IFERROR(__xludf.DUMMYFUNCTION("""COMPUTED_VALUE"""),5.0) -> 5 | H55: =IFERROR(__xludf.DUMMYFUNCTION("""COMPUTED_VALUE"""),"↗️") -> ↗️ | J55: =IFERROR(__xludf.DUMMYFUNCTION("""COMPUTED_VALUE"""),41953.0) -> 41953 | K55: =IFERROR(__xludf.DUMMYFUNCTION("""COMPUTED_VALUE"""),22.0) -> 22 | L55: =IFERROR(__xludf.DUMMYFUNCTION("""COMPUTED_VALUE"""),"NO") -> NO | M55: =IFERROR(__xludf.DUMMYFUNCTION("""COMPUTED_VALUE"""),"Private Contractor") -> Private Contractor | N55: =IFERROR(__xludf.DUMMYFUNCTION("""COMPUTED_VALUE"""),"THYSSEN-KRUPP") -> THYSSEN-KRUPP | O55: =IFERROR(__xludf.DUMMYFUNCTION("""COMPUTED_VALUE"""),"YES") -> YES | P55: =IFERROR(__xludf.DUMMYFUNCTION("""COMPUTED_VALUE"""),"NO") -> NO | Q55: =IFERROR(__xludf.DUMMYFUNCTION("""COMPUTED_VALUE"""),"NO") -> NO | U55: =IFERROR(__xludf.DUMMYFUNCTION("""COMPUTED_VALUE"""),"uptown 4/5 platform level to Transit Center exit (Fulton St east of Broadway)") -> uptown 4/5 platform level to Transit Center exit (Fulton St east of Broadway) | V55: =IFERROR(__xludf.DUMMYFUNCTION("""COMPUTED_VALUE"""),"POINT (-74.00876 40.7105)") -> POINT (-74.00876 40.7105)
A56: =IFERROR(__xludf.DUMMYFUNCTION("""COMPUTED_VALUE"""),"74 St-Broadway") -> 74 St-Broadway | B56: =IFERROR(__xludf.DUMMYFUNCTION("""COMPUTED_VALUE"""),"") | C56: =IFERROR(__xludf.DUMMYFUNCTION("""COMPUTED_VALUE"""),"") | D56: =IFERROR(__xludf.DUMMYFUNCTION("""COMPUTED_VALUE"""),"") | E56: =IFERROR(__xludf.DUMMYFUNCTION("""COMPUTED_VALUE"""),"") | F56: =IFERROR(__xludf.DUMMYFUNCTION("""COMPUTED_VALUE"""),"") | G56: =IFERROR(__xludf.DUMMYFUNCTION("""COMPUTED_VALUE"""),"") | H56: =IFERROR(__xludf.DUMMYFUNCTION("""COMPUTED_VALUE"""),"↗️") -> ↗️ | I56: =IFERROR(__xludf.DUMMYFUNCTION("""COMPUTED_VALUE"""),26900.0) -> 26900 | J56: =IFERROR(__xludf.DUMMYFUNCTION("""COMPUTED_VALUE"""),45596.0) -> 45596 | K56: =IFERROR(__xludf.DUMMYFUNCTION("""COMPUTED_VALUE"""),22.0) -> 22 | L56: =IFERROR(__xludf.DUMMYFUNCTION("""COMPUTED_VALUE"""),"YES") -> YES | M56: =IFERROR(__xludf.DUMMYFUNCTION("""COMPUTED_VALUE"""),"NYCT") -> NYCT | N56: =IFERROR(__xludf.DUMMYFUNCTION("""COMPUTED_VALUE"""),"OK") -> OK | O56: =IFERROR(__xludf.DUMMYFUNCTION("""COMPUTED_VALUE"""),"YES") -> YES | P56: =IFERROR(__xludf.DUMMYFUNCTION("""COMPUTED_VALUE"""),"NO") -> NO | Q56: =IFERROR(__xludf.DUMMYFUNCTION("""COMPUTED_VALUE"""),"NO") -> NO | R56: =IFERROR(__xludf.DUMMYFUNCTION("""COMPUTED_VALUE"""),"32'") -> 32' | S56: =IFERROR(__xludf.DUMMYFUNCTION("""COMPUTED_VALUE"""),118.0) -> 118 | T56: =IFERROR(__xludf.DUMMYFUNCTION("""COMPUTED_VALUE"""),"40in") -> 40in | U56: =IFERROR(__xludf.DUMMYFUNCTION("""COMPUTED_VALUE"""),"E/F/M/R lower mezzanine to underpass for 7 service") -> E/F/M/R lower mezzanine to underpass for 7 service | V56: =IFERROR(__xludf.DUMMYFUNCTION("""COMPUTED_VALUE"""),"POINT (-73.892456 40.746906)") -> POINT (-73.892456 40.746906)
A57: =IFERROR(__xludf.DUMMYFUNCTION("""COMPUTED_VALUE"""),"Fulton St") -> Fulton St | B57: =IFERROR(__xludf.DUMMYFUNCTION("""COMPUTED_VALUE"""),"Broadway-7 Av Line") -> Broadway-7 Av Line | C57: =IFERROR(__xludf.DUMMYFUNCTION("""COMPUTED_VALUE"""),"Manhattan") -> Manhattan | D57: =IFERROR(__xludf.DUMMYFUNCTION("""COMPUTED_VALUE"""),"Financial District") -> Financial District | E57: =IFERROR(__xludf.DUMMYFUNCTION("""COMPUTED_VALUE"""),6757.0) -> 6757 | F57: =IFERROR(__xludf.DUMMYFUNCTION("""COMPUTED_VALUE"""),1.9221396E7) -> 19221396 | G57: =IFERROR(__xludf.DUMMYFUNCTION("""COMPUTED_VALUE"""),5.0) -> 5 | H57: =IFERROR(__xludf.DUMMYFUNCTION("""COMPUTED_VALUE"""),"↗️") -> ↗️ | J57: =IFERROR(__xludf.DUMMYFUNCTION("""COMPUTED_VALUE"""),41953.0) -> 41953 | K57: =IFERROR(__xludf.DUMMYFUNCTION("""COMPUTED_VALUE"""),22.0) -> 22 | L57: =IFERROR(__xludf.DUMMYFUNCTION("""COMPUTED_VALUE"""),"NO") -> NO | M57: =IFERROR(__xludf.DUMMYFUNCTION("""COMPUTED_VALUE"""),"Private Contractor") -> Private Contractor | N57: =IFERROR(__xludf.DUMMYFUNCTION("""COMPUTED_VALUE"""),"THYSSEN-KRUPP") -> THYSSEN-KRUPP | O57: =IFERROR(__xludf.DUMMYFUNCTION("""COMPUTED_VALUE"""),"YES") -> YES | P57: =IFERROR(__xludf.DUMMYFUNCTION("""COMPUTED_VALUE"""),"NO") -> NO | Q57: =IFERROR(__xludf.DUMMYFUNCTION("""COMPUTED_VALUE"""),"NO") -> NO | U57: =IFERROR(__xludf.DUMMYFUNCTION("""COMPUTED_VALUE"""),"concourse to uptown 4/5 platform and access to Transit Center exit") -> concourse to uptown 4/5 platform and access to Transit Center exit | V57: =IFERROR(__xludf.DUMMYFUNCTION("""COMPUTED_VALUE"""),"POINT (-74.00896 40.710472)") -> POINT (-74.00896 40.710472)
A58: =IFERROR(__xludf.DUMMYFUNCTION("""COMPUTED_VALUE"""),"Jamaica Center-Parsons/Archer") -> Jamaica Center-Parsons/Archer | B58: =IFERROR(__xludf.DUMMYFUNCTION("""COMPUTED_VALUE"""),"Archer Av Line") -> Archer Av Line | C58: =IFERROR(__xludf.DUMMYFUNCTION("""COMPUTED_VALUE"""),"Queens") -> Queens | D58: =IFERROR(__xludf.DUMMYFUNCTION("""COMPUTED_VALUE"""),"Jamaica") -> Jamaica | E58: =IFERROR(__xludf.DUMMYFUNCTION("""COMPUTED_VALUE"""),32488.0) -> 32488 | F58: =IFERROR(__xludf.DUMMYFUNCTION("""COMPUTED_VALUE"""),6137267.0) -> 6137267 | G58: =IFERROR(__xludf.DUMMYFUNCTION("""COMPUTED_VALUE"""),38.0) -> 38 | H58: =IFERROR(__xludf.DUMMYFUNCTION("""COMPUTED_VALUE"""),"↗️") -> ↗️ | I58: =IFERROR(__xludf.DUMMYFUNCTION("""COMPUTED_VALUE"""),32478.0) -> 32478 | J58: =IFERROR(__xludf.DUMMYFUNCTION("""COMPUTED_VALUE"""),39643.0) -> 39643 | K58: =IFERROR(__xludf.DUMMYFUNCTION("""COMPUTED_VALUE"""),22.0) -> 22 | L58: =IFERROR(__xludf.DUMMYFUNCTION("""COMPUTED_VALUE"""),"YES") -> YES | M58: =IFERROR(__xludf.DUMMYFUNCTION("""COMPUTED_VALUE"""),"NYCT") -> NYCT | N58: =IFERROR(__xludf.DUMMYFUNCTION("""COMPUTED_VALUE"""),"KONE") -> KONE | O58: =IFERROR(__xludf.DUMMYFUNCTION("""COMPUTED_VALUE"""),"YES") -> YES | P58: =IFERROR(__xludf.DUMMYFUNCTION("""COMPUTED_VALUE"""),"NO") -> NO | Q58: =IFERROR(__xludf.DUMMYFUNCTION("""COMPUTED_VALUE"""),"NO") -> NO | R58: =IFERROR(__xludf.DUMMYFUNCTION("""COMPUTED_VALUE"""),"11'") -> 11' | S58: =IFERROR(__xludf.DUMMYFUNCTION("""COMPUTED_VALUE"""),53.0) -> 53 | T58: =IFERROR(__xludf.DUMMYFUNCTION("""COMPUTED_VALUE"""),"40in") -> 40in | U58: =IFERROR(__xludf.DUMMYFUNCTION("""COMPUTED_VALUE"""),"E platform to mezzanine for 153 St & Archer Ave exit") -> E platform to mezzanine for 153 St & Archer Ave exit | V58: =IFERROR(__xludf.DUMMYFUNCTION("""COMPUTED_VALUE"""),"POINT (-73.80144 40.7021)") -> POINT (-73.80144 40.7021)
A59: =IFERROR(__xludf.DUMMYFUNCTION("""COMPUTED_VALUE"""),"34 St-Hudson Yards") -> 34 St-Hudson Yards | B59: =IFERROR(__xludf.DUMMYFUNCTION("""COMPUTED_VALUE"""),"Flushing Line") -> Flushing Line | C59: =IFERROR(__xludf.DUMMYFUNCTION("""COMPUTED_VALUE"""),"Manhattan") -> Manhattan | D59: =IFERROR(__xludf.DUMMYFUNCTION("""COMPUTED_VALUE"""),"Hell's Kitchen") -> Hell's Kitchen | E59: =IFERROR(__xludf.DUMMYFUNCTION("""COMPUTED_VALUE"""),42260.0) -> 42260 | F59: =IFERROR(__xludf.DUMMYFUNCTION("""COMPUTED_VALUE"""),6082370.0) -> 6082370 | G59: =IFERROR(__xludf.DUMMYFUNCTION("""COMPUTED_VALUE"""),39.0) -> 39 | H59: =IFERROR(__xludf.DUMMYFUNCTION("""COMPUTED_VALUE"""),"↗️") -> ↗️ | I59: =IFERROR(__xludf.DUMMYFUNCTION("""COMPUTED_VALUE"""),42260.0) -> 42260 | J59: =IFERROR(__xludf.DUMMYFUNCTION("""COMPUTED_VALUE"""),42260.0) -> 42260 | K59: =IFERROR(__xludf.DUMMYFUNCTION("""COMPUTED_VALUE"""),22.0) -> 22 | L59: =IFERROR(__xludf.DUMMYFUNCTION("""COMPUTED_VALUE"""),"YES") -> YES | M59: =IFERROR(__xludf.DUMMYFUNCTION("""COMPUTED_VALUE"""),"NYCT") -> NYCT | N59: =IFERROR(__xludf.DUMMYFUNCTION("""COMPUTED_VALUE"""),"KONE") -> KONE | O59: =IFERROR(__xludf.DUMMYFUNCTION("""COMPUTED_VALUE"""),"YES") -> YES | P59: =IFERROR(__xludf.DUMMYFUNCTION("""COMPUTED_VALUE"""),"YES") -> YES | Q59: =IFERROR(__xludf.DUMMYFUNCTION("""COMPUTED_VALUE"""),"YES") -> YES | R59: =IFERROR(__xludf.DUMMYFUNCTION("""COMPUTED_VALUE"""),"30'") -> 30' | S59: =IFERROR(__xludf.DUMMYFUNCTION("""COMPUTED_VALUE"""),109.0) -> 109 | T59: =IFERROR(__xludf.DUMMYFUNCTION("""COMPUTED_VALUE"""),24.0) -> 24 | U59: =IFERROR(__xludf.DUMMYFUNCTION("""COMPUTED_VALUE"""),"upper mezzanine to Hudson Blvd E (between 33 St & 34 St)") -> upper mezzanine to Hudson Blvd E (between 33 St & 34 St) | V59: =IFERROR(__xludf.DUMMYFUNCTION("""COMPUTED_VALUE"""),"POINT (-74.00105 40.75495)") -> POINT (-74.00105 40.75495)
A60: =IFERROR(__xludf.DUMMYFUNCTION("""COMPUTED_VALUE"""),"Roosevelt Island") -> Roosevelt Island | B60: =IFERROR(__xludf.DUMMYFUNCTION("""COMPUTED_VALUE"""),"63rd St Line") -> 63rd St Line | C60: =IFERROR(__xludf.DUMMYFUNCTION("""COMPUTED_VALUE"""),"Manhattan") -> Manhattan | D60: =IFERROR(__xludf.DUMMYFUNCTION("""COMPUTED_VALUE"""),"Roosevelt Island") -> Roosevelt Island | E60: =IFERROR(__xludf.DUMMYFUNCTION("""COMPUTED_VALUE"""),32810.0) -> 32810 | F60: =IFERROR(__xludf.DUMMYFUNCTION("""COMPUTED_VALUE"""),1885823.0) -> 1885823 | G60: =IFERROR(__xludf.DUMMYFUNCTION("""COMPUTED_VALUE"""),171.0) -> 171 | H60: =IFERROR(__xludf.DUMMYFUNCTION("""COMPUTED_VALUE"""),"↗️") -> ↗️ | I60: =IFERROR(__xludf.DUMMYFUNCTION("""COMPUTED_VALUE"""),35258.0) -> 35258 | J60: =IFERROR(__xludf.DUMMYFUNCTION("""COMPUTED_VALUE"""),45207.0) -> 45207 | K60: =IFERROR(__xludf.DUMMYFUNCTION("""COMPUTED_VALUE"""),22.0) -> 22 | L60: =IFERROR(__xludf.DUMMYFUNCTION("""COMPUTED_VALUE"""),"YES") -> YES | M60: =IFERROR(__xludf.DUMMYFUNCTION("""COMPUTED_VALUE"""),"NYCT") -> NYCT | N60: =IFERROR(__xludf.DUMMYFUNCTION("""COMPUTED_VALUE"""),"OK") -> OK | O60: =IFERROR(__xludf.DUMMYFUNCTION("""COMPUTED_VALUE"""),"YES") -> YES | P60: =IFERROR(__xludf.DUMMYFUNCTION("""COMPUTED_VALUE"""),"NO") -> NO | Q60: =IFERROR(__xludf.DUMMYFUNCTION("""COMPUTED_VALUE"""),"NO") -> NO | R60: =IFERROR(__xludf.DUMMYFUNCTION("""COMPUTED_VALUE"""),"36'") -> 36' | S60: =IFERROR(__xludf.DUMMYFUNCTION("""COMPUTED_VALUE"""),129.0) -> 129 | T60: =IFERROR(__xludf.DUMMYFUNCTION("""COMPUTED_VALUE"""),40.0) -> 40 | U60: =IFERROR(__xludf.DUMMYFUNCTION("""COMPUTED_VALUE"""),"lower mezzanine to intermediate mezzanine") -> lower mezzanine to intermediate mezzanine | V60: =IFERROR(__xludf.DUMMYFUNCTION("""COMPUTED_VALUE"""),"POINT (-73.952835 40.758938)") -> POINT (-73.952835 40.758938)
A61: =IFERROR(__xludf.DUMMYFUNCTION("""COMPUTED_VALUE"""),"145 St") -> 145 St | B61: =IFERROR(__xludf.DUMMYFUNCTION("""COMPUTED_VALUE"""),"Broadway-7 Av Line") -> Broadway-7 Av Line | C61: =IFERROR(__xludf.DUMMYFUNCTION("""COMPUTED_VALUE"""),"Manhattan") -> Manhattan | D61: =IFERROR(__xludf.DUMMYFUNCTION("""COMPUTED_VALUE"""),"Hamilton Heights") -> Hamilton Heights | E61: =IFERROR(__xludf.DUMMYFUNCTION("""COMPUTED_VALUE"""),1762.0) -> 1762 | F61: =IFERROR(__xludf.DUMMYFUNCTION("""COMPUTED_VALUE"""),2114398.0) -> 2114398 | G61: =IFERROR(__xludf.DUMMYFUNCTION("""COMPUTED_VALUE"""),158.0) -> 158 | H61: =IFERROR(__xludf.DUMMYFUNCTION("""COMPUTED_VALUE"""),"↗️") -> ↗️ | I61: =IFERROR(__xludf.DUMMYFUNCTION("""COMPUTED_VALUE"""),12236.0) -> 12236 | J61: =IFERROR(__xludf.DUMMYFUNCTION("""COMPUTED_VALUE"""),37176.0) -> 37176 | K61: =IFERROR(__xludf.DUMMYFUNCTION("""COMPUTED_VALUE"""),22.0) -> 22 | L61: =IFERROR(__xludf.DUMMYFUNCTION("""COMPUTED_VALUE"""),"YES") -> YES | M61: =IFERROR(__xludf.DUMMYFUNCTION("""COMPUTED_VALUE"""),"NYCT") -> NYCT | N61: =IFERROR(__xludf.DUMMYFUNCTION("""COMPUTED_VALUE"""),"OK") -> OK | O61: =IFERROR(__xludf.DUMMYFUNCTION("""COMPUTED_VALUE"""),"YES") -> YES | P61: =IFERROR(__xludf.DUMMYFUNCTION("""COMPUTED_VALUE"""),"NO") -> NO | Q61: =IFERROR(__xludf.DUMMYFUNCTION("""COMPUTED_VALUE"""),"NO") -> NO | R61: =IFERROR(__xludf.DUMMYFUNCTION("""COMPUTED_VALUE"""),"27'") -> 27' | S61: =IFERROR(__xludf.DUMMYFUNCTION("""COMPUTED_VALUE"""),98.0) -> 98 | T61: =IFERROR(__xludf.DUMMYFUNCTION("""COMPUTED_VALUE"""),24.0) -> 24 | U61: =IFERROR(__xludf.DUMMYFUNCTION("""COMPUTED_VALUE"""),"uptown B/D platform to mezzanine for 145 St & St Nicholas Av exit") -> uptown B/D platform to mezzanine for 145 St & St Nicholas Av exit | V61: =IFERROR(__xludf.DUMMYFUNCTION("""COMPUTED_VALUE"""),"POINT (-73.94464 40.824055)") -> POINT (-73.94464 40.824055)
A62: =IFERROR(__xludf.DUMMYFUNCTION("""COMPUTED_VALUE"""),"Grand Central-42 St") -> Grand Central-42 St | B62: =IFERROR(__xludf.DUMMYFUNCTION("""COMPUTED_VALUE"""),"42nd St Line") -> 42nd St Line | C62: =IFERROR(__xludf.DUMMYFUNCTION("""COMPUTED_VALUE"""),"Manhattan") -> Manhattan | D62: =IFERROR(__xludf.DUMMYFUNCTION("""COMPUTED_VALUE"""),"Midtown") -> Midtown | E62: =IFERROR(__xludf.DUMMYFUNCTION("""COMPUTED_VALUE"""),1762.0) -> 1762 | F62: =IFERROR(__xludf.DUMMYFUNCTION("""COMPUTED_VALUE"""),3.3496874E7) -> 33496874 | G62: =IFERROR(__xludf.DUMMYFUNCTION("""COMPUTED_VALUE"""),2.0) -> 2 | H62: =IFERROR(__xludf.DUMMYFUNCTION("""COMPUTED_VALUE"""),"↗️") -> ↗️ | I62: =IFERROR(__xludf.DUMMYFUNCTION("""COMPUTED_VALUE"""),44174.0) -> 44174 | J62: =IFERROR(__xludf.DUMMYFUNCTION("""COMPUTED_VALUE"""),44174.0) -> 44174 | K62: =IFERROR(__xludf.DUMMYFUNCTION("""COMPUTED_VALUE"""),22.0) -> 22 | L62: =IFERROR(__xludf.DUMMYFUNCTION("""COMPUTED_VALUE"""),"NO") -> NO | M62: =IFERROR(__xludf.DUMMYFUNCTION("""COMPUTED_VALUE"""),"Private Contractor") -> Private Contractor | O62: =IFERROR(__xludf.DUMMYFUNCTION("""COMPUTED_VALUE"""),"YES") -> YES | U62: =IFERROR(__xludf.DUMMYFUNCTION("""COMPUTED_VALUE"""),"LIRR â€œMadison Concourseâ€ to Shuttle platform.") -> LIRR â€œMadison Concourseâ€_x009d_ to Shuttle platform. | V62: =IFERROR(__xludf.DUMMYFUNCTION("""COMPUTED_VALUE"""),"POINT (-73.93359 40.849506)") -> POINT (-73.93359 40.849506)
A63: =IFERROR(__xludf.DUMMYFUNCTION("""COMPUTED_VALUE"""),"Jamaica Van Wyck") -> Jamaica Van Wyck | B63: =IFERROR(__xludf.DUMMYFUNCTION("""COMPUTED_VALUE"""),"") | C63: =IFERROR(__xludf.DUMMYFUNCTION("""COMPUTED_VALUE"""),"") | D63: =IFERROR(__xludf.DUMMYFUNCTION("""COMPUTED_VALUE"""),"") | E63: =IFERROR(__xludf.DUMMYFUNCTION("""COMPUTED_VALUE"""),"") | F63: =IFERROR(__xludf.DUMMYFUNCTION("""COMPUTED_VALUE"""),"") | G63: =IFERROR(__xludf.DUMMYFUNCTION("""COMPUTED_VALUE"""),"") | H63: =IFERROR(__xludf.DUMMYFUNCTION("""COMPUTED_VALUE"""),"↗️") -> ↗️ | I63: =IFERROR(__xludf.DUMMYFUNCTION("""COMPUTED_VALUE"""),32478.0) -> 32478 | J63: =IFERROR(__xludf.DUMMYFUNCTION("""COMPUTED_VALUE"""),39808.0) -> 39808 | K63: =IFERROR(__xludf.DUMMYFUNCTION("""COMPUTED_VALUE"""),22.0) -> 22 | L63: =IFERROR(__xludf.DUMMYFUNCTION("""COMPUTED_VALUE"""),"YES") -> YES | M63: =IFERROR(__xludf.DUMMYFUNCTION("""COMPUTED_VALUE"""),"NYCT") -> NYCT | N63: =IFERROR(__xludf.DUMMYFUNCTION("""COMPUTED_VALUE"""),"KONE") -> KONE | O63: =IFERROR(__xludf.DUMMYFUNCTION("""COMPUTED_VALUE"""),"YES") -> YES | P63: =IFERROR(__xludf.DUMMYFUNCTION("""COMPUTED_VALUE"""),"YES") -> YES | Q63: =IFERROR(__xludf.DUMMYFUNCTION("""COMPUTED_VALUE"""),"YES") -> YES | R63: =IFERROR(__xludf.DUMMYFUNCTION("""COMPUTED_VALUE"""),"26'") -> 26' | S63: =IFERROR(__xludf.DUMMYFUNCTION("""COMPUTED_VALUE"""),96.0) -> 96 | T63: =IFERROR(__xludf.DUMMYFUNCTION("""COMPUTED_VALUE"""),"40in") -> 40in | U63: =IFERROR(__xludf.DUMMYFUNCTION("""COMPUTED_VALUE"""),"mezzanine to Metropolitan Ave & Jamaica Ave (NE corner)") -> mezzanine to Metropolitan Ave & Jamaica Ave (NE corner) | V63: =IFERROR(__xludf.DUMMYFUNCTION("""COMPUTED_VALUE"""),"POINT (-73.81707 40.702473)") -> POINT (-73.81707 40.702473)
A64: =IFERROR(__xludf.DUMMYFUNCTION("""COMPUTED_VALUE"""),"Grand Central-42 St") -> Grand Central-42 St | B64: =IFERROR(__xludf.DUMMYFUNCTION("""COMPUTED_VALUE"""),"42nd St Line") -> 42nd St Line | C64: =IFERROR(__xludf.DUMMYFUNCTION("""COMPUTED_VALUE"""),"Manhattan") -> Manhattan | D64: =IFERROR(__xludf.DUMMYFUNCTION("""COMPUTED_VALUE"""),"Midtown") -> Midtown | E64: =IFERROR(__xludf.DUMMYFUNCTION("""COMPUTED_VALUE"""),1762.0) -> 1762 | F64: =IFERROR(__xludf.DUMMYFUNCTION("""COMPUTED_VALUE"""),3.3496874E7) -> 33496874 | G64: =IFERROR(__xludf.DUMMYFUNCTION("""COMPUTED_VALUE"""),2.0) -> 2 | H64: =IFERROR(__xludf.DUMMYFUNCTION("""COMPUTED_VALUE"""),"↗️") -> ↗️ | J64: =IFERROR(__xludf.DUMMYFUNCTION("""COMPUTED_VALUE"""),41091.0) -> 41091 | K64: =IFERROR(__xludf.DUMMYFUNCTION("""COMPUTED_VALUE"""),22.0) -> 22 | L64: =IFERROR(__xludf.DUMMYFUNCTION("""COMPUTED_VALUE"""),"NO") -> NO | M64: =IFERROR(__xludf.DUMMYFUNCTION("""COMPUTED_VALUE"""),"Private Contractor") -> Private Contractor | N64: =IFERROR(__xludf.DUMMYFUNCTION("""COMPUTED_VALUE"""),"AM") -> AM | O64: =IFERROR(__xludf.DUMMYFUNCTION("""COMPUTED_VALUE"""),"YES") -> YES | P64: =IFERROR(__xludf.DUMMYFUNCTION("""COMPUTED_VALUE"""),"NO") -> NO | Q64: =IFERROR(__xludf.DUMMYFUNCTION("""COMPUTED_VALUE"""),"NO") -> NO | U64: =IFERROR(__xludf.DUMMYFUNCTION("""COMPUTED_VALUE"""),"Park Ave & 42 St (SW corner) to mezzanine for 4/5/6 service") -> Park Ave & 42 St (SW corner) to mezzanine for 4/5/6 service | V64: =IFERROR(__xludf.DUMMYFUNCTION("""COMPUTED_VALUE"""),"POINT (-73.97919 40.75276)") -> POINT (-73.97919 40.75276)
A65: =IFERROR(__xludf.DUMMYFUNCTION("""COMPUTED_VALUE"""),"34 St-Herald Sq") -> 34 St-Herald Sq | B65: =IFERROR(__xludf.DUMMYFUNCTION("""COMPUTED_VALUE"""),"Broadway Line") -> Broadway Line | C65: =IFERROR(__xludf.DUMMYFUNCTION("""COMPUTED_VALUE"""),"Manhattan") -> Manhattan | D65: =IFERROR(__xludf.DUMMYFUNCTION("""COMPUTED_VALUE"""),"Midtown") -> Midtown | E65: =IFERROR(__xludf.DUMMYFUNCTION("""COMPUTED_VALUE"""),6580.0) -> 6580 | F65: =IFERROR(__xludf.DUMMYFUNCTION("""COMPUTED_VALUE"""),2.5012549E7) -> 25012549 | G65: =IFERROR(__xludf.DUMMYFUNCTION("""COMPUTED_VALUE"""),3.0) -> 3 | H65: =IFERROR(__xludf.DUMMYFUNCTION("""COMPUTED_VALUE"""),"↗️") -> ↗️ | I65: =IFERROR(__xludf.DUMMYFUNCTION("""COMPUTED_VALUE"""),14960.0) -> 14960 | J65: =IFERROR(__xludf.DUMMYFUNCTION("""COMPUTED_VALUE"""),39044.0) -> 39044 | K65: =IFERROR(__xludf.DUMMYFUNCTION("""COMPUTED_VALUE"""),22.0) -> 22 | L65: =IFERROR(__xludf.DUMMYFUNCTION("""COMPUTED_VALUE"""),"YES") -> YES | M65: =IFERROR(__xludf.DUMMYFUNCTION("""COMPUTED_VALUE"""),"NYCT") -> NYCT | N65: =IFERROR(__xludf.DUMMYFUNCTION("""COMPUTED_VALUE"""),"FUJITEC") -> FUJITEC | O65: =IFERROR(__xludf.DUMMYFUNCTION("""COMPUTED_VALUE"""),"YES") -> YES | P65: =IFERROR(__xludf.DUMMYFUNCTION("""COMPUTED_VALUE"""),"NO") -> NO | Q65: =IFERROR(__xludf.DUMMYFUNCTION("""COMPUTED_VALUE"""),"NO") -> NO | R65: =IFERROR(__xludf.DUMMYFUNCTION("""COMPUTED_VALUE"""),"30'") -> 30' | S65: =IFERROR(__xludf.DUMMYFUNCTION("""COMPUTED_VALUE"""),110.0) -> 110 | T65: =IFERROR(__xludf.DUMMYFUNCTION("""COMPUTED_VALUE"""),24.0) -> 24 | U65: =IFERROR(__xludf.DUMMYFUNCTION("""COMPUTED_VALUE"""),"uptown B/D/F/M platform to mezzanine for N/Q/R/W service") -> uptown B/D/F/M platform to mezzanine for N/Q/R/W service | V65: =IFERROR(__xludf.DUMMYFUNCTION("""COMPUTED_VALUE"""),"POINT (-73.98772 40.749756)") -> POINT (-73.98772 40.749756)
A66: =IFERROR(__xludf.DUMMYFUNCTION("""COMPUTED_VALUE"""),"72 St") -> 72 St | B66: =IFERROR(__xludf.DUMMYFUNCTION("""COMPUTED_VALUE"""),"Broadway-7 Av Line") -> Broadway-7 Av Line | C66: =IFERROR(__xludf.DUMMYFUNCTION("""COMPUTED_VALUE"""),"Manhattan") -> Manhattan | D66: =IFERROR(__xludf.DUMMYFUNCTION("""COMPUTED_VALUE"""),"Upper West Side") -> Upper West Side | E66: =IFERROR(__xludf.DUMMYFUNCTION("""COMPUTED_VALUE"""),1762.0) -> 1762 | F66: =IFERROR(__xludf.DUMMYFUNCTION("""COMPUTED_VALUE"""),9752193.0) -> 9752193 | G66: =IFERROR(__xludf.DUMMYFUNCTION("""COMPUTED_VALUE"""),22.0) -> 22 | H66: =IFERROR(__xludf.DUMMYFUNCTION("""COMPUTED_VALUE"""),"↗️") -> ↗️ | I66: =IFERROR(__xludf.DUMMYFUNCTION("""COMPUTED_VALUE"""),42736.0) -> 42736 | J66: =IFERROR(__xludf.DUMMYFUNCTION("""COMPUTED_VALUE"""),42736.0) -> 42736 | K66: =IFERROR(__xludf.DUMMYFUNCTION("""COMPUTED_VALUE"""),22.0) -> 22 | L66: =IFERROR(__xludf.DUMMYFUNCTION("""COMPUTED_VALUE"""),"YES") -> YES | M66: =IFERROR(__xludf.DUMMYFUNCTION("""COMPUTED_VALUE"""),"NYCT") -> NYCT | N66: =IFERROR(__xludf.DUMMYFUNCTION("""COMPUTED_VALUE"""),"SCHINDLER") -> SCHINDLER | O66: =IFERROR(__xludf.DUMMYFUNCTION("""COMPUTED_VALUE"""),"YES") -> YES | P66: =IFERROR(__xludf.DUMMYFUNCTION("""COMPUTED_VALUE"""),"YES") -> YES | Q66: =IFERROR(__xludf.DUMMYFUNCTION("""COMPUTED_VALUE"""),"YES") -> YES | R66: =IFERROR(__xludf.DUMMYFUNCTION("""COMPUTED_VALUE"""),"3783 mm (12' 4 23/25in)") -> 3783 mm (12' 4 23/25in) | S66: =IFERROR(__xludf.DUMMYFUNCTION("""COMPUTED_VALUE"""),0.0) -> 0 | U66: =IFERROR(__xludf.DUMMYFUNCTION("""COMPUTED_VALUE"""),"upper mezzanine to 70 St & 2nd Ave (SE corner)") -> upper mezzanine to 70 St & 2nd Ave (SE corner) | V66: =IFERROR(__xludf.DUMMYFUNCTION("""COMPUTED_VALUE"""),"POINT (-73.95946 40.767166)") -> POINT (-73.95946 40.767166)
A67: =IFERROR(__xludf.DUMMYFUNCTION("""COMPUTED_VALUE"""),"96 St") -> 96 St | B67: =IFERROR(__xludf.DUMMYFUNCTION("""COMPUTED_VALUE"""),"Broadway-7 Av Line") -> Broadway-7 Av Line | C67: =IFERROR(__xludf.DUMMYFUNCTION("""COMPUTED_VALUE"""),"Manhattan") -> Manhattan | D67: =IFERROR(__xludf.DUMMYFUNCTION("""COMPUTED_VALUE"""),"Upper West Side") -> Upper West Side | E67: =IFERROR(__xludf.DUMMYFUNCTION("""COMPUTED_VALUE"""),1762.0) -> 1762 | F67: =IFERROR(__xludf.DUMMYFUNCTION("""COMPUTED_VALUE"""),8250940.0) -> 8250940 | G67: =IFERROR(__xludf.DUMMYFUNCTION("""COMPUTED_VALUE"""),26.0) -> 26 | H67: =IFERROR(__xludf.DUMMYFUNCTION("""COMPUTED_VALUE"""),"↗️") -> ↗️ | I67: =IFERROR(__xludf.DUMMYFUNCTION("""COMPUTED_VALUE"""),42736.0) -> 42736 | J67: =IFERROR(__xludf.DUMMYFUNCTION("""COMPUTED_VALUE"""),42736.0) -> 42736 | K67: =IFERROR(__xludf.DUMMYFUNCTION("""COMPUTED_VALUE"""),22.0) -> 22 | L67: =IFERROR(__xludf.DUMMYFUNCTION("""COMPUTED_VALUE"""),"YES") -> YES | M67: =IFERROR(__xludf.DUMMYFUNCTION("""COMPUTED_VALUE"""),"NYCT") -> NYCT | N67: =IFERROR(__xludf.DUMMYFUNCTION("""COMPUTED_VALUE"""),"KONE") -> KONE | O67: =IFERROR(__xludf.DUMMYFUNCTION("""COMPUTED_VALUE"""),"YES") -> YES | P67: =IFERROR(__xludf.DUMMYFUNCTION("""COMPUTED_VALUE"""),"NO") -> NO | Q67: =IFERROR(__xludf.DUMMYFUNCTION("""COMPUTED_VALUE"""),"NO") -> NO | R67: =IFERROR(__xludf.DUMMYFUNCTION("""COMPUTED_VALUE"""),"5137mm (16' 10 1/4in)") -> 5137mm (16' 10 1/4in) | S67: =IFERROR(__xludf.DUMMYFUNCTION("""COMPUTED_VALUE"""),77.0) -> 77 | T67: =IFERROR(__xludf.DUMMYFUNCTION("""COMPUTED_VALUE"""),"1000 mm (39 3/8in)") -> 1000 mm (39 3/8in) | U67: =IFERROR(__xludf.DUMMYFUNCTION("""COMPUTED_VALUE"""),"platform to mezzanine for 94 St & 2nd Ave exit") -> platform to mezzanine for 94 St & 2nd Ave exit | V67: =IFERROR(__xludf.DUMMYFUNCTION("""COMPUTED_VALUE"""),"POINT (-73.9479 40.782997)") -> POINT (-73.9479 40.782997)
A68: =IFERROR(__xludf.DUMMYFUNCTION("""COMPUTED_VALUE"""),"86 St") -> 86 St | B68: =IFERROR(__xludf.DUMMYFUNCTION("""COMPUTED_VALUE"""),"4 Av Line") -> 4 Av Line | C68: =IFERROR(__xludf.DUMMYFUNCTION("""COMPUTED_VALUE"""),"Brooklyn") -> Brooklyn | D68: =IFERROR(__xludf.DUMMYFUNCTION("""COMPUTED_VALUE"""),"Bay Ridge") -> Bay Ridge | E68: =IFERROR(__xludf.DUMMYFUNCTION("""COMPUTED_VALUE"""),5859.0) -> 5859 | F68: =IFERROR(__xludf.DUMMYFUNCTION("""COMPUTED_VALUE"""),2580130.0) -> 2580130 | G68: =IFERROR(__xludf.DUMMYFUNCTION("""COMPUTED_VALUE"""),135.0) -> 135 | H68: =IFERROR(__xludf.DUMMYFUNCTION("""COMPUTED_VALUE"""),"↗️") -> ↗️ | I68: =IFERROR(__xludf.DUMMYFUNCTION("""COMPUTED_VALUE"""),42736.0) -> 42736 | J68: =IFERROR(__xludf.DUMMYFUNCTION("""COMPUTED_VALUE"""),42736.0) -> 42736 | K68: =IFERROR(__xludf.DUMMYFUNCTION("""COMPUTED_VALUE"""),22.0) -> 22 | L68: =IFERROR(__xludf.DUMMYFUNCTION("""COMPUTED_VALUE"""),"YES") -> YES | M68: =IFERROR(__xludf.DUMMYFUNCTION("""COMPUTED_VALUE"""),"NYCT") -> NYCT | N68: =IFERROR(__xludf.DUMMYFUNCTION("""COMPUTED_VALUE"""),"KONE") -> KONE | O68: =IFERROR(__xludf.DUMMYFUNCTION("""COMPUTED_VALUE"""),"YES") -> YES | P68: =IFERROR(__xludf.DUMMYFUNCTION("""COMPUTED_VALUE"""),"YES") -> YES | Q68: =IFERROR(__xludf.DUMMYFUNCTION("""COMPUTED_VALUE"""),"YES") -> YES | R68: =IFERROR(__xludf.DUMMYFUNCTION("""COMPUTED_VALUE"""),"23,519 mm (77' 1 15/16in)") -> 23,519 mm (77' 1 15/16in) | S68: =IFERROR(__xludf.DUMMYFUNCTION("""COMPUTED_VALUE"""),269.0) -> 269 | U68: =IFERROR(__xludf.DUMMYFUNCTION("""COMPUTED_VALUE"""),"lower mezzanine to 83 St & 2nd Ave (NE corner)") -> lower mezzanine to 83 St & 2nd Ave (NE corner) | V68: =IFERROR(__xludf.DUMMYFUNCTION("""COMPUTED_VALUE"""),"POINT (-73.95273 40.7762)") -> POINT (-73.95273 40.7762)
A69: =IFERROR(__xludf.DUMMYFUNCTION("""COMPUTED_VALUE"""),"Bowling Green") -> Bowling Green | B69: =IFERROR(__xludf.DUMMYFUNCTION("""COMPUTED_VALUE"""),"Lexington Av Line") -> Lexington Av Line | C69: =IFERROR(__xludf.DUMMYFUNCTION("""COMPUTED_VALUE"""),"Manhattan") -> Manhattan | D69: =IFERROR(__xludf.DUMMYFUNCTION("""COMPUTED_VALUE"""),"Financial District") -> Financial District | E69: =IFERROR(__xludf.DUMMYFUNCTION("""COMPUTED_VALUE"""),2018.0) -> 2018 | F69: =IFERROR(__xludf.DUMMYFUNCTION("""COMPUTED_VALUE"""),4676646.0) -> 4676646 | G69: =IFERROR(__xludf.DUMMYFUNCTION("""COMPUTED_VALUE"""),62.0) -> 62 | H69: =IFERROR(__xludf.DUMMYFUNCTION("""COMPUTED_VALUE"""),"↗️") -> ↗️ | I69: =IFERROR(__xludf.DUMMYFUNCTION("""COMPUTED_VALUE"""),28216.0) -> 28216 | J69: =IFERROR(__xludf.DUMMYFUNCTION("""COMPUTED_VALUE"""),37723.0) -> 37723 | K69: =IFERROR(__xludf.DUMMYFUNCTION("""COMPUTED_VALUE"""),22.0) -> 22 | L69: =IFERROR(__xludf.DUMMYFUNCTION("""COMPUTED_VALUE"""),"YES") -> YES | M69: =IFERROR(__xludf.DUMMYFUNCTION("""COMPUTED_VALUE"""),"NYCT") -> NYCT | N69: =IFERROR(__xludf.DUMMYFUNCTION("""COMPUTED_VALUE"""),"FUJITEC") -> FUJITEC | O69: =IFERROR(__xludf.DUMMYFUNCTION("""COMPUTED_VALUE"""),"YES") -> YES | P69: =IFERROR(__xludf.DUMMYFUNCTION("""COMPUTED_VALUE"""),"NO") -> NO | Q69: =IFERROR(__xludf.DUMMYFUNCTION("""COMPUTED_VALUE"""),"NO") -> NO | R69: =IFERROR(__xludf.DUMMYFUNCTION("""COMPUTED_VALUE"""),"24'") -> 24' | S69: =IFERROR(__xludf.DUMMYFUNCTION("""COMPUTED_VALUE"""),90.0) -> 90 | T69: =IFERROR(__xludf.DUMMYFUNCTION("""COMPUTED_VALUE"""),40.0) -> 40 | U69: =IFERROR(__xludf.DUMMYFUNCTION("""COMPUTED_VALUE"""),"uptown 4/5 mezzanine to lower mezzanine for downtown 4/5 service") -> uptown 4/5 mezzanine to lower mezzanine for downtown 4/5 service | V69: =IFERROR(__xludf.DUMMYFUNCTION("""COMPUTED_VALUE"""),"POINT (-74.01384 40.704594)") -> POINT (-74.01384 40.704594)
A70: =IFERROR(__xludf.DUMMYFUNCTION("""COMPUTED_VALUE"""),"59 St") -> 59 St | B70: =IFERROR(__xludf.DUMMYFUNCTION("""COMPUTED_VALUE"""),"4 Av Line") -> 4 Av Line | C70: =IFERROR(__xludf.DUMMYFUNCTION("""COMPUTED_VALUE"""),"Brooklyn") -> Brooklyn | D70: =IFERROR(__xludf.DUMMYFUNCTION("""COMPUTED_VALUE"""),"Sunset Park") -> Sunset Park | E70: =IFERROR(__xludf.DUMMYFUNCTION("""COMPUTED_VALUE"""),5652.0) -> 5652 | F70: =IFERROR(__xludf.DUMMYFUNCTION("""COMPUTED_VALUE"""),2952891.0) -> 2952891 | G70: =IFERROR(__xludf.DUMMYFUNCTION("""COMPUTED_VALUE"""),112.0) -> 112 | H70: =IFERROR(__xludf.DUMMYFUNCTION("""COMPUTED_VALUE"""),"↗️") -> ↗️ | I70: =IFERROR(__xludf.DUMMYFUNCTION("""COMPUTED_VALUE"""),22965.0) -> 22965 | J70: =IFERROR(__xludf.DUMMYFUNCTION("""COMPUTED_VALUE"""),45710.0) -> 45710 | K70: =IFERROR(__xludf.DUMMYFUNCTION("""COMPUTED_VALUE"""),22.0) -> 22 | L70: =IFERROR(__xludf.DUMMYFUNCTION("""COMPUTED_VALUE"""),"YES") -> YES | M70: =IFERROR(__xludf.DUMMYFUNCTION("""COMPUTED_VALUE"""),"NYCT") -> NYCT | N70: =IFERROR(__xludf.DUMMYFUNCTION("""COMPUTED_VALUE"""),"KONE") -> KONE | O70: =IFERROR(__xludf.DUMMYFUNCTION("""COMPUTED_VALUE"""),"YES") -> YES | P70: =IFERROR(__xludf.DUMMYFUNCTION("""COMPUTED_VALUE"""),"NO") -> NO | Q70: =IFERROR(__xludf.DUMMYFUNCTION("""COMPUTED_VALUE"""),"NO") -> NO | R70: =IFERROR(__xludf.DUMMYFUNCTION("""COMPUTED_VALUE"""),"50'") -> 50' | S70: =IFERROR(__xludf.DUMMYFUNCTION("""COMPUTED_VALUE"""),173.0) -> 173 | T70: =IFERROR(__xludf.DUMMYFUNCTION("""COMPUTED_VALUE"""),"10in") -> 10in | U70: =IFERROR(__xludf.DUMMYFUNCTION("""COMPUTED_VALUE"""),"downtown 4/5 platform to downtown 6 platform") -> downtown 4/5 platform to downtown 6 platform | V70: =IFERROR(__xludf.DUMMYFUNCTION("""COMPUTED_VALUE"""),"POINT (-73.96808 40.76221)") -> POINT (-73.96808 40.76221)
A71: =IFERROR(__xludf.DUMMYFUNCTION("""COMPUTED_VALUE"""),"181 St") -> 181 St | B71: =IFERROR(__xludf.DUMMYFUNCTION("""COMPUTED_VALUE"""),"8 Av Line") -> 8 Av Line | C71: =IFERROR(__xludf.DUMMYFUNCTION("""COMPUTED_VALUE"""),"Manhattan") -> Manhattan | D71: =IFERROR(__xludf.DUMMYFUNCTION("""COMPUTED_VALUE"""),"Washington Heights") -> Washington Heights | E71: =IFERROR(__xludf.DUMMYFUNCTION("""COMPUTED_VALUE"""),11942.0) -> 11942 | F71: =IFERROR(__xludf.DUMMYFUNCTION("""COMPUTED_VALUE"""),2042771.0) -> 2042771 | G71: =IFERROR(__xludf.DUMMYFUNCTION("""COMPUTED_VALUE"""),160.0) -> 160 | H71: =IFERROR(__xludf.DUMMYFUNCTION("""COMPUTED_VALUE"""),"↗️") -> ↗️ | I71: =IFERROR(__xludf.DUMMYFUNCTION("""COMPUTED_VALUE"""),13656.0) -> 13656 | J71: =IFERROR(__xludf.DUMMYFUNCTION("""COMPUTED_VALUE"""),45016.0) -> 45016 | K71: =IFERROR(__xludf.DUMMYFUNCTION("""COMPUTED_VALUE"""),22.0) -> 22 | L71: =IFERROR(__xludf.DUMMYFUNCTION("""COMPUTED_VALUE"""),"YES") -> YES | M71: =IFERROR(__xludf.DUMMYFUNCTION("""COMPUTED_VALUE"""),"NYCT") -> NYCT | N71: =IFERROR(__xludf.DUMMYFUNCTION("""COMPUTED_VALUE"""),"KONE") -> KONE | O71: =IFERROR(__xludf.DUMMYFUNCTION("""COMPUTED_VALUE"""),"YES") -> YES | P71: =IFERROR(__xludf.DUMMYFUNCTION("""COMPUTED_VALUE"""),"NO") -> NO | Q71: =IFERROR(__xludf.DUMMYFUNCTION("""COMPUTED_VALUE"""),"NO") -> NO | R71: =IFERROR(__xludf.DUMMYFUNCTION("""COMPUTED_VALUE"""),"15824 mm (51'-11in)") -> 15824 mm (51'-11in) | S71: =IFERROR(__xludf.DUMMYFUNCTION("""COMPUTED_VALUE"""),112.0) -> 112 | T71: =IFERROR(__xludf.DUMMYFUNCTION("""COMPUTED_VALUE"""),"600 mm (24in NOMINAL)") -> 600 mm (24in NOMINAL) | U71: =IFERROR(__xludf.DUMMYFUNCTION("""COMPUTED_VALUE"""),"lower mezzanine to upper mezzanine for 181 St & Fort Washington Ave exit") -> lower mezzanine to upper mezzanine for 181 St & Fort Washington Ave exit | V71: =IFERROR(__xludf.DUMMYFUNCTION("""COMPUTED_VALUE"""),"POINT (-73.93812 40.851116)") -> POINT (-73.93812 40.851116)
A72: =IFERROR(__xludf.DUMMYFUNCTION("""COMPUTED_VALUE"""),"86 St") -> 86 St | B72: =IFERROR(__xludf.DUMMYFUNCTION("""COMPUTED_VALUE"""),"4 Av Line") -> 4 Av Line | C72: =IFERROR(__xludf.DUMMYFUNCTION("""COMPUTED_VALUE"""),"Brooklyn") -> Brooklyn | D72: =IFERROR(__xludf.DUMMYFUNCTION("""COMPUTED_VALUE"""),"Bay Ridge") -> Bay Ridge | E72: =IFERROR(__xludf.DUMMYFUNCTION("""COMPUTED_VALUE"""),5859.0) -> 5859 | F72: =IFERROR(__xludf.DUMMYFUNCTION("""COMPUTED_VALUE"""),2580130.0) -> 2580130 | G72: =IFERROR(__xludf.DUMMYFUNCTION("""COMPUTED_VALUE"""),135.0) -> 135 | H72: =IFERROR(__xludf.DUMMYFUNCTION("""COMPUTED_VALUE"""),"↗️") -> ↗️ | I72: =IFERROR(__xludf.DUMMYFUNCTION("""COMPUTED_VALUE"""),42736.0) -> 42736 | J72: =IFERROR(__xludf.DUMMYFUNCTION("""COMPUTED_VALUE"""),42736.0) -> 42736 | K72: =IFERROR(__xludf.DUMMYFUNCTION("""COMPUTED_VALUE"""),22.0) -> 22 | L72: =IFERROR(__xludf.DUMMYFUNCTION("""COMPUTED_VALUE"""),"YES") -> YES | M72: =IFERROR(__xludf.DUMMYFUNCTION("""COMPUTED_VALUE"""),"NYCT") -> NYCT | N72: =IFERROR(__xludf.DUMMYFUNCTION("""COMPUTED_VALUE"""),"KONE") -> KONE | O72: =IFERROR(__xludf.DUMMYFUNCTION("""COMPUTED_VALUE"""),"YES") -> YES | P72: =IFERROR(__xludf.DUMMYFUNCTION("""COMPUTED_VALUE"""),"YES") -> YES | Q72: =IFERROR(__xludf.DUMMYFUNCTION("""COMPUTED_VALUE"""),"YES") -> YES | R72: =IFERROR(__xludf.DUMMYFUNCTION("""COMPUTED_VALUE"""),"9950 mm (32 ' 7 3/4in)") -> 9950 mm (32 ' 7 3/4in) | S72: =IFERROR(__xludf.DUMMYFUNCTION("""COMPUTED_VALUE"""),125.0) -> 125 | U72: =IFERROR(__xludf.DUMMYFUNCTION("""COMPUTED_VALUE"""),"upper mezzanine to 86 St & 2nd Ave (NE corner)") -> upper mezzanine to 86 St & 2nd Ave (NE corner) | V72: =IFERROR(__xludf.DUMMYFUNCTION("""COMPUTED_VALUE"""),"POINT (-73.9514 40.77784)") -> POINT (-73.9514 40.77784)
A73: =IFERROR(__xludf.DUMMYFUNCTION("""COMPUTED_VALUE"""),"125 St") -> 125 St | B73: =IFERROR(__xludf.DUMMYFUNCTION("""COMPUTED_VALUE"""),"Broadway-7 Av Line") -> Broadway-7 Av Line | C73: =IFERROR(__xludf.DUMMYFUNCTION("""COMPUTED_VALUE"""),"Manhattan") -> Manhattan | D73: =IFERROR(__xludf.DUMMYFUNCTION("""COMPUTED_VALUE"""),"Manhattanville") -> Manhattanville | E73: =IFERROR(__xludf.DUMMYFUNCTION("""COMPUTED_VALUE"""),1762.0) -> 1762 | F73: =IFERROR(__xludf.DUMMYFUNCTION("""COMPUTED_VALUE"""),1977586.0) -> 1977586 | G73: =IFERROR(__xludf.DUMMYFUNCTION("""COMPUTED_VALUE"""),165.0) -> 165 | H73: =IFERROR(__xludf.DUMMYFUNCTION("""COMPUTED_VALUE"""),"↗️") -> ↗️ | I73: =IFERROR(__xludf.DUMMYFUNCTION("""COMPUTED_VALUE"""),11592.0) -> 11592 | J73: =IFERROR(__xludf.DUMMYFUNCTION("""COMPUTED_VALUE"""),44743.0) -> 44743 | K73: =IFERROR(__xludf.DUMMYFUNCTION("""COMPUTED_VALUE"""),22.0) -> 22 | L73: =IFERROR(__xludf.DUMMYFUNCTION("""COMPUTED_VALUE"""),"YES") -> YES | M73: =IFERROR(__xludf.DUMMYFUNCTION("""COMPUTED_VALUE"""),"NYCT") -> NYCT | N73: =IFERROR(__xludf.DUMMYFUNCTION("""COMPUTED_VALUE"""),"KONE") -> KONE | O73: =IFERROR(__xludf.DUMMYFUNCTION("""COMPUTED_VALUE"""),"YES") -> YES | P73: =IFERROR(__xludf.DUMMYFUNCTION("""COMPUTED_VALUE"""),"YES") -> YES | Q73: =IFERROR(__xludf.DUMMYFUNCTION("""COMPUTED_VALUE"""),"YES") -> YES | R73: =IFERROR(__xludf.DUMMYFUNCTION("""COMPUTED_VALUE"""),"32'") -> 32' | S73: =IFERROR(__xludf.DUMMYFUNCTION("""COMPUTED_VALUE"""),114.0) -> 114 | T73: =IFERROR(__xludf.DUMMYFUNCTION("""COMPUTED_VALUE"""),40.0) -> 40 | U73: =IFERROR(__xludf.DUMMYFUNCTION("""COMPUTED_VALUE"""),"125 St & Broadway (SE corner) to mezzanine") -> 125 St & Broadway (SE corner) to mezzanine | V73: =IFERROR(__xludf.DUMMYFUNCTION("""COMPUTED_VALUE"""),"POINT (-73.958374 40.815235)") -> POINT (-73.958374 40.815235)
A74: =IFERROR(__xludf.DUMMYFUNCTION("""COMPUTED_VALUE"""),"Jamaica Center-Parsons/Archer") -> Jamaica Center-Parsons/Archer | B74: =IFERROR(__xludf.DUMMYFUNCTION("""COMPUTED_VALUE"""),"Archer Av Line") -> Archer Av Line | C74: =IFERROR(__xludf.DUMMYFUNCTION("""COMPUTED_VALUE"""),"Queens") -> Queens | D74: =IFERROR(__xludf.DUMMYFUNCTION("""COMPUTED_VALUE"""),"Jamaica") -> Jamaica | E74: =IFERROR(__xludf.DUMMYFUNCTION("""COMPUTED_VALUE"""),32488.0) -> 32488 | F74: =IFERROR(__xludf.DUMMYFUNCTION("""COMPUTED_VALUE"""),6137267.0) -> 6137267 | G74: =IFERROR(__xludf.DUMMYFUNCTION("""COMPUTED_VALUE"""),38.0) -> 38 | H74: =IFERROR(__xludf.DUMMYFUNCTION("""COMPUTED_VALUE"""),"↗️") -> ↗️ | I74: =IFERROR(__xludf.DUMMYFUNCTION("""COMPUTED_VALUE"""),32478.0) -> 32478 | J74: =IFERROR(__xludf.DUMMYFUNCTION("""COMPUTED_VALUE"""),39419.0) -> 39419 | K74: =IFERROR(__xludf.DUMMYFUNCTION("""COMPUTED_VALUE"""),22.0) -> 22 | L74: =IFERROR(__xludf.DUMMYFUNCTION("""COMPUTED_VALUE"""),"YES") -> YES | M74: =IFERROR(__xludf.DUMMYFUNCTION("""COMPUTED_VALUE"""),"NYCT") -> NYCT | N74: =IFERROR(__xludf.DUMMYFUNCTION("""COMPUTED_VALUE"""),"KONE") -> KONE | O74: =IFERROR(__xludf.DUMMYFUNCTION("""COMPUTED_VALUE"""),"YES") -> YES | P74: =IFERROR(__xludf.DUMMYFUNCTION("""COMPUTED_VALUE"""),"YES") -> YES | Q74: =IFERROR(__xludf.DUMMYFUNCTION("""COMPUTED_VALUE"""),"YES") -> YES | R74: =IFERROR(__xludf.DUMMYFUNCTION("""COMPUTED_VALUE"""),"25'") -> 25' | S74: =IFERROR(__xludf.DUMMYFUNCTION("""COMPUTED_VALUE"""),95.0) -> 95 | T74: =IFERROR(__xludf.DUMMYFUNCTION("""COMPUTED_VALUE"""),"40in") -> 40in | U74: =IFERROR(__xludf.DUMMYFUNCTION("""COMPUTED_VALUE"""),"mezzanine to Parsons Blvd & Archer Ave (SW corner)") -> mezzanine to Parsons Blvd & Archer Ave (SW corner) | V74: =IFERROR(__xludf.DUMMYFUNCTION("""COMPUTED_VALUE"""),"POINT (-73.79986 40.702667)") -> POINT (-73.79986 40.702667)
A75: =IFERROR(__xludf.DUMMYFUNCTION("""COMPUTED_VALUE"""),"34 St-Herald Sq") -> 34 St-Herald Sq | B75: =IFERROR(__xludf.DUMMYFUNCTION("""COMPUTED_VALUE"""),"Broadway Line") -> Broadway Line | C75: =IFERROR(__xludf.DUMMYFUNCTION("""COMPUTED_VALUE"""),"Manhattan") -> Manhattan | D75: =IFERROR(__xludf.DUMMYFUNCTION("""COMPUTED_VALUE"""),"Midtown") -> Midtown | E75: =IFERROR(__xludf.DUMMYFUNCTION("""COMPUTED_VALUE"""),6580.0) -> 6580 | F75: =IFERROR(__xludf.DUMMYFUNCTION("""COMPUTED_VALUE"""),2.5012549E7) -> 25012549 | G75: =IFERROR(__xludf.DUMMYFUNCTION("""COMPUTED_VALUE"""),3.0) -> 3 | H75: =IFERROR(__xludf.DUMMYFUNCTION("""COMPUTED_VALUE"""),"↗️") -> ↗️ | I75: =IFERROR(__xludf.DUMMYFUNCTION("""COMPUTED_VALUE"""),14960.0) -> 14960 | J75: =IFERROR(__xludf.DUMMYFUNCTION("""COMPUTED_VALUE"""),39044.0) -> 39044 | K75: =IFERROR(__xludf.DUMMYFUNCTION("""COMPUTED_VALUE"""),22.0) -> 22 | L75: =IFERROR(__xludf.DUMMYFUNCTION("""COMPUTED_VALUE"""),"YES") -> YES | M75: =IFERROR(__xludf.DUMMYFUNCTION("""COMPUTED_VALUE"""),"NYCT") -> NYCT | N75: =IFERROR(__xludf.DUMMYFUNCTION("""COMPUTED_VALUE"""),"FUJITEC") -> FUJITEC | O75: =IFERROR(__xludf.DUMMYFUNCTION("""COMPUTED_VALUE"""),"YES") -> YES | P75: =IFERROR(__xludf.DUMMYFUNCTION("""COMPUTED_VALUE"""),"NO") -> NO | Q75: =IFERROR(__xludf.DUMMYFUNCTION("""COMPUTED_VALUE"""),"NO") -> NO | R75: =IFERROR(__xludf.DUMMYFUNCTION("""COMPUTED_VALUE"""),"30'") -> 30' | S75: =IFERROR(__xludf.DUMMYFUNCTION("""COMPUTED_VALUE"""),109.0) -> 109 | T75: =IFERROR(__xludf.DUMMYFUNCTION("""COMPUTED_VALUE"""),24.0) -> 24 | U75: =IFERROR(__xludf.DUMMYFUNCTION("""COMPUTED_VALUE"""),"N/Q/R/W mezzanine to downtown B/D/F/M platform") -> N/Q/R/W mezzanine to downtown B/D/F/M platform | V75: =IFERROR(__xludf.DUMMYFUNCTION("""COMPUTED_VALUE"""),"POINT (-73.9877 40.75007)") -> POINT (-73.9877 40.75007)
A76: =IFERROR(__xludf.DUMMYFUNCTION("""COMPUTED_VALUE"""),"East Broadway") -> East Broadway | B76: =IFERROR(__xludf.DUMMYFUNCTION("""COMPUTED_VALUE"""),"6 Av Line") -> 6 Av Line | C76: =IFERROR(__xludf.DUMMYFUNCTION("""COMPUTED_VALUE"""),"Manhattan") -> Manhattan | D76: =IFERROR(__xludf.DUMMYFUNCTION("""COMPUTED_VALUE"""),"Lower East Side") -> Lower East Side | E76: =IFERROR(__xludf.DUMMYFUNCTION("""COMPUTED_VALUE"""),13150.0) -> 13150 | F76: =IFERROR(__xludf.DUMMYFUNCTION("""COMPUTED_VALUE"""),3596399.0) -> 3596399 | G76: =IFERROR(__xludf.DUMMYFUNCTION("""COMPUTED_VALUE"""),91.0) -> 91 | H76: =IFERROR(__xludf.DUMMYFUNCTION("""COMPUTED_VALUE"""),"↗️") -> ↗️ | I76: =IFERROR(__xludf.DUMMYFUNCTION("""COMPUTED_VALUE"""),30773.0) -> 30773 | J76: =IFERROR(__xludf.DUMMYFUNCTION("""COMPUTED_VALUE"""),41690.0) -> 41690 | K76: =IFERROR(__xludf.DUMMYFUNCTION("""COMPUTED_VALUE"""),22.0) -> 22 | L76: =IFERROR(__xludf.DUMMYFUNCTION("""COMPUTED_VALUE"""),"YES") -> YES | M76: =IFERROR(__xludf.DUMMYFUNCTION("""COMPUTED_VALUE"""),"NYCT") -> NYCT | N76: =IFERROR(__xludf.DUMMYFUNCTION("""COMPUTED_VALUE"""),"KONE") -> KONE | O76: =IFERROR(__xludf.DUMMYFUNCTION("""COMPUTED_VALUE"""),"YES") -> YES | P76: =IFERROR(__xludf.DUMMYFUNCTION("""COMPUTED_VALUE"""),"NO") -> NO | Q76: =IFERROR(__xludf.DUMMYFUNCTION("""COMPUTED_VALUE"""),"NO") -> NO | R76: =IFERROR(__xludf.DUMMYFUNCTION("""COMPUTED_VALUE"""),"29' 8 3/4in") -> 29' 8 3/4in | S76: =IFERROR(__xludf.DUMMYFUNCTION("""COMPUTED_VALUE"""),112.0) -> 112 | T76: =IFERROR(__xludf.DUMMYFUNCTION("""COMPUTED_VALUE"""),"40in") -> 40in | U76: =IFERROR(__xludf.DUMMYFUNCTION("""COMPUTED_VALUE"""),"F platform to mezzanine for East Broadway & Rutgers St exit") -> F platform to mezzanine for East Broadway & Rutgers St exit | V76: =IFERROR(__xludf.DUMMYFUNCTION("""COMPUTED_VALUE"""),"POINT (-73.990074 40.714214)") -> POINT (-73.990074 40.714214)
A77: =IFERROR(__xludf.DUMMYFUNCTION("""COMPUTED_VALUE"""),"Broadway Junction") -> Broadway Junction | B77: =IFERROR(__xludf.DUMMYFUNCTION("""COMPUTED_VALUE"""),"Canarsie Line") -> Canarsie Line | C77: =IFERROR(__xludf.DUMMYFUNCTION("""COMPUTED_VALUE"""),"Brooklyn") -> Brooklyn | D77: =IFERROR(__xludf.DUMMYFUNCTION("""COMPUTED_VALUE"""),"East New York") -> East New York | E77: =IFERROR(__xludf.DUMMYFUNCTION("""COMPUTED_VALUE"""),10423.0) -> 10423 | F77: =IFERROR(__xludf.DUMMYFUNCTION("""COMPUTED_VALUE"""),1808472.0) -> 1808472 | G77: =IFERROR(__xludf.DUMMYFUNCTION("""COMPUTED_VALUE"""),176.0) -> 176 | H77: =IFERROR(__xludf.DUMMYFUNCTION("""COMPUTED_VALUE"""),"↗️") -> ↗️ | I77: =IFERROR(__xludf.DUMMYFUNCTION("""COMPUTED_VALUE"""),35327.0) -> 35327 | J77: =IFERROR(__xludf.DUMMYFUNCTION("""COMPUTED_VALUE"""),35327.0) -> 35327 | K77: =IFERROR(__xludf.DUMMYFUNCTION("""COMPUTED_VALUE"""),22.0) -> 22 | L77: =IFERROR(__xludf.DUMMYFUNCTION("""COMPUTED_VALUE"""),"YES") -> YES | M77: =IFERROR(__xludf.DUMMYFUNCTION("""COMPUTED_VALUE"""),"NYCT") -> NYCT | N77: =IFERROR(__xludf.DUMMYFUNCTION("""COMPUTED_VALUE"""),"OK") -> OK | O77: =IFERROR(__xludf.DUMMYFUNCTION("""COMPUTED_VALUE"""),"YES") -> YES | P77: =IFERROR(__xludf.DUMMYFUNCTION("""COMPUTED_VALUE"""),"YES") -> YES | Q77: =IFERROR(__xludf.DUMMYFUNCTION("""COMPUTED_VALUE"""),"NO") -> NO | R77: =IFERROR(__xludf.DUMMYFUNCTION("""COMPUTED_VALUE"""),"43'") -> 43' | S77: =IFERROR(__xludf.DUMMYFUNCTION("""COMPUTED_VALUE"""),150.0) -> 150 | T77: =IFERROR(__xludf.DUMMYFUNCTION("""COMPUTED_VALUE"""),32.0) -> 32 | U77: =IFERROR(__xludf.DUMMYFUNCTION("""COMPUTED_VALUE"""),"A/C mezzanine (Van Sinderen Ave) to upper mezzanine for J/Z and L service") -> A/C mezzanine (Van Sinderen Ave) to upper mezzanine for J/Z and L service | V77: =IFERROR(__xludf.DUMMYFUNCTION("""COMPUTED_VALUE"""),"POINT (-73.9039 40.67856)") -> POINT (-73.9039 40.67856)
A78: =IFERROR(__xludf.DUMMYFUNCTION("""COMPUTED_VALUE"""),"Wall St") -> Wall St | B78: =IFERROR(__xludf.DUMMYFUNCTION("""COMPUTED_VALUE"""),"Broadway-7 Av Line") -> Broadway-7 Av Line | C78: =IFERROR(__xludf.DUMMYFUNCTION("""COMPUTED_VALUE"""),"Manhattan") -> Manhattan | D78: =IFERROR(__xludf.DUMMYFUNCTION("""COMPUTED_VALUE"""),"Financial District") -> Financial District | E78: =IFERROR(__xludf.DUMMYFUNCTION("""COMPUTED_VALUE"""),6757.0) -> 6757 | F78: =IFERROR(__xludf.DUMMYFUNCTION("""COMPUTED_VALUE"""),4112164.0) -> 4112164 | G78: =IFERROR(__xludf.DUMMYFUNCTION("""COMPUTED_VALUE"""),72.0) -> 72 | H78: =IFERROR(__xludf.DUMMYFUNCTION("""COMPUTED_VALUE"""),"↗️") -> ↗️ | J78: =IFERROR(__xludf.DUMMYFUNCTION("""COMPUTED_VALUE"""),40817.0) -> 40817 | K78: =IFERROR(__xludf.DUMMYFUNCTION("""COMPUTED_VALUE"""),22.0) -> 22 | L78: =IFERROR(__xludf.DUMMYFUNCTION("""COMPUTED_VALUE"""),"NO") -> NO | M78: =IFERROR(__xludf.DUMMYFUNCTION("""COMPUTED_VALUE"""),"Private Contractor") -> Private Contractor | N78: =IFERROR(__xludf.DUMMYFUNCTION("""COMPUTED_VALUE"""),"AM") -> AM | O78: =IFERROR(__xludf.DUMMYFUNCTION("""COMPUTED_VALUE"""),"YES") -> YES | P78: =IFERROR(__xludf.DUMMYFUNCTION("""COMPUTED_VALUE"""),"NO") -> NO | Q78: =IFERROR(__xludf.DUMMYFUNCTION("""COMPUTED_VALUE"""),"NO") -> NO | S78: =IFERROR(__xludf.DUMMYFUNCTION("""COMPUTED_VALUE"""),0.0) -> 0 | U78: =IFERROR(__xludf.DUMMYFUNCTION("""COMPUTED_VALUE"""),"60 Wall St atrium (between William St & Pearl St) to mezzanine for 2/3 service") -> 60 Wall St atrium (between William St & Pearl St) to mezzanine for 2/3 service | V78: =IFERROR(__xludf.DUMMYFUNCTION("""COMPUTED_VALUE"""),"POINT (-74.00872 40.706657)") -> POINT (-74.00872 40.706657)
A79: =IFERROR(__xludf.DUMMYFUNCTION("""COMPUTED_VALUE"""),"Lexington Av/63 St") -> Lexington Av/63 St | B79: =IFERROR(__xludf.DUMMYFUNCTION("""COMPUTED_VALUE"""),"") | C79: =IFERROR(__xludf.DUMMYFUNCTION("""COMPUTED_VALUE"""),"") | D79: =IFERROR(__xludf.DUMMYFUNCTION("""COMPUTED_VALUE"""),"") | E79: =IFERROR(__xludf.DUMMYFUNCTION("""COMPUTED_VALUE"""),"") | F79: =IFERROR(__xludf.DUMMYFUNCTION("""COMPUTED_VALUE"""),"") | G79: =IFERROR(__xludf.DUMMYFUNCTION("""COMPUTED_VALUE"""),"") | H79: =IFERROR(__xludf.DUMMYFUNCTION("""COMPUTED_VALUE"""),"↗️") -> ↗️ | I79: =IFERROR(__xludf.DUMMYFUNCTION("""COMPUTED_VALUE"""),42734.0) -> 42734 | J79: =IFERROR(__xludf.DUMMYFUNCTION("""COMPUTED_VALUE"""),42734.0) -> 42734 | K79: =IFERROR(__xludf.DUMMYFUNCTION("""COMPUTED_VALUE"""),22.0) -> 22 | L79: =IFERROR(__xludf.DUMMYFUNCTION("""COMPUTED_VALUE"""),"YES") -> YES | M79: =IFERROR(__xludf.DUMMYFUNCTION("""COMPUTED_VALUE"""),"NYCT") -> NYCT | N79: =IFERROR(__xludf.DUMMYFUNCTION("""COMPUTED_VALUE"""),"KONE") -> KONE | O79: =IFERROR(__xludf.DUMMYFUNCTION("""COMPUTED_VALUE"""),"YES") -> YES | P79: =IFERROR(__xludf.DUMMYFUNCTION("""COMPUTED_VALUE"""),"YES") -> YES | Q79: =IFERROR(__xludf.DUMMYFUNCTION("""COMPUTED_VALUE"""),"YES") -> YES | R79: =IFERROR(__xludf.DUMMYFUNCTION("""COMPUTED_VALUE"""),"9611mm (31' 6 3/8in)") -> 9611mm (31' 6 3/8in) | S79: =IFERROR(__xludf.DUMMYFUNCTION("""COMPUTED_VALUE"""),122.0) -> 122 | T79: =IFERROR(__xludf.DUMMYFUNCTION("""COMPUTED_VALUE"""),"Step Width 996 mm (39 3/8in)") -> Step Width 996 mm (39 3/8in) | U79: =IFERROR(__xludf.DUMMYFUNCTION("""COMPUTED_VALUE"""),"3rd Ave & 63 St (SE corner) to mezzanine") -> 3rd Ave & 63 St (SE corner) to mezzanine | V79: =IFERROR(__xludf.DUMMYFUNCTION("""COMPUTED_VALUE"""),"POINT (-73.9646 40.76388)") -> POINT (-73.9646 40.76388)
A80: =IFERROR(__xludf.DUMMYFUNCTION("""COMPUTED_VALUE"""),"74 St-Broadway") -> 74 St-Broadway | B80: =IFERROR(__xludf.DUMMYFUNCTION("""COMPUTED_VALUE"""),"") | C80: =IFERROR(__xludf.DUMMYFUNCTION("""COMPUTED_VALUE"""),"") | D80: =IFERROR(__xludf.DUMMYFUNCTION("""COMPUTED_VALUE"""),"") | E80: =IFERROR(__xludf.DUMMYFUNCTION("""COMPUTED_VALUE"""),"") | F80: =IFERROR(__xludf.DUMMYFUNCTION("""COMPUTED_VALUE"""),"") | G80: =IFERROR(__xludf.DUMMYFUNCTION("""COMPUTED_VALUE"""),"") | H80: =IFERROR(__xludf.DUMMYFUNCTION("""COMPUTED_VALUE"""),"↗️") -> ↗️ | I80: =IFERROR(__xludf.DUMMYFUNCTION("""COMPUTED_VALUE"""),36363.0) -> 36363 | J80: =IFERROR(__xludf.DUMMYFUNCTION("""COMPUTED_VALUE"""),45596.0) -> 45596 | K80: =IFERROR(__xludf.DUMMYFUNCTION("""COMPUTED_VALUE"""),22.0) -> 22 | L80: =IFERROR(__xludf.DUMMYFUNCTION("""COMPUTED_VALUE"""),"YES") -> YES | M80: =IFERROR(__xludf.DUMMYFUNCTION("""COMPUTED_VALUE"""),"NYCT") -> NYCT | N80: =IFERROR(__xludf.DUMMYFUNCTION("""COMPUTED_VALUE"""),"OK") -> OK | O80: =IFERROR(__xludf.DUMMYFUNCTION("""COMPUTED_VALUE"""),"YES") -> YES | P80: =IFERROR(__xludf.DUMMYFUNCTION("""COMPUTED_VALUE"""),"NO") -> NO | Q80: =IFERROR(__xludf.DUMMYFUNCTION("""COMPUTED_VALUE"""),"NO") -> NO | R80: =IFERROR(__xludf.DUMMYFUNCTION("""COMPUTED_VALUE"""),"31'") -> 31' | S80: =IFERROR(__xludf.DUMMYFUNCTION("""COMPUTED_VALUE"""),115.0) -> 115 | T80: =IFERROR(__xludf.DUMMYFUNCTION("""COMPUTED_VALUE"""),"40in") -> 40in | U80: =IFERROR(__xludf.DUMMYFUNCTION("""COMPUTED_VALUE"""),"7 underpass to lower mezzanine for E/F/M/R service") -> 7 underpass to lower mezzanine for E/F/M/R service | V80: =IFERROR(__xludf.DUMMYFUNCTION("""COMPUTED_VALUE"""),"POINT (-73.89245 40.74686)") -> POINT (-73.89245 40.74686)
A81: =IFERROR(__xludf.DUMMYFUNCTION("""COMPUTED_VALUE"""),"W 4 St-Wash Sq") -> W 4 St-Wash Sq | B81: =IFERROR(__xludf.DUMMYFUNCTION("""COMPUTED_VALUE"""),"") | C81: =IFERROR(__xludf.DUMMYFUNCTION("""COMPUTED_VALUE"""),"") | D81: =IFERROR(__xludf.DUMMYFUNCTION("""COMPUTED_VALUE"""),"") | E81: =IFERROR(__xludf.DUMMYFUNCTION("""COMPUTED_VALUE"""),"") | F81: =IFERROR(__xludf.DUMMYFUNCTION("""COMPUTED_VALUE"""),"") | G81: =IFERROR(__xludf.DUMMYFUNCTION("""COMPUTED_VALUE"""),"") | H81: =IFERROR(__xludf.DUMMYFUNCTION("""COMPUTED_VALUE"""),"↗️") -> ↗️ | I81: =IFERROR(__xludf.DUMMYFUNCTION("""COMPUTED_VALUE"""),25781.0) -> 25781 | J81: =IFERROR(__xludf.DUMMYFUNCTION("""COMPUTED_VALUE"""),45788.0) -> 45788 | K81: =IFERROR(__xludf.DUMMYFUNCTION("""COMPUTED_VALUE"""),22.0) -> 22 | L81: =IFERROR(__xludf.DUMMYFUNCTION("""COMPUTED_VALUE"""),"YES") -> YES | M81: =IFERROR(__xludf.DUMMYFUNCTION("""COMPUTED_VALUE"""),"NYCT") -> NYCT | N81: =IFERROR(__xludf.DUMMYFUNCTION("""COMPUTED_VALUE"""),"ALLEN BRADLEY") -> ALLEN BRADLEY | O81: =IFERROR(__xludf.DUMMYFUNCTION("""COMPUTED_VALUE"""),"YES") -> YES | P81: =IFERROR(__xludf.DUMMYFUNCTION("""COMPUTED_VALUE"""),"NO") -> NO | Q81: =IFERROR(__xludf.DUMMYFUNCTION("""COMPUTED_VALUE"""),"NO") -> NO | R81: =IFERROR(__xludf.DUMMYFUNCTION("""COMPUTED_VALUE"""),"24' 11 1/2in") -> 24' 11 1/2in | S81: =IFERROR(__xludf.DUMMYFUNCTION("""COMPUTED_VALUE"""),94.0) -> 94 | T81: =IFERROR(__xludf.DUMMYFUNCTION("""COMPUTED_VALUE"""),"40in") -> 40in | U81: =IFERROR(__xludf.DUMMYFUNCTION("""COMPUTED_VALUE"""),"downtown B/D/F/M platform to downtown A/C/E platform and access to street") -> downtown B/D/F/M platform to downtown A/C/E platform and access to street | V81: =IFERROR(__xludf.DUMMYFUNCTION("""COMPUTED_VALUE"""),"POINT (-74.000404 40.732605)") -> POINT (-74.000404 40.732605)
A82: =IFERROR(__xludf.DUMMYFUNCTION("""COMPUTED_VALUE"""),"Lexington Av/53 St") -> Lexington Av/53 St | B82: =IFERROR(__xludf.DUMMYFUNCTION("""COMPUTED_VALUE"""),"") | C82: =IFERROR(__xludf.DUMMYFUNCTION("""COMPUTED_VALUE"""),"") | D82: =IFERROR(__xludf.DUMMYFUNCTION("""COMPUTED_VALUE"""),"") | E82: =IFERROR(__xludf.DUMMYFUNCTION("""COMPUTED_VALUE"""),"") | F82: =IFERROR(__xludf.DUMMYFUNCTION("""COMPUTED_VALUE"""),"") | G82: =IFERROR(__xludf.DUMMYFUNCTION("""COMPUTED_VALUE"""),"") | H82: =IFERROR(__xludf.DUMMYFUNCTION("""COMPUTED_VALUE"""),"↗️") -> ↗️ | J82: =IFERROR(__xludf.DUMMYFUNCTION("""COMPUTED_VALUE"""),40700.0) -> 40700 | K82: =IFERROR(__xludf.DUMMYFUNCTION("""COMPUTED_VALUE"""),22.0) -> 22 | L82: =IFERROR(__xludf.DUMMYFUNCTION("""COMPUTED_VALUE"""),"NO") -> NO | M82: =IFERROR(__xludf.DUMMYFUNCTION("""COMPUTED_VALUE"""),"Private Contractor") -> Private Contractor | N82: =IFERROR(__xludf.DUMMYFUNCTION("""COMPUTED_VALUE"""),"AM") -> AM | O82: =IFERROR(__xludf.DUMMYFUNCTION("""COMPUTED_VALUE"""),"YES") -> YES | P82: =IFERROR(__xludf.DUMMYFUNCTION("""COMPUTED_VALUE"""),"NO") -> NO | Q82: =IFERROR(__xludf.DUMMYFUNCTION("""COMPUTED_VALUE"""),"NO") -> NO | S82: =IFERROR(__xludf.DUMMYFUNCTION("""COMPUTED_VALUE"""),0.0) -> 0 | U82: =IFERROR(__xludf.DUMMYFUNCTION("""COMPUTED_VALUE"""),"E/F platform to mezzanine for 6 service and 53 St & Lexington Av exit.") -> E/F platform to mezzanine for 6 service and 53 St & Lexington Av exit. | V82: =IFERROR(__xludf.DUMMYFUNCTION("""COMPUTED_VALUE"""),"POINT (-73.96957 40.75777)") -> POINT (-73.96957 40.75777)
A83: =IFERROR(__xludf.DUMMYFUNCTION("""COMPUTED_VALUE"""),"Delancey St-Essex St") -> Delancey St-Essex St | B83: =IFERROR(__xludf.DUMMYFUNCTION("""COMPUTED_VALUE"""),"") | C83: =IFERROR(__xludf.DUMMYFUNCTION("""COMPUTED_VALUE"""),"") | D83: =IFERROR(__xludf.DUMMYFUNCTION("""COMPUTED_VALUE"""),"") | E83: =IFERROR(__xludf.DUMMYFUNCTION("""COMPUTED_VALUE"""),"") | F83: =IFERROR(__xludf.DUMMYFUNCTION("""COMPUTED_VALUE"""),"") | G83: =IFERROR(__xludf.DUMMYFUNCTION("""COMPUTED_VALUE"""),"") | H83: =IFERROR(__xludf.DUMMYFUNCTION("""COMPUTED_VALUE"""),"↗️") -> ↗️ | I83: =IFERROR(__xludf.DUMMYFUNCTION("""COMPUTED_VALUE"""),21337.0) -> 21337 | J83: =IFERROR(__xludf.DUMMYFUNCTION("""COMPUTED_VALUE"""),36286.0) -> 36286 | K83: =IFERROR(__xludf.DUMMYFUNCTION("""COMPUTED_VALUE"""),22.0) -> 22 | L83: =IFERROR(__xludf.DUMMYFUNCTION("""COMPUTED_VALUE"""),"YES") -> YES | M83: =IFERROR(__xludf.DUMMYFUNCTION("""COMPUTED_VALUE"""),"NYCT") -> NYCT | N83: =IFERROR(__xludf.DUMMYFUNCTION("""COMPUTED_VALUE"""),"OK") -> OK | O83: =IFERROR(__xludf.DUMMYFUNCTION("""COMPUTED_VALUE"""),"YES") -> YES | P83: =IFERROR(__xludf.DUMMYFUNCTION("""COMPUTED_VALUE"""),"YES") -> YES | Q83: =IFERROR(__xludf.DUMMYFUNCTION("""COMPUTED_VALUE"""),"YES") -> YES | R83: =IFERROR(__xludf.DUMMYFUNCTION("""COMPUTED_VALUE"""),"27'") -> 27' | S83: =IFERROR(__xludf.DUMMYFUNCTION("""COMPUTED_VALUE"""),97.0) -> 97 | T83: =IFERROR(__xludf.DUMMYFUNCTION("""COMPUTED_VALUE"""),24.0) -> 24 | U83: =IFERROR(__xludf.DUMMYFUNCTION("""COMPUTED_VALUE"""),"mezzanine to Delancey St & Essex St (NE corner)") -> mezzanine to Delancey St & Essex St (NE corner) | V83: =IFERROR(__xludf.DUMMYFUNCTION("""COMPUTED_VALUE"""),"POINT (-73.987564 40.718815)") -> POINT (-73.987564 40.718815)
A84: =IFERROR(__xludf.DUMMYFUNCTION("""COMPUTED_VALUE"""),"74 St-Broadway") -> 74 St-Broadway | B84: =IFERROR(__xludf.DUMMYFUNCTION("""COMPUTED_VALUE"""),"") | C84: =IFERROR(__xludf.DUMMYFUNCTION("""COMPUTED_VALUE"""),"") | D84: =IFERROR(__xludf.DUMMYFUNCTION("""COMPUTED_VALUE"""),"") | E84: =IFERROR(__xludf.DUMMYFUNCTION("""COMPUTED_VALUE"""),"") | F84: =IFERROR(__xludf.DUMMYFUNCTION("""COMPUTED_VALUE"""),"") | G84: =IFERROR(__xludf.DUMMYFUNCTION("""COMPUTED_VALUE"""),"") | H84: =IFERROR(__xludf.DUMMYFUNCTION("""COMPUTED_VALUE"""),"↗️") -> ↗️ | I84: =IFERROR(__xludf.DUMMYFUNCTION("""COMPUTED_VALUE"""),21641.0) -> 21641 | J84: =IFERROR(__xludf.DUMMYFUNCTION("""COMPUTED_VALUE"""),45596.0) -> 45596 | K84: =IFERROR(__xludf.DUMMYFUNCTION("""COMPUTED_VALUE"""),22.0) -> 22 | L84: =IFERROR(__xludf.DUMMYFUNCTION("""COMPUTED_VALUE"""),"YES") -> YES | M84: =IFERROR(__xludf.DUMMYFUNCTION("""COMPUTED_VALUE"""),"NYCT") -> NYCT | N84: =IFERROR(__xludf.DUMMYFUNCTION("""COMPUTED_VALUE"""),"OK") -> OK | O84: =IFERROR(__xludf.DUMMYFUNCTION("""COMPUTED_VALUE"""),"YES") -> YES | P84: =IFERROR(__xludf.DUMMYFUNCTION("""COMPUTED_VALUE"""),"NO") -> NO | Q84: =IFERROR(__xludf.DUMMYFUNCTION("""COMPUTED_VALUE"""),"NO") -> NO | R84: =IFERROR(__xludf.DUMMYFUNCTION("""COMPUTED_VALUE"""),"31'") -> 31' | S84: =IFERROR(__xludf.DUMMYFUNCTION("""COMPUTED_VALUE"""),115.0) -> 115 | T84: =IFERROR(__xludf.DUMMYFUNCTION("""COMPUTED_VALUE"""),"40in") -> 40in | U84: =IFERROR(__xludf.DUMMYFUNCTION("""COMPUTED_VALUE"""),"E/F/M/R lower mezzanine to underpass for 7 service") -> E/F/M/R lower mezzanine to underpass for 7 service | V84: =IFERROR(__xludf.DUMMYFUNCTION("""COMPUTED_VALUE"""),"POINT (-73.89245 40.746876)") -> POINT (-73.89245 40.746876)
A85: =IFERROR(__xludf.DUMMYFUNCTION("""COMPUTED_VALUE"""),"Howard Beach-JFK Airport") -> Howard Beach-JFK Airport | B85: =IFERROR(__xludf.DUMMYFUNCTION("""COMPUTED_VALUE"""),"Rockaway Line") -> Rockaway Line | C85: =IFERROR(__xludf.DUMMYFUNCTION("""COMPUTED_VALUE"""),"Queens") -> Queens | D85: =IFERROR(__xludf.DUMMYFUNCTION("""COMPUTED_VALUE"""),"Howard Beach") -> Howard Beach | E85: =IFERROR(__xludf.DUMMYFUNCTION("""COMPUTED_VALUE"""),20634.0) -> 20634 | F85: =IFERROR(__xludf.DUMMYFUNCTION("""COMPUTED_VALUE"""),975786.0) -> 975786 | G85: =IFERROR(__xludf.DUMMYFUNCTION("""COMPUTED_VALUE"""),297.0) -> 297 | H85: =IFERROR(__xludf.DUMMYFUNCTION("""COMPUTED_VALUE"""),"↗️") -> ↗️ | J85: =IFERROR(__xludf.DUMMYFUNCTION("""COMPUTED_VALUE"""),41263.0) -> 41263 | K85: =IFERROR(__xludf.DUMMYFUNCTION("""COMPUTED_VALUE"""),22.0) -> 22 | L85: =IFERROR(__xludf.DUMMYFUNCTION("""COMPUTED_VALUE"""),"NO") -> NO | M85: =IFERROR(__xludf.DUMMYFUNCTION("""COMPUTED_VALUE"""),"Private Contractor") -> Private Contractor | N85: =IFERROR(__xludf.DUMMYFUNCTION("""COMPUTED_VALUE"""),"AM") -> AM | O85: =IFERROR(__xludf.DUMMYFUNCTION("""COMPUTED_VALUE"""),"YES") -> YES | P85: =IFERROR(__xludf.DUMMYFUNCTION("""COMPUTED_VALUE"""),"NO") -> NO | Q85: =IFERROR(__xludf.DUMMYFUNCTION("""COMPUTED_VALUE"""),"NO") -> NO | U85: =IFERROR(__xludf.DUMMYFUNCTION("""COMPUTED_VALUE"""),"intermediate mezzanine to Brooklyn-bound platform") -> intermediate mezzanine to Brooklyn-bound platform | V85: =IFERROR(__xludf.DUMMYFUNCTION("""COMPUTED_VALUE"""),"POINT (-73.83007 40.660423)") -> POINT (-73.83007 40.660423)
A86: =IFERROR(__xludf.DUMMYFUNCTION("""COMPUTED_VALUE"""),"Times Sq-42 St") -> Times Sq-42 St | B86: =IFERROR(__xludf.DUMMYFUNCTION("""COMPUTED_VALUE"""),"42nd St Line") -> 42nd St Line | C86: =IFERROR(__xludf.DUMMYFUNCTION("""COMPUTED_VALUE"""),"Manhattan") -> Manhattan | D86: =IFERROR(__xludf.DUMMYFUNCTION("""COMPUTED_VALUE"""),"Times Square") -> Times Square | E86: =IFERROR(__xludf.DUMMYFUNCTION("""COMPUTED_VALUE"""),1762.0) -> 1762 | F86: =IFERROR(__xludf.DUMMYFUNCTION("""COMPUTED_VALUE"""),5.7743486E7) -> 57743486 | G86: =IFERROR(__xludf.DUMMYFUNCTION("""COMPUTED_VALUE"""),1.0) -> 1 | H86: =IFERROR(__xludf.DUMMYFUNCTION("""COMPUTED_VALUE"""),"↗️") -> ↗️ | J86: =IFERROR(__xludf.DUMMYFUNCTION("""COMPUTED_VALUE"""),40722.0) -> 40722 | K86: =IFERROR(__xludf.DUMMYFUNCTION("""COMPUTED_VALUE"""),22.0) -> 22 | L86: =IFERROR(__xludf.DUMMYFUNCTION("""COMPUTED_VALUE"""),"NO") -> NO | M86: =IFERROR(__xludf.DUMMYFUNCTION("""COMPUTED_VALUE"""),"Private Contractor") -> Private Contractor | N86: =IFERROR(__xludf.DUMMYFUNCTION("""COMPUTED_VALUE"""),"AM") -> AM | O86: =IFERROR(__xludf.DUMMYFUNCTION("""COMPUTED_VALUE"""),"YES") -> YES | P86: =IFERROR(__xludf.DUMMYFUNCTION("""COMPUTED_VALUE"""),"NO") -> NO | Q86: =IFERROR(__xludf.DUMMYFUNCTION("""COMPUTED_VALUE"""),"NO") -> NO | S86: =IFERROR(__xludf.DUMMYFUNCTION("""COMPUTED_VALUE"""),0.0) -> 0 | U86: =IFERROR(__xludf.DUMMYFUNCTION("""COMPUTED_VALUE"""),"N/Q/R/W mezzanine to 42 St & 7th Ave (SE corner)") -> N/Q/R/W mezzanine to 42 St & 7th Ave (SE corner) | V86: =IFERROR(__xludf.DUMMYFUNCTION("""COMPUTED_VALUE"""),"POINT (-73.98679 40.755707)") -> POINT (-73.98679 40.755707)
A87: =IFERROR(__xludf.DUMMYFUNCTION("""COMPUTED_VALUE"""),"Bowling Green") -> Bowling Green | B87: =IFERROR(__xludf.DUMMYFUNCTION("""COMPUTED_VALUE"""),"Lexington Av Line") -> Lexington Av Line | C87: =IFERROR(__xludf.DUMMYFUNCTION("""COMPUTED_VALUE"""),"Manhattan") -> Manhattan | D87: =IFERROR(__xludf.DUMMYFUNCTION("""COMPUTED_VALUE"""),"Financial District") -> Financial District | E87: =IFERROR(__xludf.DUMMYFUNCTION("""COMPUTED_VALUE"""),2018.0) -> 2018 | F87: =IFERROR(__xludf.DUMMYFUNCTION("""COMPUTED_VALUE"""),4676646.0) -> 4676646 | G87: =IFERROR(__xludf.DUMMYFUNCTION("""COMPUTED_VALUE"""),62.0) -> 62 | H87: =IFERROR(__xludf.DUMMYFUNCTION("""COMPUTED_VALUE"""),"↗️") -> ↗️ | I87: =IFERROR(__xludf.DUMMYFUNCTION("""COMPUTED_VALUE"""),28216.0) -> 28216 | J87: =IFERROR(__xludf.DUMMYFUNCTION("""COMPUTED_VALUE"""),37757.0) -> 37757 | K87: =IFERROR(__xludf.DUMMYFUNCTION("""COMPUTED_VALUE"""),22.0) -> 22 | L87: =IFERROR(__xludf.DUMMYFUNCTION("""COMPUTED_VALUE"""),"YES") -> YES | M87: =IFERROR(__xludf.DUMMYFUNCTION("""COMPUTED_VALUE"""),"NYCT") -> NYCT | N87: =IFERROR(__xludf.DUMMYFUNCTION("""COMPUTED_VALUE"""),"FUJITEC") -> FUJITEC | O87: =IFERROR(__xludf.DUMMYFUNCTION("""COMPUTED_VALUE"""),"YES") -> YES | P87: =IFERROR(__xludf.DUMMYFUNCTION("""COMPUTED_VALUE"""),"NO") -> NO | Q87: =IFERROR(__xludf.DUMMYFUNCTION("""COMPUTED_VALUE"""),"NO") -> NO | R87: =IFERROR(__xludf.DUMMYFUNCTION("""COMPUTED_VALUE"""),"24'") -> 24' | S87: =IFERROR(__xludf.DUMMYFUNCTION("""COMPUTED_VALUE"""),89.0) -> 89 | T87: =IFERROR(__xludf.DUMMYFUNCTION("""COMPUTED_VALUE"""),40.0) -> 40 | U87: =IFERROR(__xludf.DUMMYFUNCTION("""COMPUTED_VALUE"""),"lower mezzanine to downtown 4/5 platform") -> lower mezzanine to downtown 4/5 platform | V87: =IFERROR(__xludf.DUMMYFUNCTION("""COMPUTED_VALUE"""),"POINT (-74.014305 40.704437)") -> POINT (-74.014305 40.704437)
A88: =IFERROR(__xludf.DUMMYFUNCTION("""COMPUTED_VALUE"""),"34 St-Herald Sq") -> 34 St-Herald Sq | B88: =IFERROR(__xludf.DUMMYFUNCTION("""COMPUTED_VALUE"""),"Broadway Line") -> Broadway Line | C88: =IFERROR(__xludf.DUMMYFUNCTION("""COMPUTED_VALUE"""),"Manhattan") -> Manhattan | D88: =IFERROR(__xludf.DUMMYFUNCTION("""COMPUTED_VALUE"""),"Midtown") -> Midtown | E88: =IFERROR(__xludf.DUMMYFUNCTION("""COMPUTED_VALUE"""),6580.0) -> 6580 | F88: =IFERROR(__xludf.DUMMYFUNCTION("""COMPUTED_VALUE"""),2.5012549E7) -> 25012549 | G88: =IFERROR(__xludf.DUMMYFUNCTION("""COMPUTED_VALUE"""),3.0) -> 3 | H88: =IFERROR(__xludf.DUMMYFUNCTION("""COMPUTED_VALUE"""),"↗️") -> ↗️ | I88: =IFERROR(__xludf.DUMMYFUNCTION("""COMPUTED_VALUE"""),14960.0) -> 14960 | J88: =IFERROR(__xludf.DUMMYFUNCTION("""COMPUTED_VALUE"""),39460.0) -> 39460 | K88: =IFERROR(__xludf.DUMMYFUNCTION("""COMPUTED_VALUE"""),22.0) -> 22 | L88: =IFERROR(__xludf.DUMMYFUNCTION("""COMPUTED_VALUE"""),"YES") -> YES | M88: =IFERROR(__xludf.DUMMYFUNCTION("""COMPUTED_VALUE"""),"NYCT") -> NYCT | N88: =IFERROR(__xludf.DUMMYFUNCTION("""COMPUTED_VALUE"""),"FUJITEC") -> FUJITEC | O88: =IFERROR(__xludf.DUMMYFUNCTION("""COMPUTED_VALUE"""),"YES") -> YES | P88: =IFERROR(__xludf.DUMMYFUNCTION("""COMPUTED_VALUE"""),"NO") -> NO | Q88: =IFERROR(__xludf.DUMMYFUNCTION("""COMPUTED_VALUE"""),"NO") -> NO | R88: =IFERROR(__xludf.DUMMYFUNCTION("""COMPUTED_VALUE"""),"29'") -> 29' | S88: =IFERROR(__xludf.DUMMYFUNCTION("""COMPUTED_VALUE"""),110.0) -> 110 | T88: =IFERROR(__xludf.DUMMYFUNCTION("""COMPUTED_VALUE"""),24.0) -> 24 | U88: =IFERROR(__xludf.DUMMYFUNCTION("""COMPUTED_VALUE"""),"uptown B/D/F/M platform to mezzanine for N/Q/R/W service") -> uptown B/D/F/M platform to mezzanine for N/Q/R/W service | V88: =IFERROR(__xludf.DUMMYFUNCTION("""COMPUTED_VALUE"""),"POINT (-73.98753 40.75)") -> POINT (-73.98753 40.75)
A89: =IFERROR(__xludf.DUMMYFUNCTION("""COMPUTED_VALUE"""),"Roosevelt Island") -> Roosevelt Island | B89: =IFERROR(__xludf.DUMMYFUNCTION("""COMPUTED_VALUE"""),"63rd St Line") -> 63rd St Line | C89: =IFERROR(__xludf.DUMMYFUNCTION("""COMPUTED_VALUE"""),"Manhattan") -> Manhattan | D89: =IFERROR(__xludf.DUMMYFUNCTION("""COMPUTED_VALUE"""),"Roosevelt Island") -> Roosevelt Island | E89: =IFERROR(__xludf.DUMMYFUNCTION("""COMPUTED_VALUE"""),32810.0) -> 32810 | F89: =IFERROR(__xludf.DUMMYFUNCTION("""COMPUTED_VALUE"""),1885823.0) -> 1885823 | G89: =IFERROR(__xludf.DUMMYFUNCTION("""COMPUTED_VALUE"""),171.0) -> 171 | H89: =IFERROR(__xludf.DUMMYFUNCTION("""COMPUTED_VALUE"""),"↗️") -> ↗️ | I89: =IFERROR(__xludf.DUMMYFUNCTION("""COMPUTED_VALUE"""),32782.0) -> 32782 | J89: =IFERROR(__xludf.DUMMYFUNCTION("""COMPUTED_VALUE"""),39647.0) -> 39647 | K89: =IFERROR(__xludf.DUMMYFUNCTION("""COMPUTED_VALUE"""),22.0) -> 22 | L89: =IFERROR(__xludf.DUMMYFUNCTION("""COMPUTED_VALUE"""),"YES") -> YES | M89: =IFERROR(__xludf.DUMMYFUNCTION("""COMPUTED_VALUE"""),"NYCT") -> NYCT | N89: =IFERROR(__xludf.DUMMYFUNCTION("""COMPUTED_VALUE"""),"OK") -> OK | O89: =IFERROR(__xludf.DUMMYFUNCTION("""COMPUTED_VALUE"""),"YES") -> YES | P89: =IFERROR(__xludf.DUMMYFUNCTION("""COMPUTED_VALUE"""),"NO") -> NO | Q89: =IFERROR(__xludf.DUMMYFUNCTION("""COMPUTED_VALUE"""),"NO") -> NO | R89: =IFERROR(__xludf.DUMMYFUNCTION("""COMPUTED_VALUE"""),"14'") -> 14' | S89: =IFERROR(__xludf.DUMMYFUNCTION("""COMPUTED_VALUE"""),56.0) -> 56 | T89: =IFERROR(__xludf.DUMMYFUNCTION("""COMPUTED_VALUE"""),40.0) -> 40 | U89: =IFERROR(__xludf.DUMMYFUNCTION("""COMPUTED_VALUE"""),"Jamaica 179 St-bound platform to lower mezzanine") -> Jamaica 179 St-bound platform to lower mezzanine | V89: =IFERROR(__xludf.DUMMYFUNCTION("""COMPUTED_VALUE"""),"POINT (-73.95275 40.75882)") -> POINT (-73.95275 40.75882)
A90: =IFERROR(__xludf.DUMMYFUNCTION("""COMPUTED_VALUE"""),"96 St") -> 96 St | B90: =IFERROR(__xludf.DUMMYFUNCTION("""COMPUTED_VALUE"""),"Broadway-7 Av Line") -> Broadway-7 Av Line | C90: =IFERROR(__xludf.DUMMYFUNCTION("""COMPUTED_VALUE"""),"Manhattan") -> Manhattan | D90: =IFERROR(__xludf.DUMMYFUNCTION("""COMPUTED_VALUE"""),"Upper West Side") -> Upper West Side | E90: =IFERROR(__xludf.DUMMYFUNCTION("""COMPUTED_VALUE"""),1762.0) -> 1762 | F90: =IFERROR(__xludf.DUMMYFUNCTION("""COMPUTED_VALUE"""),8250940.0) -> 8250940 | G90: =IFERROR(__xludf.DUMMYFUNCTION("""COMPUTED_VALUE"""),26.0) -> 26 | H90: =IFERROR(__xludf.DUMMYFUNCTION("""COMPUTED_VALUE"""),"↗️") -> ↗️ | I90: =IFERROR(__xludf.DUMMYFUNCTION("""COMPUTED_VALUE"""),42736.0) -> 42736 | J90: =IFERROR(__xludf.DUMMYFUNCTION("""COMPUTED_VALUE"""),42736.0) -> 42736 | K90: =IFERROR(__xludf.DUMMYFUNCTION("""COMPUTED_VALUE"""),22.0) -> 22 | L90: =IFERROR(__xludf.DUMMYFUNCTION("""COMPUTED_VALUE"""),"YES") -> YES | M90: =IFERROR(__xludf.DUMMYFUNCTION("""COMPUTED_VALUE"""),"NYCT") -> NYCT | N90: =IFERROR(__xludf.DUMMYFUNCTION("""COMPUTED_VALUE"""),"KONE") -> KONE | O90: =IFERROR(__xludf.DUMMYFUNCTION("""COMPUTED_VALUE"""),"YES") -> YES | P90: =IFERROR(__xludf.DUMMYFUNCTION("""COMPUTED_VALUE"""),"YES") -> YES | Q90: =IFERROR(__xludf.DUMMYFUNCTION("""COMPUTED_VALUE"""),"YES") -> YES | R90: =IFERROR(__xludf.DUMMYFUNCTION("""COMPUTED_VALUE"""),"9687mm (31' 9 3/8in)") -> 9687mm (31' 9 3/8in) | S90: =IFERROR(__xludf.DUMMYFUNCTION("""COMPUTED_VALUE"""),122.0) -> 122 | T90: =IFERROR(__xludf.DUMMYFUNCTION("""COMPUTED_VALUE"""),"1000 mm (39 3/8in)") -> 1000 mm (39 3/8in) | U90: =IFERROR(__xludf.DUMMYFUNCTION("""COMPUTED_VALUE"""),"mezzanine to 94 St & 2nd Ave (SW corner)") -> mezzanine to 94 St & 2nd Ave (SW corner) | V90: =IFERROR(__xludf.DUMMYFUNCTION("""COMPUTED_VALUE"""),"POINT (-73.94715 40.78431)") -> POINT (-73.94715 40.78431)
A91: =IFERROR(__xludf.DUMMYFUNCTION("""COMPUTED_VALUE"""),"Roosevelt Island") -> Roosevelt Island | B91: =IFERROR(__xludf.DUMMYFUNCTION("""COMPUTED_VALUE"""),"63rd St Line") -> 63rd St Line | C91: =IFERROR(__xludf.DUMMYFUNCTION("""COMPUTED_VALUE"""),"Manhattan") -> Manhattan | D91: =IFERROR(__xludf.DUMMYFUNCTION("""COMPUTED_VALUE"""),"Roosevelt Island") -> Roosevelt Island | E91: =IFERROR(__xludf.DUMMYFUNCTION("""COMPUTED_VALUE"""),32810.0) -> 32810 | F91: =IFERROR(__xludf.DUMMYFUNCTION("""COMPUTED_VALUE"""),1885823.0) -> 1885823 | G91: =IFERROR(__xludf.DUMMYFUNCTION("""COMPUTED_VALUE"""),171.0) -> 171 | H91: =IFERROR(__xludf.DUMMYFUNCTION("""COMPUTED_VALUE"""),"↗️") -> ↗️ | I91: =IFERROR(__xludf.DUMMYFUNCTION("""COMPUTED_VALUE"""),32782.0) -> 32782 | J91: =IFERROR(__xludf.DUMMYFUNCTION("""COMPUTED_VALUE"""),39405.0) -> 39405 | K91: =IFERROR(__xludf.DUMMYFUNCTION("""COMPUTED_VALUE"""),22.0) -> 22 | L91: =IFERROR(__xludf.DUMMYFUNCTION("""COMPUTED_VALUE"""),"YES") -> YES | M91: =IFERROR(__xludf.DUMMYFUNCTION("""COMPUTED_VALUE"""),"NYCT") -> NYCT | N91: =IFERROR(__xludf.DUMMYFUNCTION("""COMPUTED_VALUE"""),"KONE") -> KONE | O91: =IFERROR(__xludf.DUMMYFUNCTION("""COMPUTED_VALUE"""),"YES") -> YES | P91: =IFERROR(__xludf.DUMMYFUNCTION("""COMPUTED_VALUE"""),"YES") -> YES | Q91: =IFERROR(__xludf.DUMMYFUNCTION("""COMPUTED_VALUE"""),"NO") -> NO | R91: =IFERROR(__xludf.DUMMYFUNCTION("""COMPUTED_VALUE"""),"38'") -> 38' | S91: =IFERROR(__xludf.DUMMYFUNCTION("""COMPUTED_VALUE"""),136.0) -> 136 | T91: =IFERROR(__xludf.DUMMYFUNCTION("""COMPUTED_VALUE"""),40.0) -> 40 | U91: =IFERROR(__xludf.DUMMYFUNCTION("""COMPUTED_VALUE"""),"W Rd entrance to intermediate mezzanine") -> W Rd entrance to intermediate mezzanine | V91: =IFERROR(__xludf.DUMMYFUNCTION("""COMPUTED_VALUE"""),"POINT (-73.95321 40.75905)") -> POINT (-73.95321 40.75905)
A92: =IFERROR(__xludf.DUMMYFUNCTION("""COMPUTED_VALUE"""),"96 St") -> 96 St | B92: =IFERROR(__xludf.DUMMYFUNCTION("""COMPUTED_VALUE"""),"Broadway-7 Av Line") -> Broadway-7 Av Line | C92: =IFERROR(__xludf.DUMMYFUNCTION("""COMPUTED_VALUE"""),"Manhattan") -> Manhattan | D92: =IFERROR(__xludf.DUMMYFUNCTION("""COMPUTED_VALUE"""),"Upper West Side") -> Upper West Side | E92: =IFERROR(__xludf.DUMMYFUNCTION("""COMPUTED_VALUE"""),1762.0) -> 1762 | F92: =IFERROR(__xludf.DUMMYFUNCTION("""COMPUTED_VALUE"""),8250940.0) -> 8250940 | G92: =IFERROR(__xludf.DUMMYFUNCTION("""COMPUTED_VALUE"""),26.0) -> 26 | H92: =IFERROR(__xludf.DUMMYFUNCTION("""COMPUTED_VALUE"""),"↗️") -> ↗️ | I92: =IFERROR(__xludf.DUMMYFUNCTION("""COMPUTED_VALUE"""),42736.0) -> 42736 | J92: =IFERROR(__xludf.DUMMYFUNCTION("""COMPUTED_VALUE"""),42736.0) -> 42736 | K92: =IFERROR(__xludf.DUMMYFUNCTION("""COMPUTED_VALUE"""),22.0) -> 22 | L92: =IFERROR(__xludf.DUMMYFUNCTION("""COMPUTED_VALUE"""),"YES") -> YES | M92: =IFERROR(__xludf.DUMMYFUNCTION("""COMPUTED_VALUE"""),"NYCT") -> NYCT | N92: =IFERROR(__xludf.DUMMYFUNCTION("""COMPUTED_VALUE"""),"KONE") -> KONE | O92: =IFERROR(__xludf.DUMMYFUNCTION("""COMPUTED_VALUE"""),"YES") -> YES | P92: =IFERROR(__xludf.DUMMYFUNCTION("""COMPUTED_VALUE"""),"YES") -> YES | Q92: =IFERROR(__xludf.DUMMYFUNCTION("""COMPUTED_VALUE"""),"YES") -> YES | R92: =IFERROR(__xludf.DUMMYFUNCTION("""COMPUTED_VALUE"""),"8,519mm (27' 11 3/8in)") -> 8,519mm (27' 11 3/8in) | S92: =IFERROR(__xludf.DUMMYFUNCTION("""COMPUTED_VALUE"""),111.0) -> 111 | T92: =IFERROR(__xludf.DUMMYFUNCTION("""COMPUTED_VALUE"""),"1000 mm (39 3/8in)") -> 1000 mm (39 3/8in) | U92: =IFERROR(__xludf.DUMMYFUNCTION("""COMPUTED_VALUE"""),"94 St & 2nd Ave (NE corner) to mezzanine") -> 94 St & 2nd Ave (NE corner) to mezzanine | V92: =IFERROR(__xludf.DUMMYFUNCTION("""COMPUTED_VALUE"""),"POINT (-73.94781 40.782993)") -> POINT (-73.94781 40.782993)
A93: =IFERROR(__xludf.DUMMYFUNCTION("""COMPUTED_VALUE"""),"Lexington Av/63 St") -> Lexington Av/63 St | B93: =IFERROR(__xludf.DUMMYFUNCTION("""COMPUTED_VALUE"""),"") | C93: =IFERROR(__xludf.DUMMYFUNCTION("""COMPUTED_VALUE"""),"") | D93: =IFERROR(__xludf.DUMMYFUNCTION("""COMPUTED_VALUE"""),"") | E93: =IFERROR(__xludf.DUMMYFUNCTION("""COMPUTED_VALUE"""),"") | F93: =IFERROR(__xludf.DUMMYFUNCTION("""COMPUTED_VALUE"""),"") | G93: =IFERROR(__xludf.DUMMYFUNCTION("""COMPUTED_VALUE"""),"") | H93: =IFERROR(__xludf.DUMMYFUNCTION("""COMPUTED_VALUE"""),"↗️") -> ↗️ | I93: =IFERROR(__xludf.DUMMYFUNCTION("""COMPUTED_VALUE"""),42734.0) -> 42734 | J93: =IFERROR(__xludf.DUMMYFUNCTION("""COMPUTED_VALUE"""),42734.0) -> 42734 | K93: =IFERROR(__xludf.DUMMYFUNCTION("""COMPUTED_VALUE"""),22.0) -> 22 | L93: =IFERROR(__xludf.DUMMYFUNCTION("""COMPUTED_VALUE"""),"YES") -> YES | M93: =IFERROR(__xludf.DUMMYFUNCTION("""COMPUTED_VALUE"""),"NYCT") -> NYCT | N93: =IFERROR(__xludf.DUMMYFUNCTION("""COMPUTED_VALUE"""),"KONE") -> KONE | O93: =IFERROR(__xludf.DUMMYFUNCTION("""COMPUTED_VALUE"""),"YES") -> YES | P93: =IFERROR(__xludf.DUMMYFUNCTION("""COMPUTED_VALUE"""),"YES") -> YES | Q93: =IFERROR(__xludf.DUMMYFUNCTION("""COMPUTED_VALUE"""),"YES") -> YES | R93: =IFERROR(__xludf.DUMMYFUNCTION("""COMPUTED_VALUE"""),"9611mm (31' 6 3/8in)") -> 9611mm (31' 6 3/8in) | S93: =IFERROR(__xludf.DUMMYFUNCTION("""COMPUTED_VALUE"""),122.0) -> 122 | T93: =IFERROR(__xludf.DUMMYFUNCTION("""COMPUTED_VALUE"""),"Step Width 996 mm (39 3/8in)") -> Step Width 996 mm (39 3/8in) | U93: =IFERROR(__xludf.DUMMYFUNCTION("""COMPUTED_VALUE"""),"mezzanine to 3rd Ave & 63 St (SE corner)") -> mezzanine to 3rd Ave & 63 St (SE corner) | V93: =IFERROR(__xludf.DUMMYFUNCTION("""COMPUTED_VALUE"""),"POINT (-73.964615 40.763866)") -> POINT (-73.964615 40.763866)
A94: =IFERROR(__xludf.DUMMYFUNCTION("""COMPUTED_VALUE"""),"72 St") -> 72 St | B94: =IFERROR(__xludf.DUMMYFUNCTION("""COMPUTED_VALUE"""),"Broadway-7 Av Line") -> Broadway-7 Av Line | C94: =IFERROR(__xludf.DUMMYFUNCTION("""COMPUTED_VALUE"""),"Manhattan") -> Manhattan | D94: =IFERROR(__xludf.DUMMYFUNCTION("""COMPUTED_VALUE"""),"Upper West Side") -> Upper West Side | E94: =IFERROR(__xludf.DUMMYFUNCTION("""COMPUTED_VALUE"""),1762.0) -> 1762 | F94: =IFERROR(__xludf.DUMMYFUNCTION("""COMPUTED_VALUE"""),9752193.0) -> 9752193 | G94: =IFERROR(__xludf.DUMMYFUNCTION("""COMPUTED_VALUE"""),22.0) -> 22 | H94: =IFERROR(__xludf.DUMMYFUNCTION("""COMPUTED_VALUE"""),"↗️") -> ↗️ | I94: =IFERROR(__xludf.DUMMYFUNCTION("""COMPUTED_VALUE"""),42736.0) -> 42736 | J94: =IFERROR(__xludf.DUMMYFUNCTION("""COMPUTED_VALUE"""),42736.0) -> 42736 | K94: =IFERROR(__xludf.DUMMYFUNCTION("""COMPUTED_VALUE"""),22.0) -> 22 | L94: =IFERROR(__xludf.DUMMYFUNCTION("""COMPUTED_VALUE"""),"YES") -> YES | M94: =IFERROR(__xludf.DUMMYFUNCTION("""COMPUTED_VALUE"""),"NYCT") -> NYCT | N94: =IFERROR(__xludf.DUMMYFUNCTION("""COMPUTED_VALUE"""),"SCHINDLER") -> SCHINDLER | O94: =IFERROR(__xludf.DUMMYFUNCTION("""COMPUTED_VALUE"""),"YES") -> YES | P94: =IFERROR(__xludf.DUMMYFUNCTION("""COMPUTED_VALUE"""),"NO") -> NO | Q94: =IFERROR(__xludf.DUMMYFUNCTION("""COMPUTED_VALUE"""),"NO") -> NO | R94: =IFERROR(__xludf.DUMMYFUNCTION("""COMPUTED_VALUE"""),"20828 mm (68'4in)") -> 20828 mm (68'4in) | S94: =IFERROR(__xludf.DUMMYFUNCTION("""COMPUTED_VALUE"""),0.0) -> 0 | U94: =IFERROR(__xludf.DUMMYFUNCTION("""COMPUTED_VALUE"""),"lower mezzanine to upper mezzanine for 69 St & 2nd Ave exit") -> lower mezzanine to upper mezzanine for 69 St & 2nd Ave exit | V94: =IFERROR(__xludf.DUMMYFUNCTION("""COMPUTED_VALUE"""),"POINT (-73.95919 40.767212)") -> POINT (-73.95919 40.767212)
A95: =IFERROR(__xludf.DUMMYFUNCTION("""COMPUTED_VALUE"""),"West 8 St-NY Aquarium") -> West 8 St-NY Aquarium | B95: =IFERROR(__xludf.DUMMYFUNCTION("""COMPUTED_VALUE"""),"") | C95: =IFERROR(__xludf.DUMMYFUNCTION("""COMPUTED_VALUE"""),"") | D95: =IFERROR(__xludf.DUMMYFUNCTION("""COMPUTED_VALUE"""),"") | E95: =IFERROR(__xludf.DUMMYFUNCTION("""COMPUTED_VALUE"""),"") | F95: =IFERROR(__xludf.DUMMYFUNCTION("""COMPUTED_VALUE"""),"") | G95: =IFERROR(__xludf.DUMMYFUNCTION("""COMPUTED_VALUE"""),"") | H95: =IFERROR(__xludf.DUMMYFUNCTION("""COMPUTED_VALUE"""),"↗️") -> ↗️ | I95: =IFERROR(__xludf.DUMMYFUNCTION("""COMPUTED_VALUE"""),26481.0) -> 26481 | J95: =IFERROR(__xludf.DUMMYFUNCTION("""COMPUTED_VALUE"""),37900.0) -> 37900 | K95: =IFERROR(__xludf.DUMMYFUNCTION("""COMPUTED_VALUE"""),22.0) -> 22 | L95: =IFERROR(__xludf.DUMMYFUNCTION("""COMPUTED_VALUE"""),"YES") -> YES | M95: =IFERROR(__xludf.DUMMYFUNCTION("""COMPUTED_VALUE"""),"NYCT") -> NYCT | N95: =IFERROR(__xludf.DUMMYFUNCTION("""COMPUTED_VALUE"""),"FUJITEC") -> FUJITEC | O95: =IFERROR(__xludf.DUMMYFUNCTION("""COMPUTED_VALUE"""),"YES") -> YES | P95: =IFERROR(__xludf.DUMMYFUNCTION("""COMPUTED_VALUE"""),"NO") -> NO | Q95: =IFERROR(__xludf.DUMMYFUNCTION("""COMPUTED_VALUE"""),"YES") -> YES | R95: =IFERROR(__xludf.DUMMYFUNCTION("""COMPUTED_VALUE"""),"37'") -> 37' | S95: =IFERROR(__xludf.DUMMYFUNCTION("""COMPUTED_VALUE"""),128.0) -> 128 | T95: =IFERROR(__xludf.DUMMYFUNCTION("""COMPUTED_VALUE"""),40.0) -> 40 | U95: =IFERROR(__xludf.DUMMYFUNCTION("""COMPUTED_VALUE"""),"mezzanine (W 5 St & Brighton Ave) to Manhattan-bound Q platform") -> mezzanine (W 5 St & Brighton Ave) to Manhattan-bound Q platform | V95: =IFERROR(__xludf.DUMMYFUNCTION("""COMPUTED_VALUE"""),"POINT (-73.97512 40.5763)") -> POINT (-73.97512 40.5763)
A96: =IFERROR(__xludf.DUMMYFUNCTION("""COMPUTED_VALUE"""),"DeKalb Av") -> DeKalb Av | B96: =IFERROR(__xludf.DUMMYFUNCTION("""COMPUTED_VALUE"""),"Canarsie Line") -> Canarsie Line | C96: =IFERROR(__xludf.DUMMYFUNCTION("""COMPUTED_VALUE"""),"Brooklyn") -> Brooklyn | D96: =IFERROR(__xludf.DUMMYFUNCTION("""COMPUTED_VALUE"""),"Bushwick") -> Bushwick | E96: =IFERROR(__xludf.DUMMYFUNCTION("""COMPUTED_VALUE"""),10423.0) -> 10423 | F96: =IFERROR(__xludf.DUMMYFUNCTION("""COMPUTED_VALUE"""),2931695.0) -> 2931695 | G96: =IFERROR(__xludf.DUMMYFUNCTION("""COMPUTED_VALUE"""),113.0) -> 113 | H96: =IFERROR(__xludf.DUMMYFUNCTION("""COMPUTED_VALUE"""),"↗️") -> ↗️ | I96: =IFERROR(__xludf.DUMMYFUNCTION("""COMPUTED_VALUE"""),22373.0) -> 22373 | J96: =IFERROR(__xludf.DUMMYFUNCTION("""COMPUTED_VALUE"""),45198.0) -> 45198 | K96: =IFERROR(__xludf.DUMMYFUNCTION("""COMPUTED_VALUE"""),22.0) -> 22 | L96: =IFERROR(__xludf.DUMMYFUNCTION("""COMPUTED_VALUE"""),"YES") -> YES | M96: =IFERROR(__xludf.DUMMYFUNCTION("""COMPUTED_VALUE"""),"NYCT") -> NYCT | N96: =IFERROR(__xludf.DUMMYFUNCTION("""COMPUTED_VALUE"""),"KONE") -> KONE | O96: =IFERROR(__xludf.DUMMYFUNCTION("""COMPUTED_VALUE"""),"YES") -> YES | P96: =IFERROR(__xludf.DUMMYFUNCTION("""COMPUTED_VALUE"""),"NO") -> NO | Q96: =IFERROR(__xludf.DUMMYFUNCTION("""COMPUTED_VALUE"""),"NO") -> NO | R96: =IFERROR(__xludf.DUMMYFUNCTION("""COMPUTED_VALUE"""),"6306mm (20' 8-1/4in)") -> 6306mm (20' 8-1/4in) | S96: =IFERROR(__xludf.DUMMYFUNCTION("""COMPUTED_VALUE"""),82.0) -> 82 | T96: =IFERROR(__xludf.DUMMYFUNCTION("""COMPUTED_VALUE"""),"1000mm (40in NOMINAL)") -> 1000mm (40in NOMINAL) | U96: =IFERROR(__xludf.DUMMYFUNCTION("""COMPUTED_VALUE"""),"Brooklyn-bound platform to mezzanine for Flatbush Ave & Lafayette St exit") -> Brooklyn-bound platform to mezzanine for Flatbush Ave & Lafayette St exit | V96: =IFERROR(__xludf.DUMMYFUNCTION("""COMPUTED_VALUE"""),"POINT (-73.9823 40.691307)") -> POINT (-73.9823 40.691307)
A97: =IFERROR(__xludf.DUMMYFUNCTION("""COMPUTED_VALUE"""),"72 St") -> 72 St | B97: =IFERROR(__xludf.DUMMYFUNCTION("""COMPUTED_VALUE"""),"Broadway-7 Av Line") -> Broadway-7 Av Line | C97: =IFERROR(__xludf.DUMMYFUNCTION("""COMPUTED_VALUE"""),"Manhattan") -> Manhattan | D97: =IFERROR(__xludf.DUMMYFUNCTION("""COMPUTED_VALUE"""),"Upper West Side") -> Upper West Side | E97: =IFERROR(__xludf.DUMMYFUNCTION("""COMPUTED_VALUE"""),1762.0) -> 1762 | F97: =IFERROR(__xludf.DUMMYFUNCTION("""COMPUTED_VALUE"""),9752193.0) -> 9752193 | G97: =IFERROR(__xludf.DUMMYFUNCTION("""COMPUTED_VALUE"""),22.0) -> 22 | H97: =IFERROR(__xludf.DUMMYFUNCTION("""COMPUTED_VALUE"""),"↗️") -> ↗️ | I97: =IFERROR(__xludf.DUMMYFUNCTION("""COMPUTED_VALUE"""),42736.0) -> 42736 | J97: =IFERROR(__xludf.DUMMYFUNCTION("""COMPUTED_VALUE"""),42736.0) -> 42736 | K97: =IFERROR(__xludf.DUMMYFUNCTION("""COMPUTED_VALUE"""),22.0) -> 22 | L97: =IFERROR(__xludf.DUMMYFUNCTION("""COMPUTED_VALUE"""),"YES") -> YES | M97: =IFERROR(__xludf.DUMMYFUNCTION("""COMPUTED_VALUE"""),"NYCT") -> NYCT | N97: =IFERROR(__xludf.DUMMYFUNCTION("""COMPUTED_VALUE"""),"SCHINDLER") -> SCHINDLER | O97: =IFERROR(__xludf.DUMMYFUNCTION("""COMPUTED_VALUE"""),"YES") -> YES | P97: =IFERROR(__xludf.DUMMYFUNCTION("""COMPUTED_VALUE"""),"YES") -> YES | Q97: =IFERROR(__xludf.DUMMYFUNCTION("""COMPUTED_VALUE"""),"YES") -> YES | R97: =IFERROR(__xludf.DUMMYFUNCTION("""COMPUTED_VALUE"""),"21577 mm (70' 9 1/2in)") -> 21577 mm (70' 9 1/2in) | S97: =IFERROR(__xludf.DUMMYFUNCTION("""COMPUTED_VALUE"""),0.0) -> 0 | U97: =IFERROR(__xludf.DUMMYFUNCTION("""COMPUTED_VALUE"""),"lower mezzanine to 72 St & 2nd Ave (NW corner)") -> lower mezzanine to 72 St & 2nd Ave (NW corner) | V97: =IFERROR(__xludf.DUMMYFUNCTION("""COMPUTED_VALUE"""),"POINT (-73.95848 40.769054)") -> POINT (-73.95848 40.769054)
A98: =IFERROR(__xludf.DUMMYFUNCTION("""COMPUTED_VALUE"""),"Fulton St") -> Fulton St | B98: =IFERROR(__xludf.DUMMYFUNCTION("""COMPUTED_VALUE"""),"Broadway-7 Av Line") -> Broadway-7 Av Line | C98: =IFERROR(__xludf.DUMMYFUNCTION("""COMPUTED_VALUE"""),"Manhattan") -> Manhattan | D98: =IFERROR(__xludf.DUMMYFUNCTION("""COMPUTED_VALUE"""),"Financial District") -> Financial District | E98: =IFERROR(__xludf.DUMMYFUNCTION("""COMPUTED_VALUE"""),6757.0) -> 6757 | F98: =IFERROR(__xludf.DUMMYFUNCTION("""COMPUTED_VALUE"""),1.9221396E7) -> 19221396 | G98: =IFERROR(__xludf.DUMMYFUNCTION("""COMPUTED_VALUE"""),5.0) -> 5 | H98: =IFERROR(__xludf.DUMMYFUNCTION("""COMPUTED_VALUE"""),"↗️") -> ↗️ | J98: =IFERROR(__xludf.DUMMYFUNCTION("""COMPUTED_VALUE"""),41953.0) -> 41953 | K98: =IFERROR(__xludf.DUMMYFUNCTION("""COMPUTED_VALUE"""),22.0) -> 22 | L98: =IFERROR(__xludf.DUMMYFUNCTION("""COMPUTED_VALUE"""),"NO") -> NO | M98: =IFERROR(__xludf.DUMMYFUNCTION("""COMPUTED_VALUE"""),"Private Contractor") -> Private Contractor | N98: =IFERROR(__xludf.DUMMYFUNCTION("""COMPUTED_VALUE"""),"SCHINDLER") -> SCHINDLER | O98: =IFERROR(__xludf.DUMMYFUNCTION("""COMPUTED_VALUE"""),"YES") -> YES | P98: =IFERROR(__xludf.DUMMYFUNCTION("""COMPUTED_VALUE"""),"NO") -> NO | Q98: =IFERROR(__xludf.DUMMYFUNCTION("""COMPUTED_VALUE"""),"NO") -> NO | U98: =IFERROR(__xludf.DUMMYFUNCTION("""COMPUTED_VALUE"""),"Transit Center entrance (John St east of Broadway) to lower concourse for A/C/J/Z/2/3 & downtown 4/5 service and connection to WTC complex") -> Transit Center entrance (John St east of Broadway) to lower concourse for A/C/J/Z/2/3 & downtown 4/5 service and connection to WTC complex | V98: =IFERROR(__xludf.DUMMYFUNCTION("""COMPUTED_VALUE"""),"POINT (-74.00935 40.71033)") -> POINT (-74.00935 40.71033)
A99: =IFERROR(__xludf.DUMMYFUNCTION("""COMPUTED_VALUE"""),"34 St-Herald Sq") -> 34 St-Herald Sq | B99: =IFERROR(__xludf.DUMMYFUNCTION("""COMPUTED_VALUE"""),"Broadway Line") -> Broadway Line | C99: =IFERROR(__xludf.DUMMYFUNCTION("""COMPUTED_VALUE"""),"Manhattan") -> Manhattan | D99: =IFERROR(__xludf.DUMMYFUNCTION("""COMPUTED_VALUE"""),"Midtown") -> Midtown | E99: =IFERROR(__xludf.DUMMYFUNCTION("""COMPUTED_VALUE"""),6580.0) -> 6580 | F99: =IFERROR(__xludf.DUMMYFUNCTION("""COMPUTED_VALUE"""),2.5012549E7) -> 25012549 | G99: =IFERROR(__xludf.DUMMYFUNCTION("""COMPUTED_VALUE"""),3.0) -> 3 | H99: =IFERROR(__xludf.DUMMYFUNCTION("""COMPUTED_VALUE"""),"↗️") -> ↗️ | I99: =IFERROR(__xludf.DUMMYFUNCTION("""COMPUTED_VALUE"""),14960.0) -> 14960 | J99: =IFERROR(__xludf.DUMMYFUNCTION("""COMPUTED_VALUE"""),39460.0) -> 39460 | K99: =IFERROR(__xludf.DUMMYFUNCTION("""COMPUTED_VALUE"""),22.0) -> 22 | L99: =IFERROR(__xludf.DUMMYFUNCTION("""COMPUTED_VALUE"""),"YES") -> YES | M99: =IFERROR(__xludf.DUMMYFUNCTION("""COMPUTED_VALUE"""),"NYCT") -> NYCT | N99: =IFERROR(__xludf.DUMMYFUNCTION("""COMPUTED_VALUE"""),"FUJITEC") -> FUJITEC | O99: =IFERROR(__xludf.DUMMYFUNCTION("""COMPUTED_VALUE"""),"YES") -> YES | P99: =IFERROR(__xludf.DUMMYFUNCTION("""COMPUTED_VALUE"""),"NO") -> NO | Q99: =IFERROR(__xludf.DUMMYFUNCTION("""COMPUTED_VALUE"""),"NO") -> NO | R99: =IFERROR(__xludf.DUMMYFUNCTION("""COMPUTED_VALUE"""),"28'") -> 28' | S99: =IFERROR(__xludf.DUMMYFUNCTION("""COMPUTED_VALUE"""),109.0) -> 109 | T99: =IFERROR(__xludf.DUMMYFUNCTION("""COMPUTED_VALUE"""),600.0) -> 600 | U99: =IFERROR(__xludf.DUMMYFUNCTION("""COMPUTED_VALUE"""),"N/Q/R/W mezzanine to downtown B/D/F/M platform") -> N/Q/R/W mezzanine to downtown B/D/F/M platform | V99: =IFERROR(__xludf.DUMMYFUNCTION("""COMPUTED_VALUE"""),"POINT (-73.987526 40.750324)") -> POINT (-73.987526 40.750324)
A100: =IFERROR(__xludf.DUMMYFUNCTION("""COMPUTED_VALUE"""),"Intervale Av") -> Intervale Av | B100: =IFERROR(__xludf.DUMMYFUNCTION("""COMPUTED_VALUE"""),"White Plains Rd Line") -> White Plains Rd Line | C100: =IFERROR(__xludf.DUMMYFUNCTION("""COMPUTED_VALUE"""),"The Bronx") -> The Bronx | D100: =IFERROR(__xludf.DUMMYFUNCTION("""COMPUTED_VALUE"""),"Longwood") -> Longwood | E100: =IFERROR(__xludf.DUMMYFUNCTION("""COMPUTED_VALUE"""),3773.0) -> 3773 | F100: =IFERROR(__xludf.DUMMYFUNCTION("""COMPUTED_VALUE"""),535565.0) -> 535565 | G100: =IFERROR(__xludf.DUMMYFUNCTION("""COMPUTED_VALUE"""),377.0) -> 377 | H100: =IFERROR(__xludf.DUMMYFUNCTION("""COMPUTED_VALUE"""),"↗️") -> ↗️ | I100: =IFERROR(__xludf.DUMMYFUNCTION("""COMPUTED_VALUE"""),3773.0) -> 3773 | J100: =IFERROR(__xludf.DUMMYFUNCTION("""COMPUTED_VALUE"""),45721.0) -> 45721 | K100: =IFERROR(__xludf.DUMMYFUNCTION("""COMPUTED_VALUE"""),22.0) -> 22 | L100: =IFERROR(__xludf.DUMMYFUNCTION("""COMPUTED_VALUE"""),"YES") -> YES | M100: =IFERROR(__xludf.DUMMYFUNCTION("""COMPUTED_VALUE"""),"NYCT") -> NYCT | N100: =IFERROR(__xludf.DUMMYFUNCTION("""COMPUTED_VALUE"""),"KONE") -> KONE | O100: =IFERROR(__xludf.DUMMYFUNCTION("""COMPUTED_VALUE"""),"YES") -> YES | P100: =IFERROR(__xludf.DUMMYFUNCTION("""COMPUTED_VALUE"""),"YES") -> YES | Q100: =IFERROR(__xludf.DUMMYFUNCTION("""COMPUTED_VALUE"""),"NO") -> NO | R100: =IFERROR(__xludf.DUMMYFUNCTION("""COMPUTED_VALUE"""),"30'- 5/5in") -> 30'- 5/5in | S100: =IFERROR(__xludf.DUMMYFUNCTION("""COMPUTED_VALUE"""),111.0) -> 111 | T100: =IFERROR(__xludf.DUMMYFUNCTION("""COMPUTED_VALUE"""),24.0) -> 24 | U100: =IFERROR(__xludf.DUMMYFUNCTION("""COMPUTED_VALUE"""),"Westchester Ave & Intervale Ave (NE corner) to mezzanine") -> Westchester Ave & Intervale Ave (NE corner) to mezzanine | V100: =IFERROR(__xludf.DUMMYFUNCTION("""COMPUTED_VALUE"""),"POINT (-73.8966 40.822376)") -> POINT (-73.8966 40.822376)
...

Sheet Sheet5
A1: Equipment Code | B1: Elevator or Escalator | C1: Station Name | D1: Station Description | E1: Station Complex MRN | F1: Station Complex Description | G1: Subway Line | H1: Borough | I1: Original Installation Date | J1: Latest Installation Date | K1: Service Status Code | L1: Service Status | M1: Service Life | N1: NYCT Owned | O1: Maintained By | P1: Installer | Q1: Revenue Machine | R1: ADA Compliant | S1: Street Access | T1: Exposed to Weather | U1: Escalator Rise | V1: Elevator Rise | W1: Elevator Capacity | X1: Elevator Loading Class | Y1: Elevator Number of Landings | Z1: Escalator Number of Steps | AA1: Escalator Step Width | AB1: Elevator Direction Serviced | AC1: Elevator Order | AD1: Elevator Mezzanine 1 Access | AE1: Elevator Mezzanine 2 Access | AF1: Elevator Platform Access | AG1: Notes | AH1: Redundant Elevator | AI1: Redundant Elevator Street Access | AJ1: Redundant Elevator Mezzanine Access | AK1: Redundant Elevator Access Between Mezzanines | AL1: Redundant Elevator Platform Access | AM1: Alternative Route | AN1: Georeference
A2: ES600X | B2: Escalator | C2: LEXINGTONAV/53ST-QBL-E/M | D2: Lexington Av/53 St - Station | E2: 612 | F2: Lexington Av-53 St (E,M)/51 St (6) | G2: IND-D-QUEENSBLVD | H2: Manhattan | J2: 3 | K2: IFIS | L2: Installed-Functioning-In Service | M2: 22 | N2: NO | O2: Private Contractor | P2: AM | Q2: YES | S2: NO | T2: NO | AG2: 6/E/F mezzanine to 52 St & Lexington Av (NE corner). | AN2: POINT (-73.970924 40.75814)
A3: ES627 | B3: Escalator | C3: 34ST-HUDSONYARDS-FLS-7 | D3: 34 St-Hudson Yards - Station | E3: 471 | G3: IRT-CC-FLUSHING | H3: Manhattan | I3: 42260 | J3: 42260 | K3: IFIS | L3: Installed-Functioning-In Service | M3: 22 | N3: YES | O3: NYCT | P3: KONE | Q3: YES | S3: YES | T3: YES | U3: 30' | Z3: 110 | AA3: 24 | AG3: Hudson Blvd E (between 33 St & 34 St) to upper mezzanine | AN3: POINT (-74.00103 40.754982)
A4: ES377X | B4: Escalator | C4: FULTONST-8AV-A/C | D4: Fulton St - Station | E4: 628 | F4: Fulton St (A,C,J,Z,2,3,4,5) | G4: IND-A-8AV/FULTONST | H4: Manhattan | J4: 41110 | K4: IFIS | L4: Installed-Functioning-In Service | M4: 22 | N4: NO | O4: Private Contractor | P4: OTIS | Q4: YES | S4: NO | T4: NO | AG4: Broad St-bound J/Z platform to Nassau St (between Maiden Lane & John St) | AN4: POINT (-74.008354 40.70928)
